Workbook
Name \_A: #N/A
Name \0: #REF!
Name \0: #REF!
Name \1: #REF!
Name \1: #REF!
Name \2: #REF!
Name \2: #REF!
Name \3: #REF!
Name \4: #REF!
Name \5: #REF!
Name \6: #REF!
Name \A: #REF!
Name \A: #REF!
Name \APR: #REF!
Name \AUG: #REF!
Name \B: #REF!
Name \B: #REF!
Name \BCYTD: #REF!
Name \BRYTD: #REF!
Name \BSYTD: #REF!
Name \BTWO: #REF!
Name \BUYTD: #REF!
Name \C: #REF!
Name \c: #REF!
Name \CTWO: #REF!
Name \D: #REF!
Name \D: #REF!
Name \DEC: #REF!
Name \DTWO: #REF!
Name \E: #REF!
Name \E: #REF!
Name \F: #REF!
Name \F: #REF!
Name \FEB: #REF!
Name \G: #REF!
Name \g: #REF!
Name \H: #REF!
Name \I: #REF!
Name \I: #REF!
Name \J: #REF!
Name \JAN: #REF!
Name \K: #REF!
Name \L: #REF!
Name \M: #REF!
Name \MAR: #REF!
Name \MAY: #REF!
Name \N: #REF!
Name \NOV: #REF!
Name \O: #REF!
Name \O: #REF!
Name \OCT: #REF!
Name \p: #N/A
Name \p: #REF!
Name \Q: #REF!
Name \Q: #REF!
Name \R: #REF!
Name \r: #REF!
Name \S: #REF!
Name \S: #REF!
Name \SEP: #REF!

Sheet Parameter
C1: Budget 2027
C2: ASSUMPTION
B4: No | C4: Item Budget | D4: Parameter | E4: PIC
B5: 1 | C5: Inflation Rate | D5: 3.5%
B6: 2 | C6: Target Marketing Revenue | D6: Target Marketing Revenue that will be achieved for year 2027 | E6: Sales Division
B7: 3 | C7: Sales Cost | D7: Base on achievement Target Marketing Revenue | E7: Sales Division
B8: =B7+1 -> 4 | C8: Program Sales | D8: Base on Approved Program Sales | E8: Sales Division
B9: =B8+1 -> 5 | C9: Marketing Advertising & Promotion | D9: Marketing division must list the detail of planning activity during the next year, and the activity must be inline with the Target Marketing Revenue | E9: Marketing Division
B10: =B9+1 -> 6 | C10: Development Cost | D10: Development cost planning that will be allocated in 2027, inline with development schedule and vendor contract agreement | E10: Project Division
B11: 7 | C11: Employee Expenses
C12: MPP | D12: Base on approved MPP | E12: HC Divison
C13: MPP Cost | D13: Base on approved MPP | E13: Payroll Division
B14: 8 | C14: General & Administration Expenses | D14: Base on actual need | E14: ALL Division
B15: 9 | C15: Others Expenses | D15: Base on actual need | E15: ALL Division
B16: 10 | C16: Tax Expenses | D16: Base on Tax expense | E16: ALL Division
B17: 11 | C17: Corporate Event & Exhibition | D17: The Division must list the detail of planning activity during the next year, and the activity must be inline with the Corporate/Management Strategic | E17: Corporate Division
B18: =B17+1 -> 12 | C18: Finance Expenses | D18: Base on agreed Interest | E18: FA Division
B19: =B18+1 -> 13 | C19: Fixed Asset | D19: Base on actual need | E19: ALL Division
C20: Laptop/PC | D20: Specification base on IT Policy | E20: ALL Division
C21: Printer | D21: Specification base on IT Policy | E21: ALL Division
C22: Monitor PC | D22: Specification base on IT Policy | E22: ALL Division
C23: Projector Presentation | D23: Specification base on IT Policy | E23: ALL Division
C24: Others IT Equipment | D24: Specification base on IT Policy | E24: ALL Division
C25: Work Desk & Chair | D25: Specification base on GA Policy | E25: ALL Division
C26: Company/Operational Vehicle | D26: Specification base on GA Policy | E26: ALL Division
C27: Others Fixed Asset | D27: Specification base on GA Policy | E27: ALL Division

Sheet Fixed Asset
A2: Budget CAPEX (Fixed Asset)
A3: Comp Name
A4: Project
A5: Budget Year | B5: 2022
A7: BUDGET CAPEX REQUEST FORM
A9: No | B9: Employee Name | C9: Divison / Dept | D9: Fixed Asset Category | E9: Item Goods Description | F9: Periode | G9: Qty | J9: UoM | K9: Price / unit | L9: Curr | M9: Total Value Local Currency | N9: Justification | O9: Reason | P9: Competent Division | Q9: Procurement
G10: New | H10: Replace | I10: Total | P10: Review Result | Q10: Review Result
B11: Lembar isian Budget Capex | T11: Budget Capex Summary
A12: 1 | I12: =SUM(G12:H12) -> 0 | J12: set | L12: IDR | M12: =I12*K12 -> 0 | U12: 44197 | V12: 44228 | W12: 44256 | X12: 44287 | Y12: 44317 | Z12: 44348 | AA12: 44378 | AB12: 44409 | AC12: 44440 | AD12: 44470 | AE12: 44501 | AF12: 44531 | AG12: Total
A13: 2 | B13: Rudi | C13: Sales Marketing | D13: IT Hardware & Software | E13: Laptop for Vacant Inhouse Sales | F13: 44621 | G13: 1 | H13: 0 | I13: =SUM(G13:H13) -> 1 | J13: Set | K13: 8000000 | L13: IDR | M13: =I13*K13 -> 8000000 | N13: Must To Have | T13: Bangunan | U13: =SUMIFS($M:$M,$F:$F,U$12,$D:$D,$T13) -> 0 | V13: =SUMIFS($M:$M,$F:$F,V$12,$D:$D,$T13) -> 0 | W13: =SUMIFS($M:$M,$F:$F,W$12,$D:$D,$T13) -> 0 | X13: =SUMIFS($M:$M,$F:$F,X$12,$D:$D,$T13) -> 0 | Y13: =SUMIFS($M:$M,$F:$F,Y$12,$D:$D,$T13) -> 0 | Z13: =SUMIFS($M:$M,$F:$F,Z$12,$D:$D,$T13) -> 0 | AA13: =SUMIFS($M:$M,$F:$F,AA$12,$D:$D,$T13) -> 0 | AB13: =SUMIFS($M:$M,$F:$F,AB$12,$D:$D,$T13) -> 0 | ... AF13: =SUMIFS($M:$M,$F:$F,AF$12,$D:$D,$T13) -> 0 | AG13: =SUM(U13:AF13) -> 0
A14: 3 | I14: =SUM(G14:H14) -> 0 | L14: IDR | M14: =I14*K14 -> 0 | T14: Kendaraan Operasional | U14: =SUMIFS($M:$M,$F:$F,U$12,$D:$D,$T14) -> 0 | V14: =SUMIFS($M:$M,$F:$F,V$12,$D:$D,$T14) -> 0 | W14: =SUMIFS($M:$M,$F:$F,W$12,$D:$D,$T14) -> 0 | X14: =SUMIFS($M:$M,$F:$F,X$12,$D:$D,$T14) -> 0 | Y14: =SUMIFS($M:$M,$F:$F,Y$12,$D:$D,$T14) -> 0 | Z14: =SUMIFS($M:$M,$F:$F,Z$12,$D:$D,$T14) -> 0 | AA14: =SUMIFS($M:$M,$F:$F,AA$12,$D:$D,$T14) -> 0 | AB14: =SUMIFS($M:$M,$F:$F,AB$12,$D:$D,$T14) -> 0 | ... AF14: =SUMIFS($M:$M,$F:$F,AF$12,$D:$D,$T14) -> 0 | AG14: =SUM(U14:AF14) -> 0
A15: 4 | I15: =SUM(G15:H15) -> 0 | L15: IDR | M15: =I15*K15 -> 0 | T15: Peralatan Kantor | U15: =SUMIFS($M:$M,$F:$F,U$12,$D:$D,$T15) -> 0 | V15: =SUMIFS($M:$M,$F:$F,V$12,$D:$D,$T15) -> 0 | W15: =SUMIFS($M:$M,$F:$F,W$12,$D:$D,$T15) -> 0 | X15: =SUMIFS($M:$M,$F:$F,X$12,$D:$D,$T15) -> 0 | Y15: =SUMIFS($M:$M,$F:$F,Y$12,$D:$D,$T15) -> 0 | Z15: =SUMIFS($M:$M,$F:$F,Z$12,$D:$D,$T15) -> 0 | AA15: =SUMIFS($M:$M,$F:$F,AA$12,$D:$D,$T15) -> 0 | AB15: =SUMIFS($M:$M,$F:$F,AB$12,$D:$D,$T15) -> 0 | ... AF15: =SUMIFS($M:$M,$F:$F,AF$12,$D:$D,$T15) -> 0 | AG15: =SUM(U15:AF15) -> 0
A16: 5 | I16: =SUM(G16:H16) -> 0 | L16: IDR | M16: =I16*K16 -> 0 | T16: Furnitur dan Perlengkapan Kantor | U16: =SUMIFS($M:$M,$F:$F,U$12,$D:$D,$T16) -> 0 | V16: =SUMIFS($M:$M,$F:$F,V$12,$D:$D,$T16) -> 0 | W16: =SUMIFS($M:$M,$F:$F,W$12,$D:$D,$T16) -> 0 | X16: =SUMIFS($M:$M,$F:$F,X$12,$D:$D,$T16) -> 0 | Y16: =SUMIFS($M:$M,$F:$F,Y$12,$D:$D,$T16) -> 0 | Z16: =SUMIFS($M:$M,$F:$F,Z$12,$D:$D,$T16) -> 0 | AA16: =SUMIFS($M:$M,$F:$F,AA$12,$D:$D,$T16) -> 0 | AB16: =SUMIFS($M:$M,$F:$F,AB$12,$D:$D,$T16) -> 0 | ... AF16: =SUMIFS($M:$M,$F:$F,AF$12,$D:$D,$T16) -> 0 | AG16: =SUM(U16:AF16) -> 0
A17: 6 | I17: =SUM(G17:H17) -> 0 | L17: IDR | M17: =I17*K17 -> 0 | T17: IT Hardware & Software | U17: =SUMIFS($M:$M,$F:$F,U$12,$D:$D,$T17) -> 0 | V17: =SUMIFS($M:$M,$F:$F,V$12,$D:$D,$T17) -> 0 | W17: =SUMIFS($M:$M,$F:$F,W$12,$D:$D,$T17) -> 0 | X17: =SUMIFS($M:$M,$F:$F,X$12,$D:$D,$T17) -> 0 | Y17: =SUMIFS($M:$M,$F:$F,Y$12,$D:$D,$T17) -> 0 | Z17: =SUMIFS($M:$M,$F:$F,Z$12,$D:$D,$T17) -> 0 | AA17: =SUMIFS($M:$M,$F:$F,AA$12,$D:$D,$T17) -> 0 | AB17: =SUMIFS($M:$M,$F:$F,AB$12,$D:$D,$T17) -> 0 | ... AF17: =SUMIFS($M:$M,$F:$F,AF$12,$D:$D,$T17) -> 0 | AG17: =SUM(U17:AF17) -> 0
A18: 7 | I18: =SUM(G18:H18) -> 0 | L18: IDR | M18: =I18*K18 -> 0 | T18: Peralatan Lainnya | U18: =SUMIFS($M:$M,$F:$F,U$12,$D:$D,$T18) -> 0 | V18: =SUMIFS($M:$M,$F:$F,V$12,$D:$D,$T18) -> 0 | W18: =SUMIFS($M:$M,$F:$F,W$12,$D:$D,$T18) -> 0 | X18: =SUMIFS($M:$M,$F:$F,X$12,$D:$D,$T18) -> 0 | Y18: =SUMIFS($M:$M,$F:$F,Y$12,$D:$D,$T18) -> 0 | Z18: =SUMIFS($M:$M,$F:$F,Z$12,$D:$D,$T18) -> 0 | AA18: =SUMIFS($M:$M,$F:$F,AA$12,$D:$D,$T18) -> 0 | AB18: =SUMIFS($M:$M,$F:$F,AB$12,$D:$D,$T18) -> 0 | ... AF18: =SUMIFS($M:$M,$F:$F,AF$12,$D:$D,$T18) -> 0 | AG18: =SUM(U18:AF18) -> 0
A19: 8 | I19: =SUM(G19:H19) -> 0 | L19: IDR | M19: =I19*K19 -> 0 | U19: =SUM(U13:U18) -> 0 | V19: =SUM(V13:V18) -> 0 | W19: =SUM(W13:W18) -> 0 | X19: =SUM(X13:X18) -> 0 | Y19: =SUM(Y13:Y18) -> 0 | Z19: =SUM(Z13:Z18) -> 0 | AA19: =SUM(AA13:AA18) -> 0 | AB19: =SUM(AB13:AB18) -> 0 | ... AF19: =SUM(AF13:AF18) -> 0 | AG19: =SUM(U19:AF19) -> 0
A20: 9 | I20: =SUM(G20:H20) -> 0 | L20: IDR | M20: =I20*K20 -> 0
A21: 10 | I21: =SUM(G21:H21) -> 0 | L21: IDR | M21: =I21*K21 -> 0
A22: 11 | I22: =SUM(G22:H22) -> 0 | L22: IDR | M22: =I22*K22 -> 0
A23: 12 | I23: =SUM(G23:H23) -> 0 | L23: IDR | M23: =I23*K23 -> 0
A24: 13 | I24: =SUM(G24:H24) -> 0 | L24: IDR | M24: =I24*K24 -> 0 | T24: Depreciation of Capex
A25: 14 | I25: =SUM(G25:H25) -> 0 | L25: IDR | M25: =I25*K25 -> 0 | W25: =U12 -> 44197 | X25: =V12 -> 44228 | Y25: =W12 -> 44256 | Z25: =X12 -> 44287 | AA25: =Y12 -> 44317 | AB25: =Z12 -> 44348 | AC25: =AA12 -> 44378 | AD25: =AB12 -> 44409 | ... AI25: =AG12 -> Total
A26: 15 | I26: =SUM(G26:H26) -> 0 | L26: IDR | M26: =I26*K26 -> 0 | T26: Biaya Penyusutan Bangunan | U26: Bangunan | AI26: =SUM(W26:AH26) -> 0
A27: 16 | I27: =SUM(G27:H27) -> 0 | L27: IDR | M27: =I27*K27 -> 0 | T27: Biaya Penyusutan Kendaraan Kantor | U27: Kendaraan Operasional | AI27: =SUM(W27:AH27) -> 0
A28: 17 | I28: =SUM(G28:H28) -> 0 | L28: IDR | M28: =I28*K28 -> 0 | T28: Biaya Penyusutan Inventaris Kantor | U28: Peralatan Kantor | AI28: =SUM(W28:AH28) -> 0
A29: 18 | I29: =SUM(G29:H29) -> 0 | L29: IDR | M29: =I29*K29 -> 0 | T29: Biaya Penyusutan Inventaris Kantor | U29: Furnitur dan Perlengkapan Kantor
A30: 19 | I30: =SUM(G30:H30) -> 0 | L30: IDR | M30: =I30*K30 -> 0 | T30: Biaya Penyusutan Inventaris Kantor | U30: IT Hardware & Software
A31: 20 | I31: =SUM(G31:H31) -> 0 | L31: IDR | M31: =I31*K31 -> 0 | T31: Biaya Penyusutan Inventaris Kantor | U31: Peralatan Lainnya
E32: TOTAL | L32: IDR | M32: =SUM(M12:M31) -> 8000000
B34: Create by, | D34: Competent Division, | I34: Review by, | O34: Approved by,
B38: Name : ____________________ | D38: Name : ____________________ | E38: Name : ____________________ | I38: Name : ____________________ | O38: Name : __________________
B39: ="Division : "&" "&B5 -> Division : 2022 | D39: Comp Div Name : ____________ | E39: Comp Div Name : ____________ | I39: Head of FA | O39: Director
B40: =B3 -> 0 | D40: =B3 -> 0 | E40: =B3 -> 0 | I40: =B3 -> 0 | O40: =B3 -> 0

Sheet Attachment1
A1: KEBIJAKAN No : PM/TRIN/HC/01
A60: Business Trip
A61: Gol / Jabatan | B61: Hotels | C61: Uang Saku & Uang Makan Lum Sum | E61: Transport
A62: Commissary
A63: BOD / BOC | B63: 1650000 | C63: 500000
A64: General Manager | B64: 900000 | C64: 400000
A65: Manager | B65: 750000 | C65: 300000
A66: Supervisor | B66: 600000 | C66: 250000
A67: Staff | B67: 500000 | C67: 150000
A68: Contract

Sheet SUM Actual vs Budget
A1: SUMMARY BUDGET
A2: ENTITAS: | B2: PT Perintis Triniti Properti Tbk
A3: PROJECT | B3: Lampung-Holdwell Business Park
A4: BUDGET YEARS | B4: BUDGET 2023
A5: MONTH: | B5: YTD SEP
B7: Description | C7: 2020 | D7: BUDGET | E7: ACTUAL | F7: Budget Realization | H7: BUDGET | I7: Budget 2022 vs Budget 2023 | J7: Budget 2023 vs Actual 2022 | L7: BUDGET | N7: BUDGET
C8: ACTUAL | D8: 2022 | E8: 2022 | F8: 2022 | H8: 2023 | I8: B2022 vs B2023 | J8: B2023 vs A2022 | L8: 2024 | N8: 2025
C9: YTD DEC | D9: YTD DEC | E9: YTD DEC | F9: =E9 -> YTD DEC | H9: YTD DEC | I9: YTD DEC | J9: YTD DEC | L9: YTD DEC | N9: YTD DEC
B11: SALES
A13: 1 | B13: in SQM
A14: 2 | B14: ='Target Marketing Revenue'!B54 -> 0 | C14: 0 | F14: =IFERROR(E14/D14,0) -> 0 | H14: =HLOOKUP(H$9,'Target Marketing Revenue'!$E$53:$P$61,$A14,FALSE) -> 0 | I14: =IFERROR(H14/D14-1,0) -> 0 | J14: =IFERROR(H14/E14-1,0) -> 0
A15: 3 | B15: ='Target Marketing Revenue'!B55 -> 0 | F15: =IFERROR(E15/D15,0) -> 0 | H15: =HLOOKUP(H$9,'Target Marketing Revenue'!$E$53:$P$61,$A15,FALSE) -> 0 | I15: =IFERROR(H15/D15-1,0) -> 0 | J15: =IFERROR(H15/E15-1,0) -> 0
A16: 4 | B16: ='Target Marketing Revenue'!B56 -> 0 | F16: =IFERROR(E16/D16,0) -> 0 | H16: =HLOOKUP(H$9,'Target Marketing Revenue'!$E$53:$P$61,$A16,FALSE) -> 0 | I16: =IFERROR(H16/D16-1,0) -> 0 | J16: =IFERROR(H16/E16-1,0) -> 0
A17: 5 | B17: ='Target Marketing Revenue'!B57 -> 0 | C17: 0 | F17: =IFERROR(E17/D17,0) -> 0 | H17: =HLOOKUP(H$9,'Target Marketing Revenue'!$E$53:$P$61,$A17,FALSE) -> 0 | I17: =IFERROR(H17/D17-1,0) -> 0 | J17: =IFERROR(H17/E17-1,0) -> 0
A18: 6 | B18: ='Target Marketing Revenue'!B58 -> 0 | C18: 0 | F18: =IFERROR(E18/D18,0) -> 0 | H18: =HLOOKUP(H$9,'Target Marketing Revenue'!$E$53:$P$61,$A18,FALSE) -> 0 | I18: =IFERROR(H18/D18-1,0) -> 0 | J18: =IFERROR(H18/E18-1,0) -> 0
C19: 0
B20: ="TOTAL"&" "&B11&" "&B13 -> TOTAL SALES in SQM | C20: =SUM(C14:C19) -> 0 | D20: =SUM(D14:D19) -> 0 | E20: =SUM(E14:E19) -> 0 | F20: =IFERROR(E20/D20,0) -> 0 | H20: =SUM(H14:H19) -> 0 | I20: =IFERROR(H20/D20-1,0) -> 0 | J20: =IFERROR(H20/E20-1,0) -> 0 | L20: =SUM(L14:L19) -> 0 | N20: =SUM(N14:N19) -> 0
A22: 1 | B22: MARKETING REVENUE (in Rp Bio)
A23: 2 | B23: ='Target Marketing Revenue'!B64 -> 0 | C23: 0 | F23: =IFERROR(E23/D23,0) -> 0 | H23: =HLOOKUP(H$9,'Target Marketing Revenue'!$E$63:$P$71,$A23,FALSE) -> 0 | I23: =IFERROR(H23/D23-1,0) -> 0 | J23: =IFERROR(H23/E23-1,0) -> 0
A24: 3 | B24: ='Target Marketing Revenue'!B65 -> 0 | F24: =IFERROR(E24/D24,0) -> 0 | H24: =HLOOKUP(H$9,'Target Marketing Revenue'!$E$63:$P$71,$A24,FALSE) -> 0 | I24: =IFERROR(H24/D24-1,0) -> 0 | J24: =IFERROR(H24/E24-1,0) -> 0
A25: 4 | B25: ='Target Marketing Revenue'!B66 -> 0 | F25: =IFERROR(E25/D25,0) -> 0 | H25: =HLOOKUP(H$9,'Target Marketing Revenue'!$E$63:$P$71,$A25,FALSE) -> 0 | I25: =IFERROR(H25/D25-1,0) -> 0 | J25: =IFERROR(H25/E25-1,0) -> 0
A26: 5 | B26: ='Target Marketing Revenue'!B67 -> 0 | C26: 0 | F26: =IFERROR(E26/D26,0) -> 0 | H26: =HLOOKUP(H$9,'Target Marketing Revenue'!$E$63:$P$71,$A26,FALSE) -> 0 | I26: =IFERROR(H26/D26-1,0) -> 0 | J26: =IFERROR(H26/E26-1,0) -> 0
A27: 6 | B27: ='Target Marketing Revenue'!B68 -> 0 | C27: 0 | F27: =IFERROR(E27/D27,0) -> 0 | H27: =HLOOKUP(H$9,'Target Marketing Revenue'!$E$63:$P$71,$A27,FALSE) -> 0 | I27: =IFERROR(H27/D27-1,0) -> 0 | J27: =IFERROR(H27/E27-1,0) -> 0
A28: 4 | C28: 0
B29: ="TOTAL"&" "&B22 -> TOTAL MARKETING REVENUE (in Rp Bio) | C29: =SUM(C23:C28) -> 0 | D29: =SUM(D23:D28) -> 0 | E29: =SUM(E23:E28) -> 0 | F29: =IFERROR(E29/D29,0) -> 0 | H29: =SUM(H23:H28) -> 0 | I29: =IFERROR(H29/D29-1,0) -> 0 | J29: =IFERROR(H29/E29-1,0) -> 0 | L29: =SUM(L23:L28) -> 0 | N29: =SUM(N23:N28) -> 0
B31: DEVELOPMENT & OPERATIONAL COST
B32: PROJECT COST
B33: Land Cost | C33: 0
A34: 1 | B34: Land Acquisition Cost | F34: =IFERROR(E34/D34,0) -> 0 | H34: =HLOOKUP($H$9,'Dev&Land Budget Plan Cost'!$M$73:$X$84,'Dev&Land Budget Plan Cost'!$C74,FALSE) -> 0 | I34: =IFERROR(H34/D34-1,0) -> 0 | J34: =IFERROR(H34/E34-1,0) -> 0
A35: 2 | B35: Land Preparation Cost | F35: =IFERROR(E35/D35,0) -> 0 | H35: =HLOOKUP($H$9,'Dev&Land Budget Plan Cost'!$M$73:$X$84,'Dev&Land Budget Plan Cost'!$C75,FALSE) -> 0 | I35: =IFERROR(H35/D35-1,0) -> 0 | J35: =IFERROR(H35/E35-1,0) -> 0
B36: Taxes on Land Acquisition | F36: =IFERROR(E36/D36,0) -> 0 | I36: =IFERROR(H36/D36-1,0) -> 0 | J36: =IFERROR(H36/E36-1,0) -> 0
B37: Hard Cost | C37: 0
A38: 3 | B38: Development Cost | F38: =IFERROR(E38/D38,0) -> 0 | I38: =IFERROR(H38/D38-1,0) -> 0 | J38: =IFERROR(H38/E38-1,0) -> 0
B39: Preliminaries | F39: =IFERROR(E39/D39,0) -> 0 | H39: =HLOOKUP($H$9,'Dev&Land Budget Plan Cost'!$M$73:$X$84,'Dev&Land Budget Plan Cost'!$C76,FALSE) -> 0 | I39: =IFERROR(H39/D39-1,0) -> 0 | J39: =IFERROR(H39/E39-1,0) -> 0
B40: Pre-Construction | F40: =IFERROR(E40/D40,0) -> 0 | H40: =HLOOKUP($H$9,'Dev&Land Budget Plan Cost'!$M$73:$X$84,'Dev&Land Budget Plan Cost'!$C77,FALSE) -> 0 | I40: =IFERROR(H40/D40-1,0) -> 0 | J40: =IFERROR(H40/E40-1,0) -> 0
B41: Construction Cost | F41: =IFERROR(E41/D41,0) -> 0 | H41: =HLOOKUP($H$9,'Dev&Land Budget Plan Cost'!$M$73:$X$84,'Dev&Land Budget Plan Cost'!$C78,FALSE) -> 0 | I41: =IFERROR(H41/D41-1,0) -> 0 | J41: =IFERROR(H41/E41-1,0) -> 0
B42: Parking Construction Cost | F42: =IFERROR(E42/D42,0) -> 0 | H42: =HLOOKUP($H$9,'Dev&Land Budget Plan Cost'!$M$73:$X$84,'Dev&Land Budget Plan Cost'!$C79,FALSE) -> 0 | I42: =IFERROR(H42/D42-1,0) -> 0 | J42: =IFERROR(H42/E42-1,0) -> 0
B43: Infrastructure Cost | F43: =IFERROR(E43/D43,0) -> 0 | H43: =HLOOKUP($H$9,'Dev&Land Budget Plan Cost'!$M$73:$X$84,'Dev&Land Budget Plan Cost'!$C80,FALSE) -> 0 | I43: =IFERROR(H43/D43-1,0) -> 0 | J43: =IFERROR(H43/E43-1,0) -> 0
B44: Facilities Construction Cost | F44: =IFERROR(E44/D44,0) -> 0 | H44: =HLOOKUP($H$9,'Dev&Land Budget Plan Cost'!$M$73:$X$84,'Dev&Land Budget Plan Cost'!$C81,FALSE) -> 0 | I44: =IFERROR(H44/D44-1,0) -> 0 | J44: =IFERROR(H44/E44-1,0) -> 0
B45: Main Gate Construction Cost | F45: =IFERROR(E45/D45,0) -> 0 | H45: =HLOOKUP($H$9,'Dev&Land Budget Plan Cost'!$M$73:$X$84,'Dev&Land Budget Plan Cost'!$C82,FALSE) -> 0 | I45: =IFERROR(H45/D45-1,0) -> 0 | J45: =IFERROR(H45/E45-1,0) -> 0
F46: =IFERROR(E46/D46,0) -> 0 | I46: =IFERROR(H46/D46-1,0) -> 0 | J46: =IFERROR(H46/E46-1,0) -> 0
B47: Soft Cost | C47: 0
A48: 7 | B48: Legal, License & Permits | F48: =IFERROR(E48/D48,0) -> 0 | H48: =HLOOKUP($H$9,'Dev&Land Budget Plan Cost'!$M$73:$X$84,'Dev&Land Budget Plan Cost'!$C83,FALSE) -> 0 | I48: =IFERROR(H48/D48-1,0) -> 0 | J48: =IFERROR(H48/E48-1,0) -> 0
A49: 8 | B49: Design & Professional Fees | F49: =IFERROR(E49/D49,0) -> 0 | H49: =HLOOKUP($H$9,'Dev&Land Budget Plan Cost'!$M$73:$X$84,'Dev&Land Budget Plan Cost'!$C84,FALSE) -> 0 | I49: =IFERROR(H49/D49-1,0) -> 0 | J49: =IFERROR(H49/E49-1,0) -> 0
B51: Total Project Cost (in Rp Bio) | C51: =SUM(C33:C50) -> 0 | D51: =SUM(D33:D50) -> 0 | E51: =SUM(E33:E50) -> 0 | F51: =IFERROR(E51/D51,0) -> 0 | H51: =SUM(H33:H50) -> 0 | I51: =IFERROR(H51/D51-1,0) -> 0 | J51: =IFERROR(H51/E51-1,0) -> 0 | L51: =SUM(L33:L50) -> 0 | N51: =SUM(N33:N50) -> 0
B53: Sales & Marketing costs (in Rp Bio)
A54: 6 | B54: Sales Commission | C54: 0 | F54: =IFERROR(E54/D54,0) -> 0 | H54: =HLOOKUP($H$9,'Budget Sales Cost'!$C$40:$N$43,4,FALSE) -> 0 | I54: =IFERROR(H54/D54-1,0) -> 0 | J54: =IFERROR(H54/E54-1,0) -> 0
B55: Advertising & Promotions | C55: =SUM(#REF!) -> #REF! | F55: =IFERROR(E55/D55,0) -> 0 | H55: =HLOOKUP($H$9,'Budget Marketing Activity'!$F$115:$Q$116,2,FALSE) -> 0 | I55: =IFERROR(H55/D55-1,0) -> 0 | J55: =IFERROR(H55/E55-1,0) -> 0
B56: Total Sales & Marketing Costs (in Rp Bio) | C56: =C54+C55 -> #REF! | D56: =D54+D55 -> 0 | E56: =E54+E55 -> 0 | F56: =IFERROR(E56/D56,0) -> 0 | H56: =H54+H55 -> 0 | I56: =IFERROR(H56/D56-1,0) -> 0 | J56: =IFERROR(H56/E56-1,0) -> 0 | L56: =L54+L55 -> 0 | N56: =N54+N55 -> 0
B57: Sales & Marketing cost to Total Sales Ratio | C57: =C56/C29 -> #REF! | D57: =D56/D29 -> #DIV/0! | E57: =E56/E29 -> #DIV/0! | H57: =H56/H29 -> #DIV/0! | I57: =I56/I29 -> #DIV/0! | J57: =J56/J29 -> #DIV/0! | L57: =L56/L29 -> #DIV/0! | N57: =N56/N29 -> #DIV/0!
B58: Employee & Operational Expenses (in Rp. Bio)
A59: 8 | B59: Employee Expenses | C59: 0 | F59: =IFERROR(E59/D59,0) -> 0 | I59: =IFERROR(H59/D59-1,0) -> 0 | J59: =IFERROR(H59/E59-1,0) -> 0
A60: 9 | B60: General & Administration Expenses | C60: 0 | F60: =IFERROR(E60/D60,0) -> 0 | H60: =HLOOKUP($H$9,'Budget GnA'!C22:N33,'Budget GnA'!A23,FALSE) -> 0 | I60: =IFERROR(H60/D60-1,0) -> 0 | J60: =IFERROR(H60/E60-1,0) -> 0
A61: 10 | B61: Others Expenses | C61: 0 | F61: =IFERROR(E61/D61,0) -> 0 | H61: =HLOOKUP($H$9,'Budget Corp Event Exihibition'!$F$47:$Q$49,2,FALSE) -> 0 | I61: =IFERROR(H61/D61-1,0) -> 0 | J61: =IFERROR(H61/E61-1,0) -> 0
B62: Finance Expense (Interest Loan) | F62: =IFERROR(E62/D62,0) -> 0 | I62: =IFERROR(H62/D62-1,0) -> 0 | J62: =IFERROR(H62/E62-1,0) -> 0
A63: 11 | B63: Taxes | F63: =IFERROR(E63/D63,0) -> 0 | I63: =IFERROR(H63/D63-1,0) -> 0 | J63: =IFERROR(H63/E63-1,0) -> 0
B64: Total Employee Expense & Operational (in Rp Bio) | C64: =SUM(C59:C61) -> 0 | D64: =SUM(D59:D63) -> 0 | E64: =SUM(E59:E63) -> 0 | F64: =IFERROR(E64/D64,0) -> 0 | H64: =SUM(H59:H61) -> 0 | I64: =IFERROR(H64/D64-1,0) -> 0 | J64: =IFERROR(H64/E64-1,0) -> 0 | L64: =SUM(L59:L61) -> 0 | N64: =SUM(N59:N61) -> 0
B66: Purchases of fixed assets | F66: =IFERROR(E66/D66,0) -> 0 | H66: =' Budget Fixed Asset'!#REF! -> #REF! | I66: =IFERROR(H66/D66-1,0) -> 0 | J66: =IFERROR(H66/E66-1,0) -> 0
B67: Total Purchase Fixed Assets (in Rp Bio) | C67: =SUM(C66) -> 0 | D67: =SUM(D66) -> 0 | E67: =SUM(E66) -> 0 | F67: =IFERROR(E67/D67,0) -> 0 | H67: =SUM(H66) -> #REF! | I67: =IFERROR(H67/D67-1,0) -> 0 | J67: =IFERROR(H67/E67-1,0) -> 0 | L67: =SUM(L66) -> 0 | N67: =SUM(N66) -> 0
B69: TOTAL ALL COST (in Rp Bio) | C69: =C51+C56+C64+C67 -> #REF! | D69: =D51+D56+D64+D67 -> 0 | E69: =E51+E56+E64+E67 -> 0 | F69: =IFERROR(E69/D69,0) -> 0 | H69: =H51+H56+H64+H67 -> #REF! | I69: =IFERROR(H69/D69-1,0) -> 0 | J69: =IFERROR(H69/E69-1,0) -> 0 | L69: =L51+L56+L64+L67 -> 0 | N69: =N51+N56+N64+N67 -> 0

Sheet SUMMARY BUDGET
A1: SUMMARY TARGET MARKETING REVENEUE & BUDGET COST
A2: ENTITAS: | B2: Pilih Perusahaan
A3: PROJECT | B3: Pilih Project
A4: BUDGET YEARS | B4: BUDGET 2027
A5: MONTH: | B5: YTD SEP
B7: Description | C7: 2020 | D7: BUDGET | E7: ACTUAL | F7: Budget Realization | H7: BUDGET | I7: Budget 2026 vs Budget 2027 | J7: Budget 2027 vs Actual 2026
C8: ACTUAL | D8: 2026 | E8: 2026 | F8: 2026 | H8: 2027 | I8: B2026 vs B2027 | J8: B2027 vs A2026
C9: YTD DEC | D9: YTD DEC | E9: YTD DEC | F9: =E9 -> YTD DEC | H9: YTD DEC | I9: YTD DEC | J9: YTD DEC
B10: TARGET MARKETING REVENUE (in Unit)
A12: 2 | B12: ='Target Marketing Revenue'!B54 -> 0 | F12: =IFERROR(E12/D12,0) -> 0 | H12: =HLOOKUP(H$9,'Target Marketing Revenue'!$E$42:$P$51,$A12,FALSE) -> 0 | I12: =IFERROR(H12/D12-1,0) -> 0 | J12: =IFERROR(H12/E12-1,0) -> 0
A13: 3 | B13: ='Target Marketing Revenue'!B55 -> 0 | F13: =IFERROR(E13/D13,0) -> 0 | H13: =HLOOKUP(H$9,'Target Marketing Revenue'!$E$42:$P$51,$A13,FALSE) -> 0 | I13: =IFERROR(H13/D13-1,0) -> 0 | J13: =IFERROR(H13/E13-1,0) -> 0
A14: 4 | B14: ='Target Marketing Revenue'!B56 -> 0 | F14: =IFERROR(E14/D14,0) -> 0 | H14: =HLOOKUP(H$9,'Target Marketing Revenue'!$E$42:$P$51,$A14,FALSE) -> 0 | I14: =IFERROR(H14/D14-1,0) -> 0 | J14: =IFERROR(H14/E14-1,0) -> 0
A15: 5 | B15: ='Target Marketing Revenue'!B57 -> 0 | F15: =IFERROR(E15/D15,0) -> 0 | H15: =HLOOKUP(H$9,'Target Marketing Revenue'!$E$42:$P$51,$A15,FALSE) -> 0 | I15: =IFERROR(H15/D15-1,0) -> 0 | J15: =IFERROR(H15/E15-1,0) -> 0
A16: 6 | B16: ='Target Marketing Revenue'!B58 -> 0 | F16: =IFERROR(E16/D16,0) -> 0 | H16: =HLOOKUP(H$9,'Target Marketing Revenue'!$E$42:$P$51,$A16,FALSE) -> 0 | I16: =IFERROR(H16/D16-1,0) -> 0 | J16: =IFERROR(H16/E16-1,0) -> 0
B17: TOTAL TARGET MARKETING REVENUE (in Unit) | C17: =SUM(C12:C16) -> 0 | D17: =SUM(D12:D16) -> 0 | E17: =SUM(E12:E16) -> 0 | F17: =IFERROR(E17/D17,0) -> 0 | H17: =SUM(H12:H16) -> 0 | I17: =IFERROR(H17/D17-1,0) -> 0 | J17: =IFERROR(H17/E17-1,0) -> 0
B19: TARGET MARKETING REVENUE (in Rp Bio)
A20: 2 | C20: 0 | F20: =IFERROR(E20/D20,0) -> 0 | H20: =HLOOKUP(H$9,'Target Marketing Revenue'!$E$63:$P$71,$A20,FALSE) -> 0 | I20: =IFERROR(H20/D20-1,0) -> 0 | J20: =IFERROR(H20/E20-1,0) -> 0
A21: 3 | B21: ='Target Marketing Revenue'!B64 -> 0 | F21: =IFERROR(E21/D21,0) -> 0 | H21: =HLOOKUP(H$9,'Target Marketing Revenue'!$E$63:$P$71,$A21,FALSE) -> 0 | I21: =IFERROR(H21/D21-1,0) -> 0 | J21: =IFERROR(H21/E21-1,0) -> 0
A22: 4 | B22: ='Target Marketing Revenue'!B65 -> 0 | F22: =IFERROR(E22/D22,0) -> 0 | H22: =HLOOKUP(H$9,'Target Marketing Revenue'!$E$63:$P$71,$A22,FALSE) -> 0 | I22: =IFERROR(H22/D22-1,0) -> 0 | J22: =IFERROR(H22/E22-1,0) -> 0
A23: 5 | B23: ='Target Marketing Revenue'!B66 -> 0 | C23: 0 | F23: =IFERROR(E23/D23,0) -> 0 | H23: =HLOOKUP(H$9,'Target Marketing Revenue'!$E$63:$P$71,$A23,FALSE) -> 0 | I23: =IFERROR(H23/D23-1,0) -> 0 | J23: =IFERROR(H23/E23-1,0) -> 0
A24: 6 | B24: ='Target Marketing Revenue'!B67 -> 0 | C24: 0 | F24: =IFERROR(E24/D24,0) -> 0 | H24: =HLOOKUP(H$9,'Target Marketing Revenue'!$E$63:$P$71,$A24,FALSE) -> 0 | I24: =IFERROR(H24/D24-1,0) -> 0 | J24: =IFERROR(H24/E24-1,0) -> 0
B25: TOTAL TARGET MARKETING REVENUE (in Rp Bio) | C25: =SUM(C19:C24) -> 0 | D25: =SUM(D19:D24) -> 0 | E25: =SUM(E19:E24) -> 0 | F25: =IFERROR(E25/D25,0) -> 0 | H25: =SUM(H19:H24) -> 0 | I25: =IFERROR(H25/D25-1,0) -> 0 | J25: =IFERROR(H25/E25-1,0) -> 0
B27: DEVELOPMENT & OPERATIONAL COST
B28: PROJECT COST
B29: Land Cost | C29: 0 | D29: =SUM(D30:D32) -> 0 | E29: =SUM(E30:E32) -> 0 | H29: =SUM(H30:H32) -> 0
A30: 1 | B30: Land Acquisition Cost | F30: =IFERROR(E30/D30,0) -> 0 | H30: =HLOOKUP($H$9,'Dev&Land Budget Plan Cost'!$M$73:$X$84,'Dev&Land Budget Plan Cost'!$C74,FALSE) -> 0 | I30: =IFERROR(H30/D30-1,0) -> 0 | J30: =IFERROR(H30/E30-1,0) -> 0
A31: 2 | B31: Land Preparation Cost | F31: =IFERROR(E31/D31,0) -> 0 | H31: =HLOOKUP($H$9,'Dev&Land Budget Plan Cost'!$M$73:$X$84,'Dev&Land Budget Plan Cost'!$C75,FALSE) -> 0 | I31: =IFERROR(H31/D31-1,0) -> 0 | J31: =IFERROR(H31/E31-1,0) -> 0
B32: Taxes on Land Acquisition | F32: =IFERROR(E32/D32,0) -> 0 | I32: =IFERROR(H32/D32-1,0) -> 0 | J32: =IFERROR(H32/E32-1,0) -> 0
B33: Hard Cost | C33: 0 | D33: =SUM(D34:D41) -> 0 | E33: =SUM(E34:E41) -> 0 | H33: =SUM(H34:H41) -> 0
A34: 3 | B34: Development Cost | F34: =IFERROR(E34/D34,0) -> 0 | I34: =IFERROR(H34/D34-1,0) -> 0 | J34: =IFERROR(H34/E34-1,0) -> 0
B35: Preliminaries | F35: =IFERROR(E35/D35,0) -> 0 | H35: =HLOOKUP($H$9,'Dev&Land Budget Plan Cost'!$M$73:$X$84,'Dev&Land Budget Plan Cost'!$C76,FALSE) -> 0 | I35: =IFERROR(H35/D35-1,0) -> 0 | J35: =IFERROR(H35/E35-1,0) -> 0
B36: Pre-Construction | F36: =IFERROR(E36/D36,0) -> 0 | H36: =HLOOKUP($H$9,'Dev&Land Budget Plan Cost'!$M$73:$X$84,'Dev&Land Budget Plan Cost'!$C77,FALSE) -> 0 | I36: =IFERROR(H36/D36-1,0) -> 0 | J36: =IFERROR(H36/E36-1,0) -> 0
B37: Construction Cost | F37: =IFERROR(E37/D37,0) -> 0 | H37: =HLOOKUP($H$9,'Dev&Land Budget Plan Cost'!$M$73:$X$84,'Dev&Land Budget Plan Cost'!$C78,FALSE) -> 0 | I37: =IFERROR(H37/D37-1,0) -> 0 | J37: =IFERROR(H37/E37-1,0) -> 0
B38: Parking Construction Cost | F38: =IFERROR(E38/D38,0) -> 0 | H38: =HLOOKUP($H$9,'Dev&Land Budget Plan Cost'!$M$73:$X$84,'Dev&Land Budget Plan Cost'!$C79,FALSE) -> 0 | I38: =IFERROR(H38/D38-1,0) -> 0 | J38: =IFERROR(H38/E38-1,0) -> 0
B39: Infrastructure Cost | F39: =IFERROR(E39/D39,0) -> 0 | H39: =HLOOKUP($H$9,'Dev&Land Budget Plan Cost'!$M$73:$X$84,'Dev&Land Budget Plan Cost'!$C80,FALSE) -> 0 | I39: =IFERROR(H39/D39-1,0) -> 0 | J39: =IFERROR(H39/E39-1,0) -> 0
B40: Facilities Construction Cost | F40: =IFERROR(E40/D40,0) -> 0 | H40: =HLOOKUP($H$9,'Dev&Land Budget Plan Cost'!$M$73:$X$84,'Dev&Land Budget Plan Cost'!$C81,FALSE) -> 0 | I40: =IFERROR(H40/D40-1,0) -> 0 | J40: =IFERROR(H40/E40-1,0) -> 0
B41: Main Gate Construction Cost | F41: =IFERROR(E41/D41,0) -> 0 | H41: =HLOOKUP($H$9,'Dev&Land Budget Plan Cost'!$M$73:$X$84,'Dev&Land Budget Plan Cost'!$C82,FALSE) -> 0 | I41: =IFERROR(H41/D41-1,0) -> 0 | J41: =IFERROR(H41/E41-1,0) -> 0
F42: =IFERROR(E42/D42,0) -> 0 | I42: =IFERROR(H42/D42-1,0) -> 0 | J42: =IFERROR(H42/E42-1,0) -> 0
B43: Soft Cost | C43: 0 | D43: =SUM(D44:D45) -> 0 | E43: =SUM(E44:E45) -> 0 | H43: =SUM(H44:H45) -> 0
A44: 7 | B44: Legal, License & Permits | F44: =IFERROR(E44/D44,0) -> 0 | H44: =HLOOKUP($H$9,'Dev&Land Budget Plan Cost'!$M$73:$X$84,'Dev&Land Budget Plan Cost'!$C83,FALSE) -> 0 | I44: =IFERROR(H44/D44-1,0) -> 0 | J44: =IFERROR(H44/E44-1,0) -> 0
A45: 8 | B45: Design & Professional Fees | F45: =IFERROR(E45/D45,0) -> 0 | H45: =HLOOKUP($H$9,'Dev&Land Budget Plan Cost'!$M$73:$X$84,'Dev&Land Budget Plan Cost'!$C84,FALSE) -> 0 | I45: =IFERROR(H45/D45-1,0) -> 0 | J45: =IFERROR(H45/E45-1,0) -> 0
B47: Total Project Cost (in Rp Bio) | C47: =SUM(C29:C46) -> 0 | D47: =SUM(D29,D33,D43) -> 0 | E47: =SUM(E29,E33,E43) -> 0 | F47: =IFERROR(E47/D47,0) -> 0 | H47: =SUM(H29,H33,H43) -> 0 | I47: =IFERROR(H47/D47-1,0) -> 0 | J47: =IFERROR(H47/E47-1,0) -> 0
B49: Sales & Marketing costs (in Rp Bio)
A50: 6 | B50: Sales Cost | C50: 0 | F50: =IFERROR(E50/D50,0) -> 0 | H50: =HLOOKUP($H$9,'Budget Sales Cost'!$C$40:$N$43,4,FALSE) -> 0 | I50: =IFERROR(H50/D50-1,0) -> 0 | J50: =IFERROR(H50/E50-1,0) -> 0
B51: Advertising & Promotions | C51: =SUM(#REF!) -> #REF! | F51: =IFERROR(E51/D51,0) -> 0 | H51: =HLOOKUP($H$9,'Budget Marketing Activity'!$F$115:$Q$116,2,FALSE) -> 0 | I51: =IFERROR(H51/D51-1,0) -> 0 | J51: =IFERROR(H51/E51-1,0) -> 0
B52: Program Sales | D52: =SUM(D53:D58) -> 0 | E52: =SUM(E53:E58) -> 0 | F52: =IFERROR(E52/D52,0) -> 0 | H52: =SUM(H53:H58) -> 0 | I52: =IFERROR(H52/D52-1,0) -> 0 | J52: =IFERROR(H52/E52-1,0) -> 0
B53: ='Budget Program Sales'!B10 -> SUBSIDI BOOKING FEE | F53: =IFERROR(E53/D53,0) -> 0 | H53: =HLOOKUP($H$9,'Budget Program Sales'!$C$26:$N$35,2,FALSE) -> 0 | I53: =IFERROR(H53/D53-1,0) -> 0 | J53: =IFERROR(H53/E53-1,0) -> 0
B54: ='Budget Program Sales'!B11 -> SUBSIDI DOWN PAYMENT | F54: =IFERROR(E54/D54,0) -> 0 | H54: =HLOOKUP($H$9,'Budget Program Sales'!$C$26:$N$35,3,FALSE) -> 0 | I54: =IFERROR(H54/D54-1,0) -> 0 | J54: =IFERROR(H54/E54-1,0) -> 0
B55: ='Budget Program Sales'!B12 -> SUBSIDI ANGSURAN | F55: =IFERROR(E55/D55,0) -> 0 | H55: =HLOOKUP($H$9,'Budget Program Sales'!$C$26:$N$35,4,FALSE) -> 0 | I55: =IFERROR(H55/D55-1,0) -> 0 | J55: =IFERROR(H55/E55-1,0) -> 0
B56: ='Budget Program Sales'!B13 -> SUBSIDI AKAD | F56: =IFERROR(E56/D56,0) -> 0 | H56: =HLOOKUP($H$9,'Budget Program Sales'!$C$26:$N$35,5,FALSE) -> 0 | I56: =IFERROR(H56/D56-1,0) -> 0 | J56: =IFERROR(H56/E56-1,0) -> 0
B57: ='Budget Program Sales'!B14 -> RENTBACK | F57: =IFERROR(E57/D57,0) -> 0 | H57: =HLOOKUP($H$9,'Budget Program Sales'!$C$26:$N$35,6,FALSE) -> 0 | I57: =IFERROR(H57/D57-1,0) -> 0 | J57: =IFERROR(H57/E57-1,0) -> 0
B58: ='Budget Program Sales'!B15 -> CASHBACK PATUNGAN RUMAH | F58: =IFERROR(E58/D58,0) -> 0 | H58: =HLOOKUP($H$9,'Budget Program Sales'!$C$26:$N$35,7,FALSE) -> 0 | I58: =IFERROR(H58/D58-1,0) -> 0 | J58: =IFERROR(H58/E58-1,0) -> 0
B62: Total Sales & Marketing Costs (in Rp Bio) | C62: =C50+C51 -> #REF! | D62: =D50+D51+D52 -> 0 | E62: =E50+E51+E52 -> 0 | F62: =IFERROR(E62/D62,0) -> 0 | H62: =H50+H51+H52 -> 0 | I62: =IFERROR(H62/D62-1,0) -> 0 | J62: =IFERROR(H62/E62-1,0) -> 0
B63: Sales commision cost to Total Sales Ratio | C63: =C62/#REF! -> #REF! | D63: =D50/D25 -> #DIV/0! | E63: =E50/E25 -> #DIV/0! | H63: =H50/H25 -> #DIV/0!
B64: Advertising & Promotion cost to Total Sales Ratio | D64: =D51/D25 -> #DIV/0! | E64: =E51/E25 -> #DIV/0! | H64: =H51/H25 -> #DIV/0!
B65: Program sales to Total Sales Ratio | D65: =D52/D25 -> #DIV/0! | E65: =E52/E25 -> #DIV/0! | H65: =H52/H25 -> #DIV/0!
B67: Employee & Operational Expenses (in Rp. Bio)
A68: 8 | B68: Employee Expenses | C68: 0 | F68: =IFERROR(E68/D68,0) -> 0 | H68: 0 | I68: =IFERROR(H68/D68-1,0) -> 0 | J68: =IFERROR(H68/E68-1,0) -> 0
A69: 9 | B69: General & Administration Expenses | C69: 0 | F69: =IFERROR(E69/D69,0) -> 0 | H69: =HLOOKUP($H$9,'Budget G&A'!E67:P68,2,FALSE) -> 0 | I69: =IFERROR(H69/D69-1,0) -> 0 | J69: =IFERROR(H69/E69-1,0) -> 0
A70: 10 | B70: Corporate Activity | C70: 0 | F70: =IFERROR(E70/D70,0) -> 0 | H70: =HLOOKUP($H$9,'Budget Corp Event Exihibition'!$F$47:$Q$49,2,FALSE) -> 0 | I70: =IFERROR(H70/D70-1,0) -> 0 | J70: =IFERROR(H70/E70-1,0) -> 0
A71: 10 | B71: Others Expenses | C71: 0 | F71: =IFERROR(E71/D71,0) -> 0 | H71: =HLOOKUP($H$9,'Budget Others'!E48:P49,2,FALSE) -> 0 | I71: =IFERROR(H71/D71-1,0) -> 0 | J71: =IFERROR(H71/E71-1,0) -> 0
B72: Finance Expense (Interest Loan) | F72: =IFERROR(E72/D72,0) -> 0 | H72: =HLOOKUP($H$9,'Budget Finance Expenses'!E19:P20,2,FALSE) -> 0 | I72: =IFERROR(H72/D72-1,0) -> 0 | J72: =IFERROR(H72/E72-1,0) -> 0
A73: 11 | B73: Taxes | F73: =IFERROR(E73/D73,0) -> 0 | H73: =HLOOKUP($H$9,'Budget Tax'!E15:P16,2,FALSE) -> 0 | I73: =IFERROR(H73/D73-1,0) -> 0 | J73: =IFERROR(H73/E73-1,0) -> 0
B74: Total Employee Expense & Operational (in Rp Bio) | C74: =SUM(C68:C70) -> 0 | D74: =SUM(D68:D73) -> 0 | E74: =SUM(E68:E73) -> 0 | F74: =IFERROR(E74/D74,0) -> 0 | H74: =SUM(H68:H73) -> 0 | I74: =IFERROR(H74/D74-1,0) -> 0 | J74: =IFERROR(H74/E74-1,0) -> 0
B76: Purchases of fixed assets | F76: =IFERROR(E76/D76,0) -> 0 | H76: =' Budget Fixed Asset'!#REF! -> #REF! | I76: =IFERROR(H76/D76-1,0) -> 0 | J76: =IFERROR(H76/E76-1,0) -> 0
B77: Total Purchase Fixed Assets (in Rp Bio) | C77: =SUM(C76) -> 0 | D77: =SUM(D76) -> 0 | E77: =SUM(E76) -> 0 | F77: =IFERROR(E77/D77,0) -> 0 | H77: =SUM(H76) -> #REF! | I77: =IFERROR(H77/D77-1,0) -> 0 | J77: =IFERROR(H77/E77-1,0) -> 0
B79: TOTAL ALL COST (in Rp Bio) | C79: =C47+C62+C74+C77 -> #REF! | D79: =D47+D62+D74+D77 -> 0 | E79: =E47+E62+E74+E77 -> 0 | F79: =IFERROR(E79/D79,0) -> 0 | H79: =H47+H62+H74+H77 -> #REF! | I79: =IFERROR(H79/D79-1,0) -> 0 | J79: =IFERROR(H79/E79-1,0) -> 0

Sheet SUM Marketing Revenue
A1: SUMMARY TARGET SALES
A2: ENTITAS: | B2: Pilih Perusahaan
A3: PROJECT | B3: Pilih Project
A4: BUDGET YEARS | B4: BUDGET 2026
A5: MONTH: | B5: YTD SEP
B7: Description | C7: 2020 | D7: BUDGET | E7: ACTUAL | F7: Budget Realization | H7: BUDGET | I7: Budget 2025 vs Budget 2026 | J7: Budget 2026 vs Actual 2025
C8: ACTUAL | D8: 2025 | E8: 2025 | F8: 2025 | H8: 2026 | I8: B2025 vs B2026 | J8: B2026 vs A2025
C9: YTD DEC | D9: YTD DEC | E9: YTD DEC | F9: =E9 -> YTD DEC | H9: YTD DEC | I9: YTD DEC | J9: YTD DEC
B11: SALES
A13: 1 | B13: in SQM
A14: 2 | B14: ='Target Marketing Revenue'!B54 -> 0 | C14: 0 | F14: =IFERROR(E14/D14,0) -> 0 | H14: =HLOOKUP(H$9,'Target Marketing Revenue'!$E$53:$P$61,$A14,FALSE) -> 0 | I14: =IFERROR(H14/D14-1,0) -> 0 | J14: =IFERROR(H14/E14-1,0) -> 0
A15: 3 | B15: ='Target Marketing Revenue'!B55 -> 0 | F15: =IFERROR(E15/D15,0) -> 0 | H15: =HLOOKUP(H$9,'Target Marketing Revenue'!$E$53:$P$61,$A15,FALSE) -> 0 | I15: =IFERROR(H15/D15-1,0) -> 0 | J15: =IFERROR(H15/E15-1,0) -> 0
A16: 4 | B16: ='Target Marketing Revenue'!B56 -> 0 | F16: =IFERROR(E16/D16,0) -> 0 | H16: =HLOOKUP(H$9,'Target Marketing Revenue'!$E$53:$P$61,$A16,FALSE) -> 0 | I16: =IFERROR(H16/D16-1,0) -> 0 | J16: =IFERROR(H16/E16-1,0) -> 0
A17: 5 | B17: ='Target Marketing Revenue'!B57 -> 0 | C17: 0 | F17: =IFERROR(E17/D17,0) -> 0 | H17: =HLOOKUP(H$9,'Target Marketing Revenue'!$E$53:$P$61,$A17,FALSE) -> 0 | I17: =IFERROR(H17/D17-1,0) -> 0 | J17: =IFERROR(H17/E17-1,0) -> 0
A18: 6 | B18: ='Target Marketing Revenue'!B58 -> 0 | C18: 0 | F18: =IFERROR(E18/D18,0) -> 0 | H18: =HLOOKUP(H$9,'Target Marketing Revenue'!$E$53:$P$61,$A18,FALSE) -> 0 | I18: =IFERROR(H18/D18-1,0) -> 0 | J18: =IFERROR(H18/E18-1,0) -> 0
C19: 0
B20: ="TOTAL"&" "&B11&" "&B13 -> TOTAL SALES in SQM | C20: =SUM(C14:C19) -> 0 | D20: =SUM(D14:D19) -> 0 | E20: =SUM(E14:E19) -> 0 | F20: =IFERROR(E20/D20,0) -> 0 | H20: =SUM(H14:H19) -> 0 | I20: =IFERROR(H20/D20-1,0) -> 0 | J20: =IFERROR(H20/E20-1,0) -> 0
A22: 1 | B22: MARKETING REVENUE (in Rp Bio)
A23: 2 | B23: ='Target Marketing Revenue'!B64 -> 0 | C23: 0 | F23: =IFERROR(E23/D23,0) -> 0 | H23: =HLOOKUP(H$9,'Target Marketing Revenue'!$E$63:$P$71,$A23,FALSE) -> 0 | I23: =IFERROR(H23/D23-1,0) -> 0 | J23: =IFERROR(H23/E23-1,0) -> 0
A24: 3 | B24: ='Target Marketing Revenue'!B65 -> 0 | F24: =IFERROR(E24/D24,0) -> 0 | H24: =HLOOKUP(H$9,'Target Marketing Revenue'!$E$63:$P$71,$A24,FALSE) -> 0 | I24: =IFERROR(H24/D24-1,0) -> 0 | J24: =IFERROR(H24/E24-1,0) -> 0
A25: 4 | B25: ='Target Marketing Revenue'!B66 -> 0 | F25: =IFERROR(E25/D25,0) -> 0 | H25: =HLOOKUP(H$9,'Target Marketing Revenue'!$E$63:$P$71,$A25,FALSE) -> 0 | I25: =IFERROR(H25/D25-1,0) -> 0 | J25: =IFERROR(H25/E25-1,0) -> 0
A26: 5 | B26: ='Target Marketing Revenue'!B67 -> 0 | C26: 0 | F26: =IFERROR(E26/D26,0) -> 0 | H26: =HLOOKUP(H$9,'Target Marketing Revenue'!$E$63:$P$71,$A26,FALSE) -> 0 | I26: =IFERROR(H26/D26-1,0) -> 0 | J26: =IFERROR(H26/E26-1,0) -> 0
A27: 6 | B27: ='Target Marketing Revenue'!B68 -> 0 | C27: 0 | F27: =IFERROR(E27/D27,0) -> 0 | H27: =HLOOKUP(H$9,'Target Marketing Revenue'!$E$63:$P$71,$A27,FALSE) -> 0 | I27: =IFERROR(H27/D27-1,0) -> 0 | J27: =IFERROR(H27/E27-1,0) -> 0
A28: 4 | C28: 0
B29: ="TOTAL"&" "&B22 -> TOTAL MARKETING REVENUE (in Rp Bio) | C29: =SUM(C23:C28) -> 0 | D29: =SUM(D23:D28) -> 0 | E29: =SUM(E23:E28) -> 0 | F29: =IFERROR(E29/D29,0) -> 0 | H29: =SUM(H23:H28) -> 0 | I29: =IFERROR(H29/D29-1,0) -> 0 | J29: =IFERROR(H29/E29-1,0) -> 0

Sheet Target Marketing Revenue
B1: Target Marketing Revenue
B2: ENTITAS: | C2: Pilih Perusahaan
B3: PROJECT | C3: Pilih Project
B4: BUDGET YEARS | C4: 2027
B6: Target Marketing Revenue (Unit) | C6: Stock Unit 1 Ags 2026 | D6: Marketing Revenue in Unit | E6: 46388 | F6: 46419 | G6: 46447 | H6: 46478 | I6: 46508 | J6: 46539 | K6: 46569 | L6: 46600 | M6: 46631 | N6: 46661 | O6: 46692 | P6: 46722
D7: =SUM(E7:P7) -> 0
D8: =SUM(E8:P8) -> 0
D9: =SUM(E9:P9) -> 0
D10: =SUM(E10:P10) -> 0
D11: =SUM(E11:P11) -> 0
D12: =SUM(E12:P12) -> 0
D13: =SUM(E13:P13) -> 0
D14: =SUM(E14:P14) -> 0
B15: ="TOTAL"&" "&B6 -> TOTAL Target Marketing Revenue (Unit) | C15: =SUM(C7:C14) -> 0 | D15: =SUM(D7:D14) -> 0 | E15: =SUM(E7:E14) -> 0 | F15: =SUM(F7:F14) -> 0 | G15: =SUM(G7:G14) -> 0 | H15: =SUM(H7:H14) -> 0 | I15: =SUM(I7:I14) -> 0 | J15: =SUM(J7:J14) -> 0 | ... P15: =SUM(P7:P14) -> 0
B18: Target Marketing Revenue in (Sqm) | C18: Stock SQM 1 Ags 2026 | D18: Marketing Revenue in SQM | E18: =E6 -> 46388 | F18: =F6 -> 46419 | G18: =G6 -> 46447 | H18: =H6 -> 46478 | I18: =I6 -> 46508 | J18: =J6 -> 46539 | K18: =K6 -> 46569 | L18: =L6 -> 46600 | ... P18: =P6 -> 46722
D19: =SUM(E19:P19) -> 0
D20: =SUM(E20:P20) -> 0
D21: =SUM(E21:P21) -> 0
D22: =SUM(E22:P22) -> 0
D23: =SUM(E23:P23) -> 0
D24: =SUM(E24:P24) -> 0
D25: =SUM(E25:P25) -> 0
D26: =SUM(E26:P26) -> 0
B27: ="TOTAL"&" "&B18 -> TOTAL Target Marketing Revenue in (Sqm) | C27: =SUM(C19:C26) -> 0 | D27: =SUM(D19:D26) -> 0 | E27: =SUM(E19:E26) -> 0 | F27: =SUM(F19:F26) -> 0 | G27: =SUM(G19:G26) -> 0 | H27: =SUM(H19:H26) -> 0 | I27: =SUM(I19:I26) -> 0 | J27: =SUM(J19:J26) -> 0 | ... P27: =SUM(P19:P26) -> 0
C29: Hard cash
B30: Target Marketing Revenue VALUE | C30: Price / sqm (Rp.)* | D30: TOTAL SALES VALUE | E30: =E18 -> 46388 | F30: =F18 -> 46419 | G30: =G18 -> 46447 | H30: =H18 -> 46478 | I30: =I18 -> 46508 | J30: =J18 -> 46539 | K30: =K18 -> 46569 | L30: =L18 -> 46600 | ... P30: =P18 -> 46722
D31: =SUM(E31:P31) -> 0 | E31: =$C31*E19 -> 0 | F31: =$C31*F19 -> 0 | G31: =$C31*G19 -> 0 | H31: =$C31*H19 -> 0 | I31: =$C31*I19 -> 0 | J31: =$C31*J19 -> 0 | K31: =$C31*K19 -> 0 | L31: =$C31*L19 -> 0 | ... P31: =$C31*P19 -> 0
D32: =SUM(E32:P32) -> 0 | E32: =$C32*E20 -> 0 | F32: =$C32*F20 -> 0 | G32: =$C32*G20 -> 0 | H32: =$C32*H20 -> 0 | I32: =$C32*I20 -> 0 | J32: =$C32*J20 -> 0 | K32: =$C32*K20 -> 0 | L32: =$C32*L20 -> 0 | ... P32: =$C32*P20 -> 0
D33: =SUM(E33:P33) -> 0 | E33: =$C33*E21 -> 0 | F33: =$C33*F21 -> 0 | G33: =$C33*G21 -> 0 | H33: =$C33*H21 -> 0 | I33: =$C33*I21 -> 0 | J33: =$C33*J21 -> 0 | K33: =$C33*K21 -> 0 | L33: =$C33*L21 -> 0 | ... P33: =$C33*P21 -> 0
D34: =SUM(E34:P34) -> 0 | E34: =$C34*E22 -> 0 | F34: =$C34*F22 -> 0 | G34: =$C34*G22 -> 0 | H34: =$C34*H22 -> 0 | I34: =$C34*I22 -> 0 | J34: =$C34*J22 -> 0 | K34: =$C34*K22 -> 0 | L34: =$C34*L22 -> 0 | ... P34: =$C34*P22 -> 0
D35: =SUM(E35:P35) -> 0 | E35: =$C35*E23 -> 0 | F35: =$C35*F23 -> 0 | G35: =$C35*G23 -> 0 | H35: =$C35*H23 -> 0 | I35: =$C35*I23 -> 0 | J35: =$C35*J23 -> 0 | K35: =$C35*K23 -> 0 | L35: =$C35*L23 -> 0 | ... P35: =$C35*P23 -> 0
D36: =SUM(E36:P36) -> 0 | E36: =$C36*E24 -> 0 | F36: =$C36*F24 -> 0 | G36: =$C36*G24 -> 0 | H36: =$C36*H24 -> 0 | I36: =$C36*I24 -> 0 | J36: =$C36*J24 -> 0 | K36: =$C36*K24 -> 0 | L36: =$C36*L24 -> 0 | ... P36: =$C36*P24 -> 0
D37: =SUM(E37:P37) -> 0 | E37: =$C37*E25 -> 0 | F37: =$C37*F25 -> 0 | G37: =$C37*G25 -> 0 | H37: =$C37*H25 -> 0 | I37: =$C37*I25 -> 0 | J37: =$C37*J25 -> 0 | K37: =$C37*K25 -> 0 | L37: =$C37*L25 -> 0 | ... P37: =$C37*P25 -> 0
D38: =SUM(E38:P38) -> 0 | E38: =$C38*E26 -> 0 | F38: =$C38*F26 -> 0 | G38: =$C38*G26 -> 0 | H38: =$C38*H26 -> 0 | I38: =$C38*I26 -> 0 | J38: =$C38*J26 -> 0 | K38: =$C38*K26 -> 0 | L38: =$C38*L26 -> 0 | ... P38: =$C38*P26 -> 0
B39: ="TOTAL"&" "&B30 -> TOTAL Target Marketing Revenue VALUE | D39: =SUM(D31:D38) -> 0 | E39: =SUM(E31:E38) -> 0 | F39: =SUM(F31:F38) -> 0 | G39: =SUM(G31:G38) -> 0 | H39: =SUM(H31:H38) -> 0 | I39: =SUM(I31:I38) -> 0 | J39: =SUM(J31:J38) -> 0 | K39: =SUM(K31:K38) -> 0 | ... P39: =SUM(P31:P38) -> 0
B40: * Price / sqm diisi dengan asumsi cara bayar Cash Keras
B42: Linked to SUM Actual vs Budget | E42: YTD JAN | F42: YTD FEB | G42: YTD MAR | H42: YTD APR | I42: YTD MAY | J42: YTD JUN | K42: YTD JUL | L42: YTD AUG | M42: YTD SEP | N42: YTD OCT | O42: YTD NOV | P42: YTD DEC
B43: =B6 -> Target Marketing Revenue (Unit)
B44: =B7 -> 0 | E44: =SUM($E7:E7) -> 0 | F44: =SUM($E7:F7) -> 0 | G44: =SUM($E7:G7) -> 0 | H44: =SUM($E7:H7) -> 0 | I44: =SUM($E7:I7) -> 0 | J44: =SUM($E7:J7) -> 0 | K44: =SUM($E7:K7) -> 0 | L44: =SUM($E7:L7) -> 0 | ... P44: =SUM($E7:P7) -> 0
B45: =B8 -> 0 | E45: =SUM($E8:E8) -> 0 | F45: =SUM($E8:F8) -> 0 | G45: =SUM($E8:G8) -> 0 | H45: =SUM($E8:H8) -> 0 | I45: =SUM($E8:I8) -> 0 | J45: =SUM($E8:J8) -> 0 | K45: =SUM($E8:K8) -> 0 | L45: =SUM($E8:L8) -> 0 | ... P45: =SUM($E8:P8) -> 0
B46: =B9 -> 0 | E46: =SUM($E9:E9) -> 0 | F46: =SUM($E9:F9) -> 0 | G46: =SUM($E9:G9) -> 0 | H46: =SUM($E9:H9) -> 0 | I46: =SUM($E9:I9) -> 0 | J46: =SUM($E9:J9) -> 0 | K46: =SUM($E9:K9) -> 0 | L46: =SUM($E9:L9) -> 0 | ... P46: =SUM($E9:P9) -> 0
B47: =B10 -> 0 | E47: =SUM($E10:E10) -> 0 | F47: =SUM($E10:F10) -> 0 | G47: =SUM($E10:G10) -> 0 | H47: =SUM($E10:H10) -> 0 | I47: =SUM($E10:I10) -> 0 | J47: =SUM($E10:J10) -> 0 | K47: =SUM($E10:K10) -> 0 | L47: =SUM($E10:L10) -> 0 | ... P47: =SUM($E10:P10) -> 0
B48: =B11 -> 0 | E48: =SUM($E11:E11) -> 0 | F48: =SUM($E11:F11) -> 0 | G48: =SUM($E11:G11) -> 0 | H48: =SUM($E11:H11) -> 0 | I48: =SUM($E11:I11) -> 0 | J48: =SUM($E11:J11) -> 0 | K48: =SUM($E11:K11) -> 0 | L48: =SUM($E11:L11) -> 0 | ... P48: =SUM($E11:P11) -> 0
B49: =B12 -> 0 | E49: =SUM($E12:E12) -> 0 | F49: =SUM($E12:F12) -> 0 | G49: =SUM($E12:G12) -> 0 | H49: =SUM($E12:H12) -> 0 | I49: =SUM($E12:I12) -> 0 | J49: =SUM($E12:J12) -> 0 | K49: =SUM($E12:K12) -> 0 | L49: =SUM($E12:L12) -> 0 | ... P49: =SUM($E12:P12) -> 0
B50: =B13 -> 0 | E50: =SUM($E13:E13) -> 0 | F50: =SUM($E13:F13) -> 0 | G50: =SUM($E13:G13) -> 0 | H50: =SUM($E13:H13) -> 0 | I50: =SUM($E13:I13) -> 0 | J50: =SUM($E13:J13) -> 0 | K50: =SUM($E13:K13) -> 0 | L50: =SUM($E13:L13) -> 0 | ... P50: =SUM($E13:P13) -> 0
B51: =B14 -> 0 | E51: =SUM($E14:E14) -> 0 | F51: =SUM($E14:F14) -> 0 | G51: =SUM($E14:G14) -> 0 | H51: =SUM($E14:H14) -> 0 | I51: =SUM($E14:I14) -> 0 | J51: =SUM($E14:J14) -> 0 | K51: =SUM($E14:K14) -> 0 | L51: =SUM($E14:L14) -> 0 | ... P51: =SUM($E14:P14) -> 0
B53: =B18 -> Target Marketing Revenue in (Sqm) | E53: =E42 -> YTD JAN | F53: =F42 -> YTD FEB | G53: =G42 -> YTD MAR | H53: =H42 -> YTD APR | I53: =I42 -> YTD MAY | J53: =J42 -> YTD JUN | K53: =K42 -> YTD JUL | L53: =L42 -> YTD AUG | ... P53: =P42 -> YTD DEC
B54: =B19 -> 0 | E54: =SUM($E19:E19) -> 0 | F54: =SUM($E19:F19) -> 0 | G54: =SUM($E19:G19) -> 0 | H54: =SUM($E19:H19) -> 0 | I54: =SUM($E19:I19) -> 0 | J54: =SUM($E19:J19) -> 0 | K54: =SUM($E19:K19) -> 0 | L54: =SUM($E19:L19) -> 0 | ... P54: =SUM($E19:P19) -> 0
B55: =B20 -> 0 | E55: =SUM($E20:E20) -> 0 | F55: =SUM($E20:F20) -> 0 | G55: =SUM($E20:G20) -> 0 | H55: =SUM($E20:H20) -> 0 | I55: =SUM($E20:I20) -> 0 | J55: =SUM($E20:J20) -> 0 | K55: =SUM($E20:K20) -> 0 | L55: =SUM($E20:L20) -> 0 | ... P55: =SUM($E20:P20) -> 0
B56: =B21 -> 0 | E56: =SUM($E21:E21) -> 0 | F56: =SUM($E21:F21) -> 0 | G56: =SUM($E21:G21) -> 0 | H56: =SUM($E21:H21) -> 0 | I56: =SUM($E21:I21) -> 0 | J56: =SUM($E21:J21) -> 0 | K56: =SUM($E21:K21) -> 0 | L56: =SUM($E21:L21) -> 0 | ... P56: =SUM($E21:P21) -> 0
B57: =B22 -> 0 | E57: =SUM($E22:E22) -> 0 | F57: =SUM($E22:F22) -> 0 | G57: =SUM($E22:G22) -> 0 | H57: =SUM($E22:H22) -> 0 | I57: =SUM($E22:I22) -> 0 | J57: =SUM($E22:J22) -> 0 | K57: =SUM($E22:K22) -> 0 | L57: =SUM($E22:L22) -> 0 | ... P57: =SUM($E22:P22) -> 0
B58: =B23 -> 0 | E58: =SUM($E23:E23) -> 0 | F58: =SUM($E23:F23) -> 0 | G58: =SUM($E23:G23) -> 0 | H58: =SUM($E23:H23) -> 0 | I58: =SUM($E23:I23) -> 0 | J58: =SUM($E23:J23) -> 0 | K58: =SUM($E23:K23) -> 0 | L58: =SUM($E23:L23) -> 0 | ... P58: =SUM($E23:P23) -> 0
B59: =B24 -> 0 | E59: =SUM($E24:E24) -> 0 | F59: =SUM($E24:F24) -> 0 | G59: =SUM($E24:G24) -> 0 | H59: =SUM($E24:H24) -> 0 | I59: =SUM($E24:I24) -> 0 | J59: =SUM($E24:J24) -> 0 | K59: =SUM($E24:K24) -> 0 | L59: =SUM($E24:L24) -> 0 | ... P59: =SUM($E24:P24) -> 0
B60: =B25 -> 0 | E60: =SUM($E25:E25) -> 0 | F60: =SUM($E25:F25) -> 0 | G60: =SUM($E25:G25) -> 0 | H60: =SUM($E25:H25) -> 0 | I60: =SUM($E25:I25) -> 0 | J60: =SUM($E25:J25) -> 0 | K60: =SUM($E25:K25) -> 0 | L60: =SUM($E25:L25) -> 0 | ... P60: =SUM($E25:P25) -> 0
B61: =B26 -> 0 | E61: =SUM($E26:E26) -> 0 | F61: =SUM($E26:F26) -> 0 | G61: =SUM($E26:G26) -> 0 | H61: =SUM($E26:H26) -> 0 | I61: =SUM($E26:I26) -> 0 | J61: =SUM($E26:J26) -> 0 | K61: =SUM($E26:K26) -> 0 | L61: =SUM($E26:L26) -> 0 | ... P61: =SUM($E26:P26) -> 0
B63: =B30 -> Target Marketing Revenue VALUE | E63: =E53 -> YTD JAN | F63: =F53 -> YTD FEB | G63: =G53 -> YTD MAR | H63: =H53 -> YTD APR | I63: =I53 -> YTD MAY | J63: =J53 -> YTD JUN | K63: =K53 -> YTD JUL | L63: =L53 -> YTD AUG | ... P63: =P53 -> YTD DEC
B64: =B31 -> 0 | E64: =SUM($E31:E31) -> 0 | F64: =SUM($E31:F31) -> 0 | G64: =SUM($E31:G31) -> 0 | H64: =SUM($E31:H31) -> 0 | I64: =SUM($E31:I31) -> 0 | J64: =SUM($E31:J31) -> 0 | K64: =SUM($E31:K31) -> 0 | L64: =SUM($E31:L31) -> 0 | ... P64: =SUM($E31:P31) -> 0
B65: =B32 -> 0 | E65: =SUM($E32:E32) -> 0 | F65: =SUM($E32:F32) -> 0 | G65: =SUM($E32:G32) -> 0 | H65: =SUM($E32:H32) -> 0 | I65: =SUM($E32:I32) -> 0 | J65: =SUM($E32:J32) -> 0 | K65: =SUM($E32:K32) -> 0 | L65: =SUM($E32:L32) -> 0 | ... P65: =SUM($E32:P32) -> 0
B66: =B33 -> 0 | E66: =SUM($E33:E33) -> 0 | F66: =SUM($E33:F33) -> 0 | G66: =SUM($E33:G33) -> 0 | H66: =SUM($E33:H33) -> 0 | I66: =SUM($E33:I33) -> 0 | J66: =SUM($E33:J33) -> 0 | K66: =SUM($E33:K33) -> 0 | L66: =SUM($E33:L33) -> 0 | ... P66: =SUM($E33:P33) -> 0
B67: =B34 -> 0 | E67: =SUM($E34:E34) -> 0 | F67: =SUM($E34:F34) -> 0 | G67: =SUM($E34:G34) -> 0 | H67: =SUM($E34:H34) -> 0 | I67: =SUM($E34:I34) -> 0 | J67: =SUM($E34:J34) -> 0 | K67: =SUM($E34:K34) -> 0 | L67: =SUM($E34:L34) -> 0 | ... P67: =SUM($E34:P34) -> 0
B68: =B35 -> 0 | E68: =SUM($E35:E35) -> 0 | F68: =SUM($E35:F35) -> 0 | G68: =SUM($E35:G35) -> 0 | H68: =SUM($E35:H35) -> 0 | I68: =SUM($E35:I35) -> 0 | J68: =SUM($E35:J35) -> 0 | K68: =SUM($E35:K35) -> 0 | L68: =SUM($E35:L35) -> 0 | ... P68: =SUM($E35:P35) -> 0
B69: =B36 -> 0 | E69: =SUM($E36:E36) -> 0 | F69: =SUM($E36:F36) -> 0 | G69: =SUM($E36:G36) -> 0 | H69: =SUM($E36:H36) -> 0 | I69: =SUM($E36:I36) -> 0 | J69: =SUM($E36:J36) -> 0 | K69: =SUM($E36:K36) -> 0 | L69: =SUM($E36:L36) -> 0 | ... P69: =SUM($E36:P36) -> 0
B70: =B37 -> 0 | E70: =SUM($E37:E37) -> 0 | F70: =SUM($E37:F37) -> 0 | G70: =SUM($E37:G37) -> 0 | H70: =SUM($E37:H37) -> 0 | I70: =SUM($E37:I37) -> 0 | J70: =SUM($E37:J37) -> 0 | K70: =SUM($E37:K37) -> 0 | L70: =SUM($E37:L37) -> 0 | ... P70: =SUM($E37:P37) -> 0
B71: =B38 -> 0 | E71: =SUM($E38:E38) -> 0 | F71: =SUM($E38:F38) -> 0 | G71: =SUM($E38:G38) -> 0 | H71: =SUM($E38:H38) -> 0 | I71: =SUM($E38:I38) -> 0 | J71: =SUM($E38:J38) -> 0 | K71: =SUM($E38:K38) -> 0 | L71: =SUM($E38:L38) -> 0 | ... P71: =SUM($E38:P38) -> 0

Sheet Budget Sales Cost
B1: BUDGET SALES COST
B2: ENTITAS: | C2: Pilih Perusahaan
B3: PROJECT | C3: Pilih Project
B4: BUDGET YEARS | C4: 2027
C6: 46388 | D6: 46419 | E6: 46447 | F6: 46478 | G6: 46508 | H6: 46539 | I6: 46569 | J6: 46600 | K6: 46631 | L6: 46661 | M6: 46692 | N6: 46722 | O6: TOTAL
B7: ='Target Marketing Revenue'!B39 -> TOTAL Target Marketing Revenue VALUE | C7: ='Target Marketing Revenue'!E39 -> 0 | D7: ='Target Marketing Revenue'!F39 -> 0 | E7: ='Target Marketing Revenue'!G39 -> 0 | F7: ='Target Marketing Revenue'!H39 -> 0 | G7: ='Target Marketing Revenue'!I39 -> 0 | H7: ='Target Marketing Revenue'!J39 -> 0 | I7: ='Target Marketing Revenue'!K39 -> 0 | J7: ='Target Marketing Revenue'!L39 -> 0 | ... N7: ='Target Marketing Revenue'!P39 -> 0 | O7: =SUM(C7:N7) -> 0
B9: SALES COST
B10: SALES INHOUSE | C10: =C25 -> 0 | D10: =D25 -> 0 | E10: =E25 -> 0 | F10: =F25 -> 0 | G10: =G25 -> 0 | H10: =H25 -> 0 | I10: =I25 -> 0 | J10: =J25 -> 0 | ... N10: =N25 -> 0 | O10: =SUM(C10:N10) -> 0
B11: SALES AGENT | C11: =C36 -> 0 | D11: =D36 -> 0 | E11: =E36 -> 0 | F11: =F36 -> 0 | G11: =G36 -> 0 | H11: =H36 -> 0 | I11: =I36 -> 0 | J11: =J36 -> 0 | ... N11: =N36 -> 0 | O11: =SUM(C11:N11) -> 0
B13: TOTAL SALES COST | C13: =SUM(C10:C11) -> 0 | D13: =SUM(D10:D11) -> 0 | E13: =SUM(E10:E11) -> 0 | F13: =SUM(F10:F11) -> 0 | G13: =SUM(G10:G11) -> 0 | H13: =SUM(H10:H11) -> 0 | I13: =SUM(I10:I11) -> 0 | J13: =SUM(J10:J11) -> 0 | ... O13: =SUM(O10:O11) -> 0
B14: % ratio to Target Sales | C14: =C13/C7 -> #DIV/0! | D14: =D13/D7 -> #DIV/0! | E14: =E13/E7 -> #DIV/0! | F14: =F13/F7 -> #DIV/0! | G14: =G13/G7 -> #DIV/0! | H14: =H13/H7 -> #DIV/0! | I14: =I13/I7 -> #DIV/0! | J14: =J13/J7 -> #DIV/0! | ... N14: =N13/N7 -> #DIV/0!
B17: Sales Cost (In House) | C17: =C6 -> 46388 | D17: =D6 -> 46419 | E17: =E6 -> 46447 | F17: =F6 -> 46478 | G17: =G6 -> 46508 | H17: =H6 -> 46539 | I17: =I6 -> 46569 | J17: =J6 -> 46600 | ... N17: =N6 -> 46722
B18: Closing Fee
B19: OR
B20: Komisi
B21: Reward Sales
B25: ="Total"&" "&B17 -> Total Sales Cost (In House) | C25: =SUM(C18:C24) -> 0 | D25: =SUM(D18:D24) -> 0 | E25: =SUM(E18:E24) -> 0 | F25: =SUM(F18:F24) -> 0 | G25: =SUM(G18:G24) -> 0 | H25: =SUM(H18:H24) -> 0 | I25: =SUM(I18:I24) -> 0 | J25: =SUM(J18:J24) -> 0 | ... N25: =SUM(N18:N24) -> 0
B28: Sales Cost (Agent) | C28: =C6 -> 46388 | D28: =D6 -> 46419 | E28: =E6 -> 46447 | F28: =F6 -> 46478 | G28: =G6 -> 46508 | H28: =H6 -> 46539 | I28: =I6 -> 46569 | J28: =J6 -> 46600 | ... N28: =N6 -> 46722
B29: Closing Fee
B30: OR
B31: Komisi
B36: ="Total"&" "&B28 -> Total Sales Cost (Agent) | C36: =SUM(C29:C35) -> 0 | D36: =SUM(D29:D35) -> 0 | E36: =SUM(E29:E35) -> 0 | F36: =SUM(F29:F35) -> 0 | G36: =SUM(G29:G35) -> 0 | H36: =SUM(H29:H35) -> 0 | I36: =SUM(I29:I35) -> 0 | J36: =SUM(J29:J35) -> 0 | ... N36: =SUM(N29:N35) -> 0
B40: Linked to SUM Actual vs Budget | C40: YTD JAN | D40: YTD FEB | E40: YTD MAR | F40: YTD APR | G40: YTD MAY | H40: YTD JUN | I40: YTD JUL | J40: YTD AUG | K40: YTD SEP | L40: YTD OCT | M40: YTD NOV | N40: YTD DEC
B41: =B10 -> SALES INHOUSE | C41: =SUM($C10:C10) -> 0 | D41: =SUM($C10:D10) -> 0 | E41: =SUM($C10:E10) -> 0 | F41: =SUM($C10:F10) -> 0 | G41: =SUM($C10:G10) -> 0 | H41: =SUM($C10:H10) -> 0 | I41: =SUM($C10:I10) -> 0 | J41: =SUM($C10:J10) -> 0 | ... N41: =SUM($C10:N10) -> 0
B42: =B11 -> SALES AGENT | C42: =SUM($C11:C11) -> 0 | D42: =SUM($C11:D11) -> 0 | E42: =SUM($C11:E11) -> 0 | F42: =SUM($C11:F11) -> 0 | G42: =SUM($C11:G11) -> 0 | H42: =SUM($C11:H11) -> 0 | I42: =SUM($C11:I11) -> 0 | J42: =SUM($C11:J11) -> 0 | ... N42: =SUM($C11:N11) -> 0
B43: TOTAL SALES COST | C43: =SUM($C12:C12) -> 0 | D43: =SUM($C12:D12) -> 0 | E43: =SUM($C12:E12) -> 0 | F43: =SUM($C12:F12) -> 0 | G43: =SUM($C12:G12) -> 0 | H43: =SUM($C12:H12) -> 0 | I43: =SUM($C12:I12) -> 0 | J43: =SUM($C12:J12) -> 0 | ... N43: =SUM($C12:N12) -> 0

Sheet Budget Program Sales
B1: PROGRAM SALES
B2: ENTITAS: | C2: Pilih Perusahaan
B3: PROJECT | C3: Pilih Project
B4: BUDGET YEARS | C4: 2027
C6: 46388 | D6: 46419 | E6: 46447 | F6: 46478 | G6: 46508 | H6: 46539 | I6: 46569 | J6: 46600 | K6: 46631 | L6: 46661 | M6: 46692 | N6: 46722 | O6: TOTAL
B7: ='Target Marketing Revenue'!B39 -> TOTAL Target Marketing Revenue VALUE | C7: ='Target Marketing Revenue'!E39 -> 0 | D7: ='Target Marketing Revenue'!F39 -> 0 | E7: ='Target Marketing Revenue'!G39 -> 0 | F7: ='Target Marketing Revenue'!H39 -> 0 | G7: ='Target Marketing Revenue'!I39 -> 0 | H7: ='Target Marketing Revenue'!J39 -> 0 | I7: ='Target Marketing Revenue'!K39 -> 0 | J7: ='Target Marketing Revenue'!L39 -> 0 | ... N7: ='Target Marketing Revenue'!P39 -> 0 | O7: =SUM(C7:N7) -> 0
B9: PROGRAM SALES
B10: SUBSIDI BOOKING FEE | O10: =SUM(C10:N10) -> 0
B11: SUBSIDI DOWN PAYMENT
B12: SUBSIDI ANGSURAN | O12: =SUM(C12:N12) -> 0
B13: SUBSIDI AKAD | O13: =SUM(C13:N13) -> 0
B14: RENTBACK | O14: =SUM(C14:N14) -> 0 | P14: *Bukan nilai unit buybacknya tapi program rentback ini ada biaya investment yg harus dibayarkan developer ke konsumen masuk sini ( biaya interest , dll )
B15: CASHBACK PATUNGAN RUMAH | O15: =SUM(C15:N15) -> 0
O16: =SUM(C16:N16) -> 0 | P16: *Buyback tidak masuk budget >> masuk cashflow
O17: =SUM(C17:N17) -> 0
O18: =SUM(C18:N18) -> 0
B19: TOTAL SALES PROGRAM | C19: =SUM(C10:C18) -> 0 | D19: =SUM(D10:D18) -> 0 | E19: =SUM(E10:E18) -> 0 | F19: =SUM(F10:F18) -> 0 | G19: =SUM(G10:G18) -> 0 | H19: =SUM(H10:H18) -> 0 | I19: =SUM(I10:I18) -> 0 | J19: =SUM(J10:J18) -> 0 | ... O19: =SUM(O10:O18) -> 0
B20: % ratio to Target Sales | C20: =C19/C7 -> #DIV/0! | D20: =D19/D7 -> #DIV/0! | E20: =E19/E7 -> #DIV/0! | F20: =F19/F7 -> #DIV/0! | G20: =G19/G7 -> #DIV/0! | H20: =H19/H7 -> #DIV/0! | I20: =I19/I7 -> #DIV/0! | J20: =J19/J7 -> #DIV/0! | ... N20: =N19/N7 -> #DIV/0!
B26: Linked to SUM Budget Cost | C26: YTD JAN | D26: YTD FEB | E26: YTD MAR | F26: YTD APR | G26: YTD MAY | H26: YTD JUN | I26: YTD JUL | J26: YTD AUG | K26: YTD SEP | L26: YTD OCT | M26: YTD NOV | N26: YTD DEC
B27: =B10 -> SUBSIDI BOOKING FEE | C27: =SUM($C10:C10) -> 0 | D27: =SUM($C10:D10) -> 0 | E27: =SUM($C10:E10) -> 0 | F27: =SUM($C10:F10) -> 0 | G27: =SUM($C10:G10) -> 0 | H27: =SUM($C10:H10) -> 0 | I27: =SUM($C10:I10) -> 0 | J27: =SUM($C10:J10) -> 0 | ... N27: =SUM($C10:N10) -> 0
B28: SUBSIDI DOWN PAYMENT | C28: =SUM($C11:C11) -> 0 | D28: =SUM($C11:D11) -> 0 | E28: =SUM($C11:E11) -> 0 | F28: =SUM($C11:F11) -> 0 | G28: =SUM($C11:G11) -> 0 | H28: =SUM($C11:H11) -> 0 | I28: =SUM($C11:I11) -> 0 | J28: =SUM($C11:J11) -> 0 | ... N28: =SUM($C11:N11) -> 0
B29: =B12 -> SUBSIDI ANGSURAN | C29: =SUM($C12:C12) -> 0 | D29: =SUM($C12:D12) -> 0 | E29: =SUM($C12:E12) -> 0 | F29: =SUM($C12:F12) -> 0 | G29: =SUM($C12:G12) -> 0 | H29: =SUM($C12:H12) -> 0 | I29: =SUM($C12:I12) -> 0 | J29: =SUM($C12:J12) -> 0 | ... N29: =SUM($C12:N12) -> 0
B30: =B13 -> SUBSIDI AKAD | C30: =SUM($C13:C13) -> 0 | D30: =SUM($C13:D13) -> 0 | E30: =SUM($C13:E13) -> 0 | F30: =SUM($C13:F13) -> 0 | G30: =SUM($C13:G13) -> 0 | H30: =SUM($C13:H13) -> 0 | I30: =SUM($C13:I13) -> 0 | J30: =SUM($C13:J13) -> 0 | ... N30: =SUM($C13:N13) -> 0
B31: =B14 -> RENTBACK | C31: =SUM($C14:C14) -> 0 | D31: =SUM($C14:D14) -> 0 | E31: =SUM($C14:E14) -> 0 | F31: =SUM($C14:F14) -> 0 | G31: =SUM($C14:G14) -> 0 | H31: =SUM($C14:H14) -> 0 | I31: =SUM($C14:I14) -> 0 | J31: =SUM($C14:J14) -> 0 | ... N31: =SUM($C14:N14) -> 0
B32: =B15 -> CASHBACK PATUNGAN RUMAH | C32: =SUM($C15:C15) -> 0 | D32: =SUM($C15:D15) -> 0 | E32: =SUM($C15:E15) -> 0 | F32: =SUM($C15:F15) -> 0 | G32: =SUM($C15:G15) -> 0 | H32: =SUM($C15:H15) -> 0 | I32: =SUM($C15:I15) -> 0 | J32: =SUM($C15:J15) -> 0 | ... N32: =SUM($C15:N15) -> 0
B33: =B16 -> 0 | C33: =SUM($C16:C16) -> 0 | D33: =SUM($C16:D16) -> 0 | E33: =SUM($C16:E16) -> 0 | F33: =SUM($C16:F16) -> 0 | G33: =SUM($C16:G16) -> 0 | H33: =SUM($C16:H16) -> 0 | I33: =SUM($C16:I16) -> 0 | J33: =SUM($C16:J16) -> 0 | ... N33: =SUM($C16:N16) -> 0
B34: =B17 -> 0 | C34: =SUM($C17:C17) -> 0 | D34: =SUM($C17:D17) -> 0 | E34: =SUM($C17:E17) -> 0 | F34: =SUM($C17:F17) -> 0 | G34: =SUM($C17:G17) -> 0 | H34: =SUM($C17:H17) -> 0 | I34: =SUM($C17:I17) -> 0 | J34: =SUM($C17:J17) -> 0 | ... N34: =SUM($C17:N17) -> 0
B35: =B18 -> 0 | C35: =SUM($C18:C18) -> 0 | D35: =SUM($C18:D18) -> 0 | E35: =SUM($C18:E18) -> 0 | F35: =SUM($C18:F18) -> 0 | G35: =SUM($C18:G18) -> 0 | H35: =SUM($C18:H18) -> 0 | I35: =SUM($C18:I18) -> 0 | J35: =SUM($C18:J18) -> 0 | ... N35: =SUM($C18:N18) -> 0
B36: TOTAL SALES COST | C36: =SUM(C27:C35) -> 0 | D36: =SUM(D27:D35) -> 0 | E36: =SUM(E27:E35) -> 0 | F36: =SUM(F27:F35) -> 0 | G36: =SUM(G27:G35) -> 0 | H36: =SUM(H27:H35) -> 0 | I36: =SUM(I27:I35) -> 0 | J36: =SUM(J27:J35) -> 0 | ... N36: =SUM(N27:N35) -> 0

Sheet Budget Marketing Activity
A1: MARKETING BUDGET PLANNING
A3: ENTITAS: | B3: Pilih Perusahaan
A4: PROJECT: | B4: Pilih Project | E4: Total Sales TaSget (full yeaS) : | F4: ='Target Marketing Revenue'!D39 -> 0
A5: DIVISION: | E5: Total Marketing Expenses : | F5: =E104 -> 0
A6: BUDGET YEAR: | B6: 2027 | E6: Ratio of Mkt Expenses to Sales TaSget : | F6: =F5/F4 -> #DIV/0!
A8: Marketing Budget Plan | F8: 2027
A9: Category | B9: Budget Classification | C9: Estimated Quantity | D9: Estimated Cost per Unit | E9: Estimated Subtotal | F9: 46388 | G9: 46419 | H9: 46447 | I9: 46478 | J9: 46508 | K9: 46539 | L9: 46569 | M9: 46600 | N9: 46631 | O9: 46661 | P9: 46692 | Q9: 46722
A11: Adv & Promotion - Above-The-Line | B11: Main Chart
E12: =SUM(F12:Q12) -> 0 | F12: =F13+F21 -> 0 | G12: =G13+G21 -> 0 | H12: =H13+H21 -> 0 | I12: =I13+I21 -> 0 | J12: =J13+J21 -> 0 | K12: =K13+K21 -> 0 | L12: =L13+L21 -> 0 | M12: =M13+M21 -> 0 | ... Q12: =Q13+Q21 -> 0
A13: Production: | B13: Sub Chart | E13: =SUM(F13:Q13) -> 0 | F13: =SUM(F14:F20) -> 0 | G13: =SUM(G14:G20) -> 0 | H13: =SUM(H14:H20) -> 0 | I13: =SUM(I14:I20) -> 0 | J13: =SUM(J14:J20) -> 0 | K13: =SUM(K14:K20) -> 0 | L13: =SUM(L14:L20) -> 0 | M13: =SUM(M14:M20) -> 0 | ... Q13: =SUM(Q14:Q20) -> 0
A14: TV Commercial | B14: Media Digital, Online, TV, Radio | E14: =SUM(F14:Q14) -> 0
A15: Print Ad | B15: Media Cetak, Brosur, Spanduk, Katalog | E15: =SUM(F15:Q15) -> 0
A16: Radio Ad/spot/jingle | B16: Media Cetak, Brosur, Spanduk, Katalog | E16: =SUM(F16:Q16) -> 0
A17: Website | B17: Media Digital, Online, TV, Radio | E17: =SUM(F17:Q17) -> 0
A18: Other (social media) | B18: Media Digital, Online, TV, Radio | E18: =SUM(F18:Q18) -> 0
E19: =SUM(F19:Q19) -> 0
E20: =SUM(F20:Q20) -> 0
A21: Placement: | B21: Sub Chart | E21: =SUM(F21:Q21) -> 0 | F21: =F22+F27+F32+F37+F41 -> 0 | G21: =G22+G27+G32+G37+G41 -> 0 | H21: =H22+H27+H32+H37+H41 -> 0 | I21: =I22+I27+I32+I37+I41 -> 0 | J21: =J22+J27+J32+J37+J41 -> 0 | K21: =K22+K27+K32+K37+K41 -> 0 | L21: =L22+L27+L32+L37+L41 -> 0 | M21: =M22+M27+M32+M37+M41 -> 0 | ... Q21: =Q22+Q27+Q32+Q37+Q41 -> 0
A22: TV Commercial | E22: =SUM(F22:Q22) -> 0 | F22: =SUM(F23:F26) -> 0 | G22: =SUM(G23:G26) -> 0 | H22: =SUM(H23:H26) -> 0 | I22: =SUM(I23:I26) -> 0 | J22: =SUM(J23:J26) -> 0 | K22: =SUM(K23:K26) -> 0 | L22: =SUM(L23:L26) -> 0 | M22: =SUM(M23:M26) -> 0 | ... Q22: =SUM(Q23:Q26) -> 0
A23: - Spot, sponsor, bumper | B23: Media Digital, Online, TV, Radio | E23: =SUM(F23:Q23) -> 0
A24: - Filler, blocking, TV program | B24: Media Digital, Online, TV, Radio | E24: =SUM(F24:Q24) -> 0
E25: =SUM(F25:Q25) -> 0
E26: =SUM(F26:Q26) -> 0
A27: Print Ad | E27: =SUM(F27:Q27) -> 0 | F27: =SUM(F28:F31) -> 0 | G27: =SUM(G28:G31) -> 0 | H27: =SUM(H28:H31) -> 0 | I27: =SUM(I28:I31) -> 0 | J27: =SUM(J28:J31) -> 0 | K27: =SUM(K28:K31) -> 0 | L27: =SUM(L28:L31) -> 0 | M27: =SUM(M28:M31) -> 0 | ... Q27: =SUM(Q28:Q31) -> 0
A28: - Newspaper & tabloid (national, local, area) | B28: Media Digital, Online, TV, Radio | E28: =SUM(F28:Q28) -> 0
A29: - Magazine (national, local, area) | B29: Media Digital, Online, TV, Radio | E29: =SUM(F29:Q29) -> 0
E30: =SUM(F30:Q30) -> 0
E31: =SUM(F31:Q31) -> 0
A32: Radio Ad | E32: =SUM(F32:Q32) -> 0 | F32: =SUM(F33:F36) -> 0 | G32: =SUM(G33:G36) -> 0 | H32: =SUM(H33:H36) -> 0 | I32: =SUM(I33:I36) -> 0 | J32: =SUM(J33:J36) -> 0 | K32: =SUM(K33:K36) -> 0 | L32: =SUM(L33:L36) -> 0 | M32: =SUM(M33:M36) -> 0 | ... Q32: =SUM(Q33:Q36) -> 0
A33: - Spot & adlibs | B33: Media Digital, Online, TV, Radio | E33: =SUM(F33:Q33) -> 0
A34: - Program, blocking, interview/talkshow | B34: Media Digital, Online, TV, Radio | E34: =SUM(F34:Q34) -> 0 | G34: 0 | H34: 0 | I34: 0 | J34: 0 | K34: 0 | L34: 0 | M34: 0 | O34: 0 | P34: 0 | Q34: 0
E35: =SUM(F35:Q35) -> 0
E36: =SUM(F36:Q36) -> 0
A37: Website | E37: =SUM(F37:Q37) -> 0 | F37: =SUM(F38:F40) -> 0 | G37: =SUM(G38:G40) -> 0 | H37: =SUM(H38:H40) -> 0 | I37: =SUM(I38:I40) -> 0 | J37: =SUM(J38:J40) -> 0 | K37: =SUM(K38:K40) -> 0 | L37: =SUM(L38:L40) -> 0 | M37: =SUM(M38:M40) -> 0 | ... Q37: =SUM(Q38:Q40) -> 0
A38: - Hosting fee, maintenance | B38: Media Digital, Online, TV, Radio | E38: =SUM(F38:Q38) -> 0
E39: =SUM(F39:Q39) -> 0
E40: =SUM(F40:Q40) -> 0
A41: SOCIAL MEDIA | E41: =SUM(F41:Q41) -> 0 | F41: =SUM(F42:F44) -> 0 | G41: =SUM(G42:G44) -> 0 | H41: =SUM(H42:H44) -> 0 | I41: =SUM(I42:I44) -> 0 | J41: =SUM(J42:J44) -> 0 | K41: =SUM(K42:K44) -> 0 | L41: =SUM(L42:L44) -> 0 | M41: =SUM(M42:M44) -> 0 | ... Q41: =SUM(Q42:Q44) -> 0
A42: - Airing cost, blasting cost | B42: Media Digital, Online, TV, Radio | E42: =SUM(F42:Q42) -> 0
E43: =SUM(F43:Q43) -> 0
E44: =SUM(F44:Q44) -> 0
A46: Adv & Promotion - Below-The-Line | B46: Main Chart
E47: =SUM(F47:Q47) -> 0 | F47: =F48+F80 -> 0 | G47: =G48+G80 -> 0 | H47: =H48+H80 -> 0 | I47: =I48+I80 -> 0 | J47: =J48+J80 -> 0 | K47: =K48+K80 -> 0 | L47: =L48+L80 -> 0 | M47: =M48+M80 -> 0 | ... Q47: =Q48+Q80 -> 0
A48: Production: | B48: Sub Chart | E48: =SUM(F48:Q48) -> 0 | F48: =F49+F56+F62+F68+F74 -> 0 | G48: =G49+G56+G62+G68+G74 -> 0 | H48: =H49+H56+H62+H68+H74 -> 0 | I48: =I49+I56+I62+I68+I74 -> 0 | J48: =J49+J56+J62+J68+J74 -> 0 | K48: =K49+K56+K62+K68+K74 -> 0 | L48: =L49+L56+L62+L68+L74 -> 0 | M48: =M49+M56+M62+M68+M74 -> 0 | ... Q48: =Q49+Q56+Q62+Q68+Q74 -> 0
A49: Out-of-Home | E49: =SUM(F49:Q49) -> 0 | F49: =SUM(F50:F55) -> 0 | G49: =SUM(G50:G55) -> 0 | H49: =SUM(H50:H55) -> 0 | I49: =SUM(I50:I55) -> 0 | J49: =SUM(J50:J55) -> 0 | K49: =SUM(K50:K55) -> 0 | L49: =SUM(L50:L55) -> 0 | M49: =SUM(M50:M55) -> 0 | ... Q49: =SUM(Q50:Q55) -> 0
A50: - Billboard, neonbox, signboard, baliho, banner (outdoor), project signage & directory | B50: Billboard | E50: =SUM(F50:Q50) -> 0
A51: - Mobile ad, bus ad, taxi ad | B51: Billboard | E51: =SUM(F51:Q51) -> 0
E52: =SUM(F52:Q52) -> 0
E53: =SUM(F53:Q53) -> 0
E54: =SUM(F54:Q54) -> 0
E55: =SUM(F55:Q55) -> 0
A56: Point-of-Sale & Merchandising | E56: =SUM(F56:Q56) -> 0 | F56: =SUM(F57:F61) -> 0 | G56: =SUM(G57:G61) -> 0 | H56: =SUM(H57:H61) -> 0 | I56: =SUM(I57:I61) -> 0 | J56: =SUM(J57:J61) -> 0 | K56: =SUM(K57:K61) -> 0 | L56: =SUM(L57:L61) -> 0 | M56: =SUM(M57:M61) -> 0 | ... Q56: =SUM(Q57:Q61) -> 0
A57: - Poster, flyer, brochure, catalogue, city directory, map | B57: Media Cetak, Brosur, Spanduk, Katalog | E57: =SUM(F57:Q57) -> 0
A58: - In-door banner, roll-up banner, Floor display unit, trade marketing, etc | B58: Media Cetak, Brosur, Spanduk, Katalog | E58: =SUM(F58:Q58) -> 0
A59: - Corporate merchandise, giveaways, corporate attributes | B59: Media Cetak, Brosur, Spanduk, Katalog | E59: =SUM(F59:Q59) -> 0
E60: =SUM(F60:Q60) -> 0
E61: =SUM(F61:Q61) -> 0
A62: Corporate Presentation | E62: =SUM(F62:Q62) -> 0 | F62: =SUM(F63:F67) -> 0 | G62: =SUM(G63:G67) -> 0 | H62: =SUM(H63:H67) -> 0 | I62: =SUM(I63:I67) -> 0 | J62: =SUM(J63:J67) -> 0 | K62: =SUM(K63:K67) -> 0 | L62: =SUM(L63:L67) -> 0 | M62: =SUM(M63:M67) -> 0 | ... Q62: =SUM(Q63:Q67) -> 0
A63: - Video presentation, multimedia presentation | B63: Media Cetak, Brosur, Spanduk, Katalog | E63: =SUM(F63:Q63) -> 0
A64: - Company profile (printed) | B64: Media Cetak, Brosur, Spanduk, Katalog | E64: =SUM(F64:Q64) -> 0
A65: - Special communication (corp magazine, intranet, newsletter, portal, etc) | B65: Media Cetak, Brosur, Spanduk, Katalog | E65: =SUM(F65:Q65) -> 0
E66: =SUM(F66:Q66) -> 0
E67: =SUM(F67:Q67) -> 0
A68: Event & exhibition | E68: =SUM(F68:Q68) -> 0 | F68: =SUM(F69:F73) -> 0 | G68: =SUM(G69:G73) -> 0 | H68: =SUM(H69:H73) -> 0 | I68: =SUM(I69:I73) -> 0 | J68: =SUM(J69:J73) -> 0 | K68: =SUM(K69:K73) -> 0 | L68: =SUM(L69:L73) -> 0 | M68: =SUM(M69:M73) -> 0 | ... Q68: =SUM(Q69:Q73) -> 0
A69: - Launching, special events, internal/corporate events | B69: Events & Exibition | E69: =SUM(F69:Q69) -> 0
A70: - Exhibition & expo | B70: Events & Exibition | E70: =SUM(F70:Q70) -> 0
A71: - Sponsorship, co-branding, joint event, etc | B71: Events & Exibition | E71: =SUM(F71:Q71) -> 0
E72: =SUM(F72:Q72) -> 0
E73: =SUM(F73:Q73) -> 0
A74: Other (Direct mail,telemkt,sms,viral,etc) | E74: =SUM(F74:Q74) -> 0 | F74: =SUM(F75:F78) -> 0 | G74: =SUM(G75:G78) -> 0 | H74: =SUM(H75:H78) -> 0 | I74: =SUM(I75:I78) -> 0 | J74: =SUM(J75:J78) -> 0 | K74: =SUM(K75:K78) -> 0 | L74: =SUM(L75:L78) -> 0 | M74: =SUM(M75:M78) -> 0 | ... Q74: =SUM(Q75:Q78) -> 0
A75: - Direct Mail, telemarketing | B75: Beban Marketing Promosi Lainnya | E75: =SUM(F75:Q75) -> 0
A76: - SMS, Viral, social media | B76: Beban Marketing Promosi Lainnya | E76: =SUM(F76:Q76) -> 0
E77: =SUM(F77:Q77) -> 0
E78: =SUM(F78:Q78) -> 0
A80: Placement/distribution: | B80: Sub Chart | E80: =SUM(F80:Q80) -> 0 | F80: =F81+F86+F92+F98 -> 0 | G80: =G81+G86+G92+G98 -> 0 | H80: =H81+H86+H92+H98 -> 0 | I80: =I81+I86+I92+I98 -> 0 | J80: =J81+J86+J92+J98 -> 0 | K80: =K81+K86+K92+K98 -> 0 | L80: =L81+L86+L92+L98 -> 0 | M80: =M81+M86+M92+M98 -> 0 | ... Q80: =Q81+Q86+Q92+Q98 -> 0
A81: Out-of-Home (location fee, advertisement tax, etc) | E81: =SUM(F81:Q81) -> 0 | F81: =SUM(F82:F85) -> 0 | G81: =SUM(G82:G85) -> 0 | H81: =SUM(H82:H85) -> 0 | I81: =SUM(I82:I85) -> 0 | J81: =SUM(J82:J85) -> 0 | K81: =SUM(K82:K85) -> 0 | L81: =SUM(L82:L85) -> 0 | M81: =SUM(M82:M85) -> 0 | ... Q81: =SUM(Q82:Q85) -> 0
A82: - Billboard, neonbox, signboard, baliho, banner (outdoor), project signage & directory | B82: Beban Marketing Promosi Lainnya | E82: =SUM(F82:Q82) -> 0
A83: - Mobile ad, bus ad, taxi ad | B83: Beban Marketing Promosi Lainnya | E83: =SUM(F83:Q83) -> 0
E84: =SUM(F84:Q84) -> 0
E85: =SUM(F85:Q85) -> 0
A86: Point-of-Sale & Merchandising (cost of distribution) | E86: =SUM(F86:Q86) -> 0 | F86: =SUM(F87:F91) -> 0 | G86: =SUM(G87:G91) -> 0 | H86: =SUM(H87:H91) -> 0 | I86: =SUM(I87:I91) -> 0 | J86: =SUM(J87:J91) -> 0 | K86: =SUM(K87:K91) -> 0 | L86: =SUM(L87:L91) -> 0 | M86: =SUM(M87:M91) -> 0 | ... Q86: =SUM(Q87:Q91) -> 0
A87: - Poster, flyer, brochure, catalogue, city directory, map | B87: Media Cetak, Brosur, Spanduk, Katalog | E87: =SUM(F87:Q87) -> 0
A88: - In-door banner, roll-up banner, Floor display unit, trade marketing, etc | B88: Media Cetak, Brosur, Spanduk, Katalog | E88: =SUM(F88:Q88) -> 0
A89: - Corporate merchandise, giveaways, corporate attributes | B89: Media Cetak, Brosur, Spanduk, Katalog | E89: =SUM(F89:Q89) -> 0
E90: =SUM(F90:Q90) -> 0
E91: =SUM(F91:Q91) -> 0
A92: Corporate Presentation (cost of distribution) | E92: =SUM(F92:Q92) -> 0 | F92: =SUM(F93:F97) -> 0 | G92: =SUM(G93:G97) -> 0 | H92: =SUM(H93:H97) -> 0 | I92: =SUM(I93:I97) -> 0 | J92: =SUM(J93:J97) -> 0 | K92: =SUM(K93:K97) -> 0 | L92: =SUM(L93:L97) -> 0 | M92: =SUM(M93:M97) -> 0 | ... Q92: =SUM(Q93:Q97) -> 0
A93: - Video presentation, multimedia presentation | B93: Media Digital, Online, TV, Radio | E93: =SUM(F93:Q93) -> 0
A94: - Company profile (printed) | B94: Media Cetak, Brosur, Spanduk, Katalog | E94: =SUM(F94:Q94) -> 0
A95: - Special communication (corp magazine, intranet, newsletter, portal, etc) | B95: Media Cetak, Brosur, Spanduk, Katalog | E95: =SUM(F95:Q95) -> 0
E96: =SUM(F96:Q96) -> 0
E97: =SUM(F97:Q97) -> 0
A98: Other (cost of placement/blast) | E98: =SUM(F98:Q98) -> 0 | F98: =SUM(F99:F102) -> 0 | G98: =SUM(G99:G102) -> 0 | H98: =SUM(H99:H102) -> 0 | I98: =SUM(I99:I102) -> 0 | J98: =SUM(J99:J102) -> 0 | K98: =SUM(K99:K102) -> 0 | L98: =SUM(L99:L102) -> 0 | M98: =SUM(M99:M102) -> 0 | ... Q98: =SUM(Q99:Q102) -> 0
A99: - Direct Mail, telemarketing | B99: Beban Marketing Promosi Lainnya | E99: =SUM(F99:Q99) -> 0
A100: - SMS, Viral | B100: Beban Marketing Promosi Lainnya | E100: =SUM(F100:Q100) -> 0
E101: =SUM(F101:Q101) -> 0
E102: =SUM(F102:Q102) -> 0
A104: ESTIMATED MARKETING BUDGET PLAN GRAND TOTAL | E104: =SUM(F104:Q104) -> 0 | F104: =F47+F12 -> 0 | G104: =G47+G12 -> 0 | H104: =H47+H12 -> 0 | I104: =I47+I12 -> 0 | J104: =J47+J12 -> 0 | K104: =K47+K12 -> 0 | L104: =L47+L12 -> 0 | M104: =M47+M12 -> 0 | ... Q104: =Q47+Q12 -> 0
F115: YTD JAN | G115: YTD FEB | H115: YTD MAR | I115: YTD APR | J115: YTD MAY | K115: YTD JUN | L115: YTD JUL | M115: YTD AUG | N115: YTD SEP | O115: YTD OCT | P115: YTD NOV | Q115: YTD DEC
F116: =SUM($F$104:F104) -> 0 | G116: =SUM($F$104:G104) -> 0 | H116: =SUM($F$104:H104) -> 0 | I116: =SUM($F$104:I104) -> 0 | J116: =SUM($F$104:J104) -> 0 | K116: =SUM($F$104:K104) -> 0 | L116: =SUM($F$104:L104) -> 0 | M116: =SUM($F$104:M104) -> 0 | ... Q116: =SUM($F$104:Q104) -> 0

Sheet Budget Employee
B2: EMPLOYEE
B3: ENTITAS: | C3: PT Perintis Triniti Properti Tbk
B4: PROJECT | C4: Head Office
B5: BUDGET YEARS | C5: 2026
C7: 46023 | D7: 46054 | E7: 46082 | F7: 46113 | G7: 46143 | H7: 46174 | I7: 46204 | J7: 46235 | K7: 46266 | L7: 46296 | M7: 46327 | N7: 46357 | O7: TOTAL
B8: Salary | O8: =SUM(C8:N8) -> 0 | P8: Gaji Terakhir
B10: TAX | O10: =SUM(C10:N10) -> 0 | P10: Pajak Terakhir
B11: BPJS | O11: =SUM(C11:N11) -> 0 | P11: BPJS TK 16jt, Kes 2,1jt (terakhir)
O12: =SUM(C12:N12) -> 0
B13: Total Cost | C13: =SUM(C8:C12) -> 0 | D13: =SUM(D8:D12) -> 0 | E13: =SUM(E8:E12) -> 0 | F13: =SUM(F8:F12) -> 0 | G13: =SUM(G8:G12) -> 0 | H13: =SUM(H8:H12) -> 0 | I13: =SUM(I8:I12) -> 0 | J13: =SUM(J8:J12) -> 0 | ... O13: =SUM(O8:O12) -> 0
A17: 1 | C17: YTD JAN | D17: YTD FEB | E17: YTD MAR | F17: YTD APR | G17: YTD MAY | H17: YTD JUN | I17: YTD JUL | J17: YTD AUG | K17: YTD SEP | L17: YTD OCT | M17: YTD NOV | N17: YTD DEC
A18: =A17+1 -> 2 | B18: TOTAL | C18: =SUM($C$13:C13) -> 0 | D18: =SUM($C$13:D13) -> 0 | E18: =SUM($C$13:E13) -> 0 | F18: =SUM($C$13:F13) -> 0 | G18: =SUM($C$13:G13) -> 0 | H18: =SUM($C$13:H13) -> 0 | I18: =SUM($C$13:I13) -> 0 | J18: =SUM($C$13:J13) -> 0 | ... N18: =SUM($C$13:N13) -> 0
C20: =SUM(C18:C19) -> 0 | D20: =SUM(D18:D19) -> 0 | E20: =SUM(E18:E19) -> 0 | F20: =SUM(F18:F19) -> 0 | G20: =SUM(G18:G19) -> 0 | H20: =SUM(H18:H19) -> 0 | I20: =SUM(I18:I19) -> 0 | J20: =SUM(J18:J19) -> 0 | ... N20: =SUM(N18:N19) -> 0

Sheet Dev&Land Budget Plan Cost
D1: DEVELOPMENT BUDGET PLANNING
D2: ENTITAS: | E2: Pilih Perusahaan
D3: PROJECT | E3: Pilih Project
D4: BUDGET YEARS | E4: 2027
B6: A. | C6: DEVELOPMENT COST | E6: SQM | F6: Cost / sqm | G6: Total Nilai RAB / SPK | H6: Total Nilai Realisasi s.d 31 July 2026 | I6: Best Estrimate ( Aug - Des 2026 ) | J6: % Realisasi | L6: Total Nilai Budget 2027 | M6: 46388 | N6: 46419 | O6: 46447 | P6: 46478 | Q6: 46508 | R6: 46539 | S6: 46569 | T6: 46600 | U6: 46631 | V6: 46661 | W6: 46692 | X6: 46722 | Y6: H1 | Z6: H2 | AA6: TOTAL | AB6: H1 | AC6: H2 | AD6: TOTAL
B7: 1 | C7: Land Cost | L7: =SUM(L8,L11) -> 0 | M7: =SUM(M8,M11) -> 0 | N7: =SUM(N8,N11) -> 0 | O7: =SUM(O8,O11) -> 0 | P7: =SUM(P8,P11) -> 0 | Q7: =SUM(Q8,Q11) -> 0 | R7: =SUM(R8,R11) -> 0 | S7: =SUM(S8,S11) -> 0 | ... X7: =SUM(X8,X11) -> 0
C8: 1.1 | D8: Land Improvement Cost | L8: =SUM(M8:X8) -> 0 | M8: =SUM(M9:M10) -> 0 | N8: =SUM(N9:N10) -> 0 | O8: =SUM(O9:O10) -> 0 | P8: =SUM(P9:P10) -> 0 | Q8: =SUM(Q9:Q10) -> 0 | R8: =SUM(R9:R10) -> 0 | S8: =SUM(S9:S10) -> 0 | T8: =SUM(T9:T10) -> 0 | ... X8: =SUM(X9:X10) -> 0
D9: a | J9: =IFERROR((H9+I9)/G9,0) -> 0 | L9: =SUM(M9:X9) -> 0
D10: b | J10: =IFERROR((H10+I10)/G10,0) -> 0 | L10: =SUM(M10:X10) -> 0
C11: 1.2 | D11: Land Acquisition Cost | L11: =SUM(M11:X11) -> 0 | M11: =SUM(M12:M13) -> 0 | N11: =SUM(N12:N13) -> 0 | O11: =SUM(O12:O13) -> 0 | P11: =SUM(P12:P13) -> 0 | Q11: =SUM(Q12:Q13) -> 0 | R11: =SUM(R12:R13) -> 0 | S11: =SUM(S12:S13) -> 0 | T11: =SUM(T12:T13) -> 0 | ... X11: =SUM(X12:X13) -> 0
D12: a | J12: =IFERROR((H12+I12)/G12,0) -> 0 | L12: =SUM(M12:X12) -> 0
D13: b | J13: =IFERROR((H13+I13)/G13,0) -> 0 | L13: =SUM(M13:X13) -> 0
B15: 2 | C15: Development Cost | L15: =SUM(M15:X15) -> 0 | M15: =SUM(M16,M46) -> 0 | N15: =SUM(N16,N46) -> 0 | O15: =SUM(O16,O46) -> 0 | P15: =SUM(P16,P46) -> 0 | Q15: =SUM(Q16,Q46) -> 0 | R15: =SUM(R16,R46) -> 0 | S15: =SUM(S16,S46) -> 0 | T15: =SUM(T16,T46) -> 0 | ... X15: =SUM(X16,X46) -> 0
C16: Hard Cost | L16: =SUM(M16:X16) -> 0 | M16: =SUM(M17,M21,M25,M29,M33,M37,M41) -> 0 | N16: =SUM(N17,N21,N25,N29,N33,N37,N41) -> 0 | O16: =SUM(O17,O21,O25,O29,O33,O37,O41) -> 0 | P16: =SUM(P17,P21,P25,P29,P33,P37,P41) -> 0 | Q16: =SUM(Q17,Q21,Q25,Q29,Q33,Q37,Q41) -> 0 | R16: =SUM(R17,R21,R25,R29,R33,R37,R41) -> 0 | S16: =SUM(S17,S21,S25,S29,S33,S37,S41) -> 0 | T16: =SUM(T17,T21,T25,T29,T33,T37,T41) -> 0 | ... X16: =SUM(X17,X21,X25,X29,X33,X37,X41) -> 0
C17: 2.1 | D17: Preliminaries | L17: =SUM(M17:X17) -> 0 | M17: =SUM(M18:M20) -> 0 | N17: =SUM(N18:N20) -> 0 | O17: =SUM(O18:O20) -> 0 | P17: =SUM(P18:P20) -> 0 | Q17: =SUM(Q18:Q20) -> 0 | R17: =SUM(R18:R20) -> 0 | S17: =SUM(S18:S20) -> 0 | T17: =SUM(T18:T20) -> 0 | ... X17: =SUM(X18:X20) -> 0
D18: a | J18: =IFERROR((H18+I18)/G18,0) -> 0 | L18: =SUM(M18:X18) -> 0
D19: b | J19: =IFERROR((H19+I19)/G19,0) -> 0 | L19: =SUM(M19:X19) -> 0
D20: c | L20: =SUM(M20:X20) -> 0
C21: 2.2 | D21: Pre-Construction | L21: =SUM(M21:X21) -> 0 | M21: =SUM(M22:M24) -> 0 | N21: =SUM(N22:N24) -> 0 | O21: =SUM(O22:O24) -> 0 | P21: =SUM(P22:P24) -> 0 | Q21: =SUM(Q22:Q24) -> 0 | R21: =SUM(R22:R24) -> 0 | S21: =SUM(S22:S24) -> 0 | T21: =SUM(T22:T24) -> 0 | ... X21: =SUM(X22:X24) -> 0
D22: a | J22: =IFERROR((H22+I22)/G22,0) -> 0 | L22: =SUM(M22:X22) -> 0
D23: b | J23: =IFERROR((H23+I23)/G23,0) -> 0 | L23: =SUM(M23:X23) -> 0
D24: c | L24: =SUM(M24:X24) -> 0
C25: 2.3 | D25: Building Construction Cost | L25: =SUM(M25:X25) -> 0 | M25: =SUM(M26:M28) -> 0 | N25: =SUM(N26:N28) -> 0 | O25: =SUM(O26:O28) -> 0 | P25: =SUM(P26:P28) -> 0 | Q25: =SUM(Q26:Q28) -> 0 | R25: =SUM(R26:R28) -> 0 | S25: =SUM(S26:S28) -> 0 | T25: =SUM(T26:T28) -> 0 | ... X25: =SUM(X26:X28) -> 0
D26: a | J26: =IFERROR((H26+I26)/G26,0) -> 0 | L26: =SUM(M26:X26) -> 0
D27: b | J27: =IFERROR((H27+I27)/G27,0) -> 0 | L27: =SUM(M27:X27) -> 0
D28: c | L28: =SUM(M28:X28) -> 0
C29: 2.4 | D29: Parking Construction Cost | L29: =SUM(M29:X29) -> 0 | M29: =SUM(M30:M32) -> 0 | N29: =SUM(N30:N32) -> 0 | O29: =SUM(O30:O32) -> 0 | P29: =SUM(P30:P32) -> 0 | Q29: =SUM(Q30:Q32) -> 0 | R29: =SUM(R30:R32) -> 0 | S29: =SUM(S30:S32) -> 0 | T29: =SUM(T30:T32) -> 0 | ... X29: =SUM(X30:X32) -> 0
D30: a | J30: =IFERROR((H30+I30)/G30,0) -> 0 | L30: =SUM(M30:X30) -> 0
D31: b | J31: =IFERROR((H31+I31)/G31,0) -> 0 | L31: =SUM(M31:X31) -> 0
D32: c | L32: =SUM(M32:X32) -> 0
C33: 2.5 | D33: Infrastructure Cost | L33: =SUM(M33:X33) -> 0 | M33: =SUM(M34:M36) -> 0 | N33: =SUM(N34:N36) -> 0 | O33: =SUM(O34:O36) -> 0 | P33: =SUM(P34:P36) -> 0 | Q33: =SUM(Q34:Q36) -> 0 | R33: =SUM(R34:R36) -> 0 | S33: =SUM(S34:S36) -> 0 | T33: =SUM(T34:T36) -> 0 | ... X33: =SUM(X34:X36) -> 0
D34: a | J34: =IFERROR((H34+I34)/G34,0) -> 0 | L34: =SUM(M34:X34) -> 0
D35: b | J35: =IFERROR((H35+I35)/G35,0) -> 0 | L35: =SUM(M35:X35) -> 0
D36: c | L36: =SUM(M36:X36) -> 0
C37: 2.6 | D37: Facilities Construction Cost | L37: =SUM(M37:X37) -> 0 | M37: =SUM(M38:M40) -> 0 | N37: =SUM(N38:N40) -> 0 | O37: =SUM(O38:O40) -> 0 | P37: =SUM(P38:P40) -> 0 | Q37: =SUM(Q38:Q40) -> 0 | R37: =SUM(R38:R40) -> 0 | S37: =SUM(S38:S40) -> 0 | T37: =SUM(T38:T40) -> 0 | ... X37: =SUM(X38:X40) -> 0
D38: a | J38: =IFERROR((H38+I38)/G38,0) -> 0 | L38: =SUM(M38:X38) -> 0
D39: b | J39: =IFERROR((H39+I39)/G39,0) -> 0 | L39: =SUM(M39:X39) -> 0
D40: c | L40: =SUM(M40:X40) -> 0
C41: 2.7 | D41: Main Gate Construction Cost | L41: =SUM(M41:X41) -> 0 | M41: =SUM(M42:M44) -> 0 | N41: =SUM(N42:N44) -> 0 | O41: =SUM(O42:O44) -> 0 | P41: =SUM(P42:P44) -> 0 | Q41: =SUM(Q42:Q44) -> 0 | R41: =SUM(R42:R44) -> 0 | S41: =SUM(S42:S44) -> 0 | T41: =SUM(T42:T44) -> 0 | ... X41: =SUM(X42:X44) -> 0
D42: a | J42: =IFERROR((H42+I42)/G42,0) -> 0 | L42: =SUM(M42:X42) -> 0
D43: b | J43: =IFERROR((H43+I43)/G43,0) -> 0 | L43: =SUM(M43:X43) -> 0
D44: c | L44: =SUM(M44:X44) -> 0
C46: Soft Cost
C47: 2.8 | D47: Legal, License, & Permits | L47: =SUM(M47:X47) -> 0 | M47: =SUM(M48:M50) -> 0 | N47: =SUM(N48:N50) -> 0 | O47: =SUM(O48:O50) -> 0 | P47: =SUM(P48:P50) -> 0 | Q47: =SUM(Q48:Q50) -> 0 | R47: =SUM(R48:R50) -> 0 | S47: =SUM(S48:S50) -> 0 | T47: =SUM(T48:T50) -> 0 | ... X47: =SUM(X48:X50) -> 0
D48: a | J48: =IFERROR((H48+I48)/G48,0) -> 0 | L48: =SUM(M48:X48) -> 0
D49: b | J49: =IFERROR((H49+I49)/G49,0) -> 0 | L49: =SUM(M49:X49) -> 0
C51: 2.9 | D51: Design & Professional Fees | L51: =SUM(M51:X51) -> 0 | M51: =SUM(M52:M57) -> 0 | N51: =SUM(N52:N57) -> 0 | O51: =SUM(O52:O57) -> 0 | P51: =SUM(P52:P57) -> 0 | Q51: =SUM(Q52:Q57) -> 0 | R51: =SUM(R52:R57) -> 0 | S51: =SUM(S52:S57) -> 0 | T51: =SUM(T52:T57) -> 0 | ... X51: =SUM(X52:X57) -> 0
D52: a. Master Planner | J52: =IFERROR((H52+I52)/G52,0) -> 0 | L52: =SUM(M52:X52) -> 0
D53: b. Architecture | J53: =IFERROR((H53+I53)/G53,0) -> 0 | L53: =SUM(M53:X53) -> 0
D54: c. Land Survey | J54: =IFERROR((H54+I54)/G54,0) -> 0 | L54: =SUM(M54:X54) -> 0
D55: d. Consutant | J55: =IFERROR((H55+I55)/G55,0) -> 0 | L55: =SUM(M55:X55) -> 0
D56: e | J56: =IFERROR((H56+I56)/G56,0) -> 0
D58: TOTAL LAND & DEVELOPMENT COST | G58: =SUM(G7:G57) -> 0 | H58: =SUM(H7:H57) -> 0 | J58: =IFERROR((H58+I58)/G58,0) -> 0 | L58: =SUM(L7,L15) -> 0 | M58: =SUM(M7,M15) -> 0 | N58: =SUM(N7,N15) -> 0 | O58: =SUM(O7,O15) -> 0 | P58: =SUM(P7,P15) -> 0 | Q58: =SUM(Q7,Q15) -> 0 | R58: =SUM(R7,R15) -> 0 | S58: =SUM(S7,S15) -> 0 | ... X58: =SUM(X7,X15) -> 0 | Y58: =SUM(Y7:Y57) -> 0 | Z58: =SUM(Z7:Z57) -> 0 | AA58: =SUM(AA7:AA57) -> 0 | AB58: =SUM(AB7:AB57) -> 0 | AC58: =SUM(AC7:AC57) -> 0 | AD58: =SUM(AD7:AD57) -> 0
D61: Catatan
D62: 1. Nilai yang harus diisi sesuai dengan SPK yang sudah disepakati
D63: 2. Apabila pekerjaan pembangunan, konsultan belum ada SPK maka diisi berdasarkan nilai RAB terupdate
D64: 3. Apabila pekerjaan tersebut sudah berlangsung dari periode sebelumnya dan akan berlanjut di tahun Budget maka nilai Budget yang diisi sesuai dengan jadwal progress pada tahun Budget
D65: 4. Agar dilampirkan rencana progress pekerjaan (Timeline) pada periode tahun Budget
C73: 1 | M73: YTD JAN | N73: YTD FEB | O73: YTD MAR | P73: YTD APR | Q73: YTD MAY | R73: YTD JUN | S73: YTD JUL | T73: YTD AUG | U73: YTD SEP | V73: YTD OCT | W73: YTD NOV | X73: YTD DEC
C74: =C73+1 -> 2 | D74: =D8 -> Land Improvement Cost | M74: =SUM($M$8:M8) -> 0 | N74: =SUM($M$8:N8) -> 0 | O74: =SUM($M$8:O8) -> 0 | P74: =SUM($M$8:P8) -> 0 | Q74: =SUM($M$8:Q8) -> 0 | R74: =SUM($M$8:R8) -> 0 | S74: =SUM($M$8:S8) -> 0 | T74: =SUM($M$8:T8) -> 0 | ... X74: =SUM($M$8:X8) -> 0
C75: =C74+1 -> 3 | D75: =D11 -> Land Acquisition Cost | M75: =SUM($M$11:M11) -> 0 | N75: =SUM($M$11:N11) -> 0 | O75: =SUM($M$11:O11) -> 0 | P75: =SUM($M$11:P11) -> 0 | Q75: =SUM($M$11:Q11) -> 0 | R75: =SUM($M$11:R11) -> 0 | S75: =SUM($M$11:S11) -> 0 | T75: =SUM($M$11:T11) -> 0 | ... X75: =SUM($M$11:X11) -> 0
C76: =C75+1 -> 4 | D76: =D17 -> Preliminaries | M76: =SUM($M$17:M17) -> 0 | N76: =SUM($M$17:N17) -> 0 | O76: =SUM($M$17:O17) -> 0 | P76: =SUM($M$17:P17) -> 0 | Q76: =SUM($M$17:Q17) -> 0 | R76: =SUM($M$17:R17) -> 0 | S76: =SUM($M$17:S17) -> 0 | T76: =SUM($M$17:T17) -> 0 | ... X76: =SUM($M$17:X17) -> 0
C77: =C76+1 -> 5 | D77: =D21 -> Pre-Construction | M77: =SUM($M$21:M21) -> 0 | N77: =SUM($M$21:N21) -> 0 | O77: =SUM($M$21:O21) -> 0 | P77: =SUM($M$21:P21) -> 0 | Q77: =SUM($M$21:Q21) -> 0 | R77: =SUM($M$21:R21) -> 0 | S77: =SUM($M$21:S21) -> 0 | T77: =SUM($M$21:T21) -> 0 | ... X77: =SUM($M$21:X21) -> 0
C78: =C77+1 -> 6 | D78: =D25 -> Building Construction Cost | M78: =SUM($M$25:M25) -> 0 | N78: =SUM($M$25:N25) -> 0 | O78: =SUM($M$25:O25) -> 0 | P78: =SUM($M$25:P25) -> 0 | Q78: =SUM($M$25:Q25) -> 0 | R78: =SUM($M$25:R25) -> 0 | S78: =SUM($M$25:S25) -> 0 | T78: =SUM($M$25:T25) -> 0 | ... X78: =SUM($M$25:X25) -> 0
C79: =C78+1 -> 7 | D79: =D29 -> Parking Construction Cost | M79: =SUM($M$29:M29) -> 0 | N79: =SUM($M$29:N29) -> 0 | O79: =SUM($M$29:O29) -> 0 | P79: =SUM($M$29:P29) -> 0 | Q79: =SUM($M$29:Q29) -> 0 | R79: =SUM($M$29:R29) -> 0 | S79: =SUM($M$29:S29) -> 0 | T79: =SUM($M$29:T29) -> 0 | ... X79: =SUM($M$29:X29) -> 0
C80: =C79+1 -> 8 | D80: =D33 -> Infrastructure Cost | M80: =SUM($M$33:M33) -> 0 | N80: =SUM($M$33:N33) -> 0 | O80: =SUM($M$33:O33) -> 0 | P80: =SUM($M$33:P33) -> 0 | Q80: =SUM($M$33:Q33) -> 0 | R80: =SUM($M$33:R33) -> 0 | S80: =SUM($M$33:S33) -> 0 | T80: =SUM($M$33:T33) -> 0 | ... X80: =SUM($M$33:X33) -> 0
C81: =C80+1 -> 9 | D81: =D37 -> Facilities Construction Cost | M81: =SUM($M$37:M37) -> 0 | N81: =SUM($M$37:N37) -> 0 | O81: =SUM($M$37:O37) -> 0 | P81: =SUM($M$37:P37) -> 0 | Q81: =SUM($M$37:Q37) -> 0 | R81: =SUM($M$37:R37) -> 0 | S81: =SUM($M$37:S37) -> 0 | T81: =SUM($M$37:T37) -> 0 | ... X81: =SUM($M$37:X37) -> 0
C82: =C81+1 -> 10 | D82: =D41 -> Main Gate Construction Cost | M82: =SUM($M$41:M41) -> 0 | N82: =SUM($M$41:N41) -> 0 | O82: =SUM($M$41:O41) -> 0 | P82: =SUM($M$41:P41) -> 0 | Q82: =SUM($M$41:Q41) -> 0 | R82: =SUM($M$41:R41) -> 0 | S82: =SUM($M$41:S41) -> 0 | T82: =SUM($M$41:T41) -> 0 | ... X82: =SUM($M$41:X41) -> 0
C83: =C82+1 -> 11 | D83: =D47 -> Legal, License, & Permits | M83: =SUM($M$47:M47) -> 0 | N83: =SUM($M$47:N47) -> 0 | O83: =SUM($M$47:O47) -> 0 | P83: =SUM($M$47:P47) -> 0 | Q83: =SUM($M$47:Q47) -> 0 | R83: =SUM($M$47:R47) -> 0 | S83: =SUM($M$47:S47) -> 0 | T83: =SUM($M$47:T47) -> 0 | ... X83: =SUM($M$47:X47) -> 0
C84: =C83+1 -> 12 | D84: =D51 -> Design & Professional Fees | M84: =SUM($M$52:M57) -> 0 | N84: =SUM($M$51:N51) -> 0 | O84: =SUM($M$51:O51) -> 0 | P84: =SUM($M$51:P51) -> 0 | Q84: =SUM($M$51:Q51) -> 0 | R84: =SUM($M$51:R51) -> 0 | S84: =SUM($M$51:S51) -> 0 | T84: =SUM($M$51:T51) -> 0 | U84: =SUM($M$51:U51) -> 0 | ... X84: =SUM($M$51:X51) -> 0
M85: =SUM(M74:M84) -> 0 | N85: =SUM(N74:N84) -> 0 | O85: =SUM(O74:O84) -> 0 | P85: =SUM(P74:P84) -> 0 | Q85: =SUM(Q74:Q84) -> 0 | R85: =SUM(R74:R84) -> 0 | S85: =SUM(S74:S84) -> 0 | T85: =SUM(T74:T84) -> 0 | ... X85: =SUM(X74:X84) -> 0

Sheet Budget G&A
A1: BUDGET G&A Expenses
A2: ENTITAS: | B2: Pilih Perusahaan
A3: PROJECT | B3: Pilih Project
A4: Division
A5: BUDGET YEARS | B5: 2027
A7: No Akun | B7: Keterangan Biaya | C7: Rincian Budget | D7: Budget Tahun 2027 | E7: 46388 | F7: 46419 | G7: 46447 | H7: 46478 | I7: 46508 | J7: 46539 | K7: 46569 | L7: 46600 | M7: 46631 | N7: 46661 | O7: 46692 | P7: 46722
A8: 62210001 | B8: BEBAN PEMELIHARAAN & RENOVASI BANGUNAN KANTOR | D8: =SUM(E8:P8) -> 0
A9: 62210002 | B9: BEBAN PEMELIHARAAN INVENTARIS KANTOR | D9: =SUM(E9:P9) -> 0
A10: 62210003 | B10: BEBAN PEMELIHARAAN KENDARAAN KANTOR | D10: =SUM(E10:P10) -> 0
A11: 62220001 | B11: BEBAN SEWA BANGUNAN UNTUK OPERASIONAL KANTOR | D11: =SUM(E11:P11) -> 0
A12: 62220002 | B12: BEBAN SEWA RUMAH MESS UNTUK OPERASIONAL | D12: =SUM(E12:P12) -> 0
A13: 62220003 | B13: BEBAN SEWA GEDUNG UNTUK ACARA KANTOR | D13: =SUM(E13:P13) -> 0
A14: 62220004 | B14: BEBAN SEWA KENDARAAN | D14: =SUM(E14:P14) -> 0
A15: 62220005 | B15: BEBAN SEWA LAINNYA | D15: =SUM(E15:P15) -> 0
A16: 62220006 | B16: BEBAN SEWA PERALATAN | D16: =SUM(E16:P16) -> 0
A17: 62220007 | B17: BEBAN SEWA RUMAH DINAS / MESS KARYAWAN | D17: =SUM(E17:P17) -> 0
A18: 62220008 | B18: BEBAN SEWA PERALATAN KANTOR | D18: =SUM(E18:P18) -> 0
A19: 62230001 | B19: BEBAN ASURANSI BANGUNAN KANTOR | D19: =SUM(E19:P19) -> 0
... A62: 62280016 | B62: BEBAN KANTOR HAND OVER | D62: =SUM(E62:P62) -> 0
D63: =SUM(D8:D62) -> 0 | E63: =SUM(E8:E62) -> 0 | F63: =SUM(F8:F62) -> 0 | G63: =SUM(G8:G62) -> 0 | H63: =SUM(H8:H62) -> 0 | I63: =SUM(I8:I62) -> 0 | J63: =SUM(J8:J62) -> 0 | K63: =SUM(K8:K62) -> 0 | ... P63: =SUM(P8:P62) -> 0
C67: TOTAL | E67: YTD JAN | F67: YTD FEB | G67: YTD MAR | H67: YTD APR | I67: YTD MAY | J67: YTD JUN | K67: YTD JUL | L67: YTD AUG | M67: YTD SEP | N67: YTD OCT | O67: YTD NOV | P67: YTD DEC
E68: =SUM(E63) -> 0 | F68: =SUM($E$63:F$63) -> 0 | G68: =SUM($E$63:G$63) -> 0 | H68: =SUM($E$63:H$63) -> 0 | I68: =SUM($E$63:I$63) -> 0 | J68: =SUM($E$63:J$63) -> 0 | K68: =SUM($E$63:K$63) -> 0 | L68: =SUM($E$63:L$63) -> 0 | M68: =SUM($E$63:M$63) -> 0 | ... P68: =SUM($E$63:P$63) -> 0

Sheet Budget Others
A1: BUDGET Others
A2: ENTITAS: | B2: Pilih Perusahaan
A3: PROJECT | B3: Pilih Project
A4: Division
A5: BUDGET YEARS | B5: 2027
A7: No Akun | B7: Keterangan Biaya | C7: Rincian Budget | D7: Budget Tahun 2027 | E7: 46388 | F7: 46419 | G7: 46447 | H7: 46478 | I7: 46508 | J7: 46539 | K7: 46569 | L7: 46600 | M7: 46631 | N7: 46661 | O7: 46692 | P7: 46722
A8: 71110001 | B8: PENDAPATAN BUNGA | D8: =SUM(E8:P8) -> 0
A9: 71110002 | B9: PENDAPATAN BUNGA DEPOSITO | D9: =SUM(E9:P9) -> 0
A10: 71110003 | B10: PENDAPATAN BUNGA JASA GIRO | D10: =SUM(E10:P10) -> 0
A11: 71110004 | B11: PENDAPATAN BUNGA OBLIGASI | D11: =SUM(E11:P11) -> 0
A12: 71120001 | B12: PENDAPATAN DENDA PENJUALAN | D12: =SUM(E12:P12) -> 0
A13: 71120002 | B13: PENDAPATAN JASA GIRO | D13: =SUM(E13:P13) -> 0
A14: 71120003 | B14: PENDAPATAN ADMINISTRASI PENJUALAN | D14: =SUM(E14:P14) -> 0
A15: 71120004 | B15: PENDAPATAN ATAS PENJUALAN ASET TETAP | D15: =SUM(E15:P15) -> 0
A16: 71120005 | B16: PENDAPATAN INSENTIF KPA | D16: =SUM(E16:P16) -> 0
A17: 71120006 | B17: PENDAPATAN KOMPREHENSIF LAIN - PASKA KERJA | D17: =SUM(E17:P17) -> 0
A18: 71120007 | B18: PENDAPATAN LAIN-LAIN | D18: =SUM(E18:P18) -> 0
A19: 71120008 | B19: REIMBURSMENT (BILLING RATE) | D19: =SUM(E19:P19) -> 0
... A46: 72120018 | B46: BEBAN KOMPREHENSIF LAIN - PASKA KERJA | D46: =SUM(E46:P46) -> 0
E47: =SUM(E8:E46) -> 0 | F47: =SUM(F8:F46) -> 0 | G47: =SUM(G8:G46) -> 0 | H47: =SUM(H8:H46) -> 0 | I47: =SUM(I8:I46) -> 0 | J47: =SUM(J8:J46) -> 0 | K47: =SUM(K8:K46) -> 0 | L47: =SUM(L8:L46) -> 0 | ... P47: =SUM(P8:P46) -> 0
E48: YTD JAN | F48: YTD FEB | G48: YTD MAR | H48: YTD APR | I48: YTD MAY | J48: YTD JUN | K48: YTD JUL | L48: YTD AUG | M48: YTD SEP | N48: YTD OCT | O48: YTD NOV | P48: YTD DEC
E49: =SUM(E47) -> 0 | F49: =SUM($E$47:F$47) -> 0 | G49: =SUM($E$47:G$47) -> 0 | H49: =SUM($E$47:H$47) -> 0 | I49: =SUM($E$47:I$47) -> 0 | J49: =SUM($E$47:J$47) -> 0 | K49: =SUM($E$47:K$47) -> 0 | L49: =SUM($E$47:L$47) -> 0 | M49: =SUM($E$47:M$47) -> 0 | ... P49: =SUM($E$47:P$47) -> 0

Sheet Budget Finance Expenses
A1: BUDGET Finance expense
A2: ENTITAS: | B2: Pilih Perusahaan
A3: PROJECT | B3: Pilih Project
A4: Division
A5: BUDGET YEARS | B5: 2027
A7: No Akun | B7: Keterangan Biaya | C7: Rincian Budget | D7: Budget Tahun 2027 | E7: 46388 | F7: 46419 | G7: 46447 | H7: 46478 | I7: 46508 | J7: 46539 | K7: 46569 | L7: 46600 | M7: 46631 | N7: 46661 | O7: 46692 | P7: 46722
A8: 72110001 | B8: BEBAN BUNGA PINJAMAN | D8: =SUM(E8:P8) -> 0
A9: 72110002 | B9: BEBAN PROVISI DAN ADM PINJAMAN | D9: =SUM(E9:P9) -> 0
A10: 72110003 | B10: BEBAN ASURANSI ATAS PINJAMAN | D10: =SUM(E10:P10) -> 0
A11: 72110004 | B11: BEBAN LINDUNG NILAI ATAS PINJAMAN | D11: =SUM(E11:P11) -> 0
A12: 72120007 | B12: BIAYA BUNGA, PROVISI & ADM PINJAMAN | D12: =SUM(E12:P12) -> 0
A13: 72120015 | B13: PAJAK BUNGA DEPOSITO | D13: =SUM(E13:P13) -> 0
A14: 72120019 | B14: BEBAN LAIN-LAIN | D14: =SUM(E14:P14) -> 0
A15: 72120020 | B15: BEBAN BUNGA UANG MUKA PELANGGAN | D15: =SUM(E15:P15) -> 0
A16: 11610010 | B16: UANG MUKA PROYEK | D16: =SUM(E16:P16) -> 0
A17: TOTAL | D17: =SUM(D8:D16) -> 0 | E17: =SUM(E8:E16) -> 0 | F17: =SUM(F8:F16) -> 0 | G17: =SUM(G8:G16) -> 0 | H17: =SUM(H8:H16) -> 0 | I17: =SUM(I8:I16) -> 0 | J17: =SUM(J8:J16) -> 0 | K17: =SUM(K8:K16) -> 0 | ... P17: =SUM(P8:P16) -> 0
E19: YTD JAN | F19: YTD FEB | G19: YTD MAR | H19: YTD APR | I19: YTD MAY | J19: YTD JUN | K19: YTD JUL | L19: YTD AUG | M19: YTD SEP | N19: YTD OCT | O19: YTD NOV | P19: YTD DEC
C20: TOTAL | E20: =SUM(E17) -> 0 | F20: =SUM($E$17:F$17) -> 0 | G20: =SUM($E$17:G$17) -> 0 | H20: =SUM($E$17:H$17) -> 0 | I20: =SUM($E$17:I$17) -> 0 | J20: =SUM($E$17:J$17) -> 0 | K20: =SUM($E$17:K$17) -> 0 | L20: =SUM($E$17:L$17) -> 0 | M20: =SUM($E$17:M$17) -> 0 | ... P20: =SUM($E$17:P$17) -> 0

Sheet Budget Corp Event Exihibition
A1: CORPORATE EVENT & EXHIBITION PLANNING
A2: ENTITAS: | B2: Pilih Perusahaan
A3: PROJECT: | B3: Pilih Project
A4: DIVISION: | G4: Corsec / Investor & Public Relation / HC Even/ Training & Development
A5: BUDGET YEAR: | B5: 2027
A7: =B4&" "&"Budget Plan" -> Budget Plan | F7: 2027
A8: Activitiy | B8: Classification | C8: Estimated Quantity | D8: Estimated Cost per Unit | E8: Estimated Subtotal | F8: 46388 | G8: 46419 | H8: 46447 | I8: 46478 | J8: 46508 | K8: 46539 | L8: 46569 | M8: 46600 | N8: 46631 | O8: 46661 | P8: 46692 | Q8: 46722
E11: =SUM(F11:Q11) -> 0 | F11: =SUM(F12:F17) -> 0 | G11: =SUM(G12:G17) -> 0 | H11: =SUM(H12:H17) -> 0 | I11: =SUM(I12:I17) -> 0 | J11: =SUM(J12:J17) -> 0 | K11: =SUM(K12:K17) -> 0 | L11: =SUM(L12:L17) -> 0 | M11: =SUM(M12:M17) -> 0 | ... Q11: =SUM(Q12:Q17) -> 0
E12: =C12*D12 -> 0
E13: =C13*D13 -> 0
E14: =C14*D14 -> 0
E15: =C15*D15 -> 0
E16: =C16*D16 -> 0
E17: =C17*D17 -> 0
E18: =SUM(F18:Q18) -> 0
E19: =SUM(F19:Q19) -> 0 | F19: =SUM(F20:F22) -> 0 | G19: =SUM(G20:G22) -> 0 | H19: =SUM(H20:H22) -> 0 | I19: =SUM(I20:I22) -> 0 | J19: =SUM(J20:J22) -> 0 | K19: =SUM(K20:K22) -> 0 | L19: =SUM(L20:L22) -> 0 | M19: =SUM(M20:M22) -> 0 | ... Q19: =SUM(Q20:Q22) -> 0
E20: =C20*D20 -> 0 | K20: =E20 -> 0
E21: =C21*D21 -> 0 | J21: =E21 -> 0
E22: =C22*D22 -> 0
E23: =SUM(F23:Q23) -> 0
E24: =SUM(F24:Q24) -> 0 | F24: =SUM(F25:F27) -> 0 | G24: =SUM(G25:G27) -> 0 | H24: =SUM(H25:H27) -> 0 | I24: =SUM(I25:I27) -> 0 | J24: =SUM(J25:J27) -> 0 | K24: =SUM(K25:K27) -> 0 | L24: =SUM(L25:L27) -> 0 | M24: =SUM(M25:M27) -> 0 | ... Q24: =SUM(Q25:Q27) -> 0
E25: =SUM(F25:Q25) -> 0
E26: =SUM(F26:Q26) -> 0
E27: =SUM(F27:Q27) -> 0
A30: =B4&" "&"Budget Plan" -> Budget Plan | E30: =SUM(F30:Q30) -> 0 | F30: =F24+F19+F11 -> 0 | G30: =G24+G19+G11 -> 0 | H30: =H24+H19+H11 -> 0 | I30: =I24+I19+I11 -> 0 | J30: =J24+J19+J11 -> 0 | K30: =K24+K19+K11 -> 0 | L30: =L24+L19+L11 -> 0 | M30: =M24+M19+M11 -> 0 | ... Q30: =Q24+Q19+Q11 -> 0
F47: YTD JAN | G47: YTD FEB | H47: YTD MAR | I47: YTD APR | J47: YTD MAY | K47: YTD JUN | L47: YTD JUL | M47: YTD AUG | N47: YTD SEP | O47: YTD OCT | P47: YTD NOV | Q47: YTD DEC
F48: =SUM($F$30:F30) -> 0 | G48: =SUM($F$30:G30) -> 0 | H48: =SUM($F$30:H30) -> 0 | I48: =SUM($F$30:I30) -> 0 | J48: =SUM($F$30:J30) -> 0 | K48: =SUM($F$30:K30) -> 0 | L48: =SUM($F$30:L30) -> 0 | M48: =SUM($F$30:M30) -> 0 | ... Q48: =SUM($F$30:Q30) -> 0

Sheet  Budget Fixed Asset
B1: CAPEX PLANNING (NON CONSTRUCTION)
B2: ENTITAS: | C2: Pilih Perusahaan
B3: PROJECT | C3: Pilih Project
B4: DIVISION
B5: BUDGET | C5: 2027
B7: Description | C7: Estimate Total Unit | F7: Price / Unit | G7: 2027 | I7: =G7+1 -> 2028 | K7: =I7+1 -> 2029 | M7: 2027
B8: MUST TO HAVE | C8: New | D8: Replace | E8: Total | G8: Qty | H8: Total | I8: Qty | J8: Total | K8: Qty | L8: Total | M8: Budget Full Year | N8: 46388 | O8: 46419 | P8: 46447 | Q8: 46478 | R8: 46508 | S8: 46539 | T8: 46569 | U8: 46600 | V8: 46631 | W8: 46661 | X8: 46692 | Y8: 46722
E9: =SUM(C9:D9) -> 0 | H9: =$F9*G9 -> 0 | J9: =$F9*I9 -> 0 | L9: =$F9*K9 -> 0 | M9: =SUM(N9:Y9) -> 0
E10: =SUM(C10:D10) -> 0 | H10: =$F10*G10 -> 0 | J10: =$F10*I10 -> 0 | L10: =$F10*K10 -> 0 | M10: =SUM(N10:Y10) -> 0
E11: =SUM(C11:D11) -> 0 | H11: =$F11*G11 -> 0 | J11: =$F11*I11 -> 0 | L11: =$F11*K11 -> 0 | M11: =SUM(N11:Y11) -> 0
E12: =SUM(C12:D12) -> 0 | H12: =$F12*G12 -> 0 | J12: =$F12*I12 -> 0 | L12: =$F12*K12 -> 0 | M12: =SUM(N12:Y12) -> 0
E13: =SUM(C13:D13) -> 0 | H13: =$F13*G13 -> 0 | J13: =$F13*I13 -> 0 | L13: =$F13*K13 -> 0 | M13: =SUM(N13:Y13) -> 0
E14: =SUM(C14:D14) -> 0 | H14: =$F14*G14 -> 0 | J14: =$F14*I14 -> 0 | L14: =$F14*K14 -> 0 | M14: =SUM(N14:Y14) -> 0
E15: =SUM(C15:D15) -> 0 | H15: =$F15*G15 -> 0 | J15: =$F15*I15 -> 0 | L15: =$F15*K15 -> 0 | M15: =SUM(N15:Y15) -> 0
E16: =SUM(C16:D16) -> 0 | H16: =$F16*G16 -> 0 | J16: =$F16*I16 -> 0 | L16: =$F16*K16 -> 0 | M16: =SUM(N16:Y16) -> 0
E17: =SUM(C17:D17) -> 0 | H17: =$F17*G17 -> 0 | J17: =$F17*I17 -> 0 | L17: =$F17*K17 -> 0 | M17: =SUM(N17:Y17) -> 0
E18: =SUM(C18:D18) -> 0 | H18: =$F18*G18 -> 0 | J18: =$F18*I18 -> 0 | L18: =$F18*K18 -> 0 | M18: =SUM(N18:Y18) -> 0
E19: =SUM(C19:D19) -> 0 | H19: =$F19*G19 -> 0 | J19: =$F19*I19 -> 0 | L19: =$F19*K19 -> 0 | M19: =SUM(N19:Y19) -> 0
E20: =SUM(C20:D20) -> 0 | H20: =$F20*G20 -> 0 | J20: =$F20*I20 -> 0 | L20: =$F20*K20 -> 0 | M20: =SUM(N20:Y20) -> 0
C21: =SUM(C9:C20) -> 0 | D21: =SUM(D9:D20) -> 0 | E21: =SUM(E9:E20) -> 0 | G21: =SUM(G9:G20) -> 0 | H21: =SUM(H9:H20) -> 0 | I21: =SUM(I9:I20) -> 0 | J21: =SUM(J9:J20) -> 0 | K21: =SUM(K9:K20) -> 0 | L21: =SUM(L9:L20) -> 0 | M21: =SUM(M9:M20) -> 0 | N21: =SUM(N9:N20) -> 0 | ... Y21: =SUM(Y9:Y20) -> 0
B23: Description | C23: Estimate Total Unit | F23: Price / Unit | G23: =G7 -> 2027 | I23: =I7 -> 2028 | K23: =K7 -> 2029
B24: NICE TO HAVE | C24: New | D24: Replace | E24: Total | G24: Qty | H24: Total | I24: Qty | J24: Total | K24: Qty | L24: Total
E25: =SUM(C25:D25) -> 0 | H25: =$F25*G25 -> 0 | J25: =$F25*I25 -> 0 | L25: =$F25*K25 -> 0
E26: =SUM(C26:D26) -> 0 | H26: =$F26*G26 -> 0 | J26: =$F26*I26 -> 0 | L26: =$F26*K26 -> 0
E27: =SUM(C27:D27) -> 0 | H27: =$F27*G27 -> 0 | J27: =$F27*I27 -> 0 | L27: =$F27*K27 -> 0
E28: =SUM(C28:D28) -> 0 | H28: =$F28*G28 -> 0 | J28: =$F28*I28 -> 0 | L28: =$F28*K28 -> 0
E29: =SUM(C29:D29) -> 0 | H29: =$F29*G29 -> 0 | J29: =$F29*I29 -> 0 | L29: =$F29*K29 -> 0
E30: =SUM(C30:D30) -> 0 | H30: =$F30*G30 -> 0 | J30: =$F30*I30 -> 0 | L30: =$F30*K30 -> 0
E31: =SUM(C31:D31) -> 0 | H31: =$F31*G31 -> 0 | J31: =$F31*I31 -> 0 | L31: =$F31*K31 -> 0
E32: =SUM(C32:D32) -> 0 | H32: =$F32*G32 -> 0 | J32: =$F32*I32 -> 0 | L32: =$F32*K32 -> 0
C33: =SUM(C25:C32) -> 0 | D33: =SUM(D25:D32) -> 0 | E33: =SUM(E25:E32) -> 0 | G33: =SUM(G25:G32) -> 0 | H33: =SUM(H25:H32) -> 0 | I33: =SUM(I25:I32) -> 0 | J33: =SUM(J25:J32) -> 0 | K33: =SUM(K25:K32) -> 0 | L33: =SUM(L25:L32) -> 0
N37: YTD JAN | O37: YTD FEB | P37: YTD MAR | Q37: YTD APR | R37: YTD MAY | S37: YTD JUN | T37: YTD JUL | U37: YTD AUG | V37: YTD SEP | W37: YTD OCT | X37: YTD NOV | Y37: YTD DEC
N38: =SUM(N21) -> 0 | O38: =SUM($N$21:O$21) -> 0 | P38: =SUM($N$21:P$21) -> 0 | Q38: =SUM($N$21:Q$21) -> 0 | R38: =SUM($N$21:R$21) -> 0 | S38: =SUM($N$21:S$21) -> 0 | T38: =SUM($N$21:T$21) -> 0 | U38: =SUM($N$21:U$21) -> 0 | V38: =SUM($N$21:V$21) -> 0 | ... Y38: =SUM($N$21:Y$21) -> 0

Sheet Budget Tax
A1: BUDGET Tax
A2: ENTITAS: | B2: Pilih Perusahaan
A3: PROJECT | B3: Pilih Project
A4: Division
A5: BUDGET YEARS | B5: 2027
A7: No Akun | B7: Keterangan Biaya | C7: Rincian Budget | D7: Budget Tahun 2027 | E7: 46388 | F7: 46419 | G7: 46447 | H7: 46478 | I7: 46508 | J7: 46539 | K7: 46569 | L7: 46600 | M7: 46631 | N7: 46661 | O7: 46692 | P7: 46722
A8: 62290001 | B8: BEBAN ADMINISTRASI PAJAK | D8: =SUM(E8:P8) -> 0
A9: 62290002 | B9: BEBAN PAJAK DITANGGUNG PERUSAHAAN | D9: =SUM(E9:P9) -> 0
A10: 62290003 | B10: BEBAN PAJAK FINAL (PPHTB) | D10: =SUM(E10:P10) -> 0
A11: 62290004 | B11: BEBAN PAJAK KENDARAAN | D11: =SUM(E11:P11) -> 0
A12: 62290005 | B12: BEBAN PAJAK NON FINAL | D12: =SUM(E12:P12) -> 0
A13: 62290006 | B13: BEBAN PAJAK LAINNYA | D13: =SUM(E13:P13) -> 0 | H13: =SUM(I13:T13) -> 0
E14: =SUM(E8:E13) -> 0 | F14: =SUM(F8:F13) -> 0 | G14: =SUM(G8:G13) -> 0 | H14: =SUM(H8:H13) -> 0 | I14: =SUM(I8:I13) -> 0 | J14: =SUM(J8:J13) -> 0 | K14: =SUM(K8:K13) -> 0 | L14: =SUM(L8:L13) -> 0 | ... P14: =SUM(P8:P13) -> 0
D15: TOTAL | E15: YTD JAN | F15: YTD FEB | G15: YTD MAR | H15: YTD APR | I15: YTD MAY | J15: YTD JUN | K15: YTD JUL | L15: YTD AUG | M15: YTD SEP | N15: YTD OCT | O15: YTD NOV | P15: YTD DEC
E16: =SUM(E14) -> 0 | F16: =SUM($E$14:F$14) -> 0 | G16: =SUM($E$14:G$14) -> 0 | H16: =SUM($E$14:H$14) -> 0 | I16: =SUM($E$14:I$14) -> 0 | J16: =SUM($E$14:J$14) -> 0 | K16: =SUM($E$14:K$14) -> 0 | L16: =SUM($E$14:L$14) -> 0 | M16: =SUM($E$14:M$14) -> 0 | ... P16: =SUM($E$14:P$14) -> 0

Sheet Budget GnA
B1: BUDGET G&A Expenses
B2: ENTITAS: | C2: Pilih Perusahaan
B3: PROJECT | C3: Pilih Project
B4: Division
B5: BUDGET YEARS | C5: 2026
B7: G&A Expenses | C7: 46023 | D7: 46054 | E7: 46082 | F7: 46113 | G7: 46143 | H7: 46174 | I7: 46204 | J7: 46235 | K7: 46266 | L7: 46296 | M7: 46327 | N7: 46357 | O7: TOTAL
B8: Maintenance Expenses | O8: =SUM(C8:N8) -> 0
B9: Rent Expenses | O9: =SUM(C9:N9) -> 0
B10: Insurance Expenses | O10: =SUM(C10:N10) -> 0
B11: Profesional Fee | O11: =SUM(C11:N11) -> 0
B12: Transport Expenses | O12: =SUM(C12:N12) -> 0
B13: Business Trip Expenses | C13: ='Business Trip'!S17 -> 0 | D13: ='Business Trip'!T17 -> 0 | E13: ='Business Trip'!U17 -> 0 | F13: ='Business Trip'!V17 -> 0 | G13: ='Business Trip'!W17 -> 0 | H13: ='Business Trip'!X17 -> 0 | I13: ='Business Trip'!Y17 -> 0 | J13: ='Business Trip'!Z17 -> 0 | ... N13: ='Business Trip'!AD17 -> 0 | O13: =SUM(C13:N13) -> 0
B14: Utility Expenses | O14: =SUM(C14:N14) -> 0
B15: Equipment Expenses | O15: =SUM(C15:N15) -> 0
B16: Office Supply | O16: =SUM(C16:N16) -> 0
B17: Taxes | O17: =SUM(C17:N17) -> 0
B18: Depreciation & Amortization | O18: =SUM(C18:N18) -> 0
A22: 1 | B22: G&A Expenses | C22: YTD JAN | D22: YTD FEB | E22: YTD MAR | F22: YTD APR | G22: YTD MAY | H22: YTD JUN | I22: YTD JUL | J22: YTD AUG | K22: YTD SEP | L22: YTD OCT | M22: YTD NOV | N22: YTD DEC
A23: =A22+1 -> 2 | B23: Maintenance Expenses | C23: =SUM(C8) -> 0 | D23: =SUM($C8:D8) -> 0 | E23: =SUM($C8:E8) -> 0 | F23: =SUM($C8:F8) -> 0 | G23: =SUM($C8:G8) -> 0 | H23: =SUM($C8:H8) -> 0 | I23: =SUM($C8:I8) -> 0 | J23: =SUM($C8:J8) -> 0 | K23: =SUM($C8:K8) -> 0 | ... N23: =SUM($C8:N8) -> 0
A24: =A23+1 -> 3 | B24: Rent Expenses | C24: =SUM(C9) -> 0 | D24: =SUM($C9:D9) -> 0 | E24: =SUM($C9:E9) -> 0 | F24: =SUM($C9:F9) -> 0 | G24: =SUM($C9:G9) -> 0 | H24: =SUM($C9:H9) -> 0 | I24: =SUM($C9:I9) -> 0 | J24: =SUM($C9:J9) -> 0 | K24: =SUM($C9:K9) -> 0 | ... N24: =SUM($C9:N9) -> 0
A25: =A24+1 -> 4 | B25: Insurance Expenses | C25: =SUM(C10) -> 0 | D25: =SUM($C10:D10) -> 0 | E25: =SUM($C10:E10) -> 0 | F25: =SUM($C10:F10) -> 0 | G25: =SUM($C10:G10) -> 0 | H25: =SUM($C10:H10) -> 0 | I25: =SUM($C10:I10) -> 0 | J25: =SUM($C10:J10) -> 0 | K25: =SUM($C10:K10) -> 0 | ... N25: =SUM($C10:N10) -> 0
A26: =A25+1 -> 5 | B26: Profesional Fee | C26: =SUM(C11) -> 0 | D26: =SUM($C11:D11) -> 0 | E26: =SUM($C11:E11) -> 0 | F26: =SUM($C11:F11) -> 0 | G26: =SUM($C11:G11) -> 0 | H26: =SUM($C11:H11) -> 0 | I26: =SUM($C11:I11) -> 0 | J26: =SUM($C11:J11) -> 0 | K26: =SUM($C11:K11) -> 0 | ... N26: =SUM($C11:N11) -> 0
A27: =A26+1 -> 6 | B27: Transport Expenses | C27: =SUM(C12) -> 0 | D27: =SUM($C12:D12) -> 0 | E27: =SUM($C12:E12) -> 0 | F27: =SUM($C12:F12) -> 0 | G27: =SUM($C12:G12) -> 0 | H27: =SUM($C12:H12) -> 0 | I27: =SUM($C12:I12) -> 0 | J27: =SUM($C12:J12) -> 0 | K27: =SUM($C12:K12) -> 0 | ... N27: =SUM($C12:N12) -> 0
A28: =A27+1 -> 7 | B28: Business Trip Expenses | C28: =SUM(C13) -> 0 | D28: =SUM($C13:D13) -> 0 | E28: =SUM($C13:E13) -> 0 | F28: =SUM($C13:F13) -> 0 | G28: =SUM($C13:G13) -> 0 | H28: =SUM($C13:H13) -> 0 | I28: =SUM($C13:I13) -> 0 | J28: =SUM($C13:J13) -> 0 | K28: =SUM($C13:K13) -> 0 | ... N28: =SUM($C13:N13) -> 0
A29: =A28+1 -> 8 | B29: Utility Expenses | C29: =SUM(C14) -> 0 | D29: =SUM($C14:D14) -> 0 | E29: =SUM($C14:E14) -> 0 | F29: =SUM($C14:F14) -> 0 | G29: =SUM($C14:G14) -> 0 | H29: =SUM($C14:H14) -> 0 | I29: =SUM($C14:I14) -> 0 | J29: =SUM($C14:J14) -> 0 | K29: =SUM($C14:K14) -> 0 | ... N29: =SUM($C14:N14) -> 0
A30: =A29+1 -> 9 | B30: Equipment Expenses | C30: =SUM(C15) -> 0 | D30: =SUM($C15:D15) -> 0 | E30: =SUM($C15:E15) -> 0 | F30: =SUM($C15:F15) -> 0 | G30: =SUM($C15:G15) -> 0 | H30: =SUM($C15:H15) -> 0 | I30: =SUM($C15:I15) -> 0 | J30: =SUM($C15:J15) -> 0 | K30: =SUM($C15:K15) -> 0 | ... N30: =SUM($C15:N15) -> 0
A31: =A30+1 -> 10 | B31: Office Supply | C31: =SUM(C16) -> 0 | D31: =SUM($C16:D16) -> 0 | E31: =SUM($C16:E16) -> 0 | F31: =SUM($C16:F16) -> 0 | G31: =SUM($C16:G16) -> 0 | H31: =SUM($C16:H16) -> 0 | I31: =SUM($C16:I16) -> 0 | J31: =SUM($C16:J16) -> 0 | K31: =SUM($C16:K16) -> 0 | ... N31: =SUM($C16:N16) -> 0
A32: =A31+1 -> 11 | B32: Taxes | C32: =SUM(C17) -> 0 | D32: =SUM($C17:D17) -> 0 | E32: =SUM($C17:E17) -> 0 | F32: =SUM($C17:F17) -> 0 | G32: =SUM($C17:G17) -> 0 | H32: =SUM($C17:H17) -> 0 | I32: =SUM($C17:I17) -> 0 | J32: =SUM($C17:J17) -> 0 | K32: =SUM($C17:K17) -> 0 | ... N32: =SUM($C17:N17) -> 0
A33: =A32+1 -> 12 | B33: Depreciation & Amortization | C33: =SUM(C18) -> 0 | D33: =SUM($C18:D18) -> 0 | E33: =SUM($C18:E18) -> 0 | F33: =SUM($C18:F18) -> 0 | G33: =SUM($C18:G18) -> 0 | H33: =SUM($C18:H18) -> 0 | I33: =SUM($C18:I18) -> 0 | J33: =SUM($C18:J18) -> 0 | K33: =SUM($C18:K18) -> 0 | ... N33: =SUM($C18:N18) -> 0
A34: =A33+1 -> 13 | C34: =SUM(C23:C33) -> 0 | D34: =SUM(D23:D33) -> 0 | E34: =SUM(E23:E33) -> 0 | F34: =SUM(F23:F33) -> 0 | G34: =SUM(G23:G33) -> 0 | H34: =SUM(H23:H33) -> 0 | I34: =SUM(I23:I33) -> 0 | J34: =SUM(J23:J33) -> 0 | ... N34: =SUM(N23:N33) -> 0

Sheet Business Trip
A2: Budget Busniess Trip
A3: Entitas | B3: PT Perintis Triniti Properti Tbk | T3: \
A4: Project | B4: Lampung-Holdwell Business Park
A5: Budget Year | B5: 2026
A7: BUSINESS TRIP - DOMESTIC
A9: No | B9: Employee Name | C9: Level | D9: Divison / Dept | E9: Travel Period | F9: Local/ Overseas | G9: Departure | H9: Arrival | I9: Days | J9: Curr | K9: Flight Cost (Round Trip) | L9: Hotel | M9: Money Allowance | N9: Meals Allowance | O9: Transport | P9: Total Cost
B10: Lembar pengisian Budget
A11: 1 | B11: XX | C11: BOD / BOC | E11: 46082 | G11: Jakarta | H11: Batam | I11: 3 | J11: IDR | K11: =IF($C11=Attachment1!$A$63,_xlfn.IFNA(INDEX(database!$O$3:$O$7,MATCH(G11&H11,database!$M$3:$M$8,0)),0),_xlfn.IFNA(INDEX(database!$N$3:$N$7,MATCH(G11&H11,database!$M$3:$M$8,0)),0)) -> 3000000 | L11: =IF(I11=0,0,IF(I11=1,0,_xlfn.IFNA(INDEX(Attachment1!$B$63:$B$68,MATCH($C11,Attachment1!$A$63:$A$68,0)),0)*I11)) -> 4950000 | M11: =IF(I11=0,0,_xlfn.IFNA(INDEX(Attachment1!$C$63:$C$68,MATCH($C11,Attachment1!$A$63:$A$68,0)),0))*I11 -> 1500000 | P11: =SUM(K11:M11) -> 9450000
A12: 2 | J12: IDR | K12: =IF($C12=Attachment1!$A$63,_xlfn.IFNA(INDEX(database!$O$3:$O$7,MATCH(G12&H12,database!$M$3:$M$8,0)),0),_xlfn.IFNA(INDEX(database!$N$3:$N$7,MATCH(G12&H12,database!$M$3:$M$8,0)),0)) -> 0 | L12: =IF(I12=0,0,IF(I12=1,0,_xlfn.IFNA(INDEX(Attachment1!$B$63:$B$68,MATCH($C12,Attachment1!$A$63:$A$68,0)),0)*I12)) -> 0 | M12: =IF(I12=0,0,_xlfn.IFNA(INDEX(Attachment1!$C$63:$C$68,MATCH($C12,Attachment1!$A$63:$A$68,0)),0))*I12 -> 0 | P12: =SUM(K12:M12) -> 0
A13: 3 | J13: IDR | K13: =IF($C13=Attachment1!$A$63,_xlfn.IFNA(INDEX(database!$O$3:$O$7,MATCH(G13&H13,database!$M$3:$M$8,0)),0),_xlfn.IFNA(INDEX(database!$N$3:$N$7,MATCH(G13&H13,database!$M$3:$M$8,0)),0)) -> 0 | L13: =IF(I13=0,0,IF(I13=1,0,_xlfn.IFNA(INDEX(Attachment1!$B$63:$B$68,MATCH($C13,Attachment1!$A$63:$A$68,0)),0)*I13)) -> 0 | M13: =IF(I13=0,0,_xlfn.IFNA(INDEX(Attachment1!$C$63:$C$68,MATCH($C13,Attachment1!$A$63:$A$68,0)),0))*I13 -> 0 | P13: =SUM(K13:M13) -> 0
A14: 4 | J14: IDR | K14: =IF($C14=Attachment1!$A$63,_xlfn.IFNA(INDEX(database!$O$3:$O$7,MATCH(G14&H14,database!$M$3:$M$8,0)),0),_xlfn.IFNA(INDEX(database!$N$3:$N$7,MATCH(G14&H14,database!$M$3:$M$8,0)),0)) -> 0 | L14: =IF(I14=0,0,IF(I14=1,0,_xlfn.IFNA(INDEX(Attachment1!$B$63:$B$68,MATCH($C14,Attachment1!$A$63:$A$68,0)),0)*I14)) -> 0 | M14: =IF(I14=0,0,_xlfn.IFNA(INDEX(Attachment1!$C$63:$C$68,MATCH($C14,Attachment1!$A$63:$A$68,0)),0))*I14 -> 0 | P14: =SUM(K14:M14) -> 0 | S14: BUDGET 2025
A15: 5 | J15: IDR | K15: =IF($C15=Attachment1!$A$63,_xlfn.IFNA(INDEX(database!$O$3:$O$7,MATCH(G15&H15,database!$M$3:$M$8,0)),0),_xlfn.IFNA(INDEX(database!$N$3:$N$7,MATCH(G15&H15,database!$M$3:$M$8,0)),0)) -> 0 | L15: =IF(I15=0,0,IF(I15=1,0,_xlfn.IFNA(INDEX(Attachment1!$B$63:$B$68,MATCH($C15,Attachment1!$A$63:$A$68,0)),0)*I15)) -> 0 | M15: =IF(I15=0,0,_xlfn.IFNA(INDEX(Attachment1!$C$63:$C$68,MATCH($C15,Attachment1!$A$63:$A$68,0)),0))*I15 -> 0 | P15: =SUM(K15:M15) -> 0 | S15: Biaya Perjalanan Dinas Dalam Negeri
A16: 6 | J16: IDR | K16: =IF($C16=Attachment1!$A$63,_xlfn.IFNA(INDEX(database!$O$3:$O$7,MATCH(G16&H16,database!$M$3:$M$8,0)),0),_xlfn.IFNA(INDEX(database!$N$3:$N$7,MATCH(G16&H16,database!$M$3:$M$8,0)),0)) -> 0 | L16: =IF(I16=0,0,IF(I16=1,0,_xlfn.IFNA(INDEX(Attachment1!$B$63:$B$68,MATCH($C16,Attachment1!$A$63:$A$68,0)),0)*I16)) -> 0 | M16: =IF(I16=0,0,_xlfn.IFNA(INDEX(Attachment1!$C$63:$C$68,MATCH($C16,Attachment1!$A$63:$A$68,0)),0))*I16 -> 0 | P16: =SUM(K16:M16) -> 0 | S16: 45658 | T16: 45689 | U16: 45717 | V16: 45748 | W16: 45778 | X16: 45809 | Y16: 45839 | Z16: 45870 | AA16: 45901 | AB16: 45931 | AC16: 45962 | AD16: 45992 | AE16: TOTAL
A17: 7 | J17: IDR | K17: =IF($C17=Attachment1!$A$63,_xlfn.IFNA(INDEX(database!$O$3:$O$7,MATCH(G17&H17,database!$M$3:$M$8,0)),0),_xlfn.IFNA(INDEX(database!$N$3:$N$7,MATCH(G17&H17,database!$M$3:$M$8,0)),0)) -> 0 | L17: =IF(I17=0,0,IF(I17=1,0,_xlfn.IFNA(INDEX(Attachment1!$B$63:$B$68,MATCH($C17,Attachment1!$A$63:$A$68,0)),0)*I17)) -> 0 | M17: =IF(I17=0,0,_xlfn.IFNA(INDEX(Attachment1!$C$63:$C$68,MATCH($C17,Attachment1!$A$63:$A$68,0)),0))*I17 -> 0 | P17: =SUM(K17:M17) -> 0 | S17: =SUMIF($E:$E,S16,$P:$P) -> 0 | T17: =SUMIF($E:$E,T16,$P:$P) -> 0 | U17: =SUMIF($E:$E,U16,$P:$P) -> 0 | V17: =SUMIF($E:$E,V16,$P:$P) -> 0 | W17: =SUMIF($E:$E,W16,$P:$P) -> 0 | X17: =SUMIF($E:$E,X16,$P:$P) -> 0 | Y17: =SUMIF($E:$E,Y16,$P:$P) -> 0 | Z17: =SUMIF($E:$E,Z16,$P:$P) -> 0 | ... AD17: =SUMIF($E:$E,AD16,$P:$P) -> 0 | AE17: =SUM(S17:AD17) -> 0
A18: 8 | J18: IDR | K18: =IF($C18=Attachment1!$A$63,_xlfn.IFNA(INDEX(database!$O$3:$O$7,MATCH(G18&H18,database!$M$3:$M$8,0)),0),_xlfn.IFNA(INDEX(database!$N$3:$N$7,MATCH(G18&H18,database!$M$3:$M$8,0)),0)) -> 0 | L18: =IF(I18=0,0,IF(I18=1,0,_xlfn.IFNA(INDEX(Attachment1!$B$63:$B$68,MATCH($C18,Attachment1!$A$63:$A$68,0)),0)*I18)) -> 0 | M18: =IF(I18=0,0,_xlfn.IFNA(INDEX(Attachment1!$C$63:$C$68,MATCH($C18,Attachment1!$A$63:$A$68,0)),0))*I18 -> 0 | P18: =SUM(K18:M18) -> 0
A19: 9 | J19: IDR | K19: =IF($C19=Attachment1!$A$63,_xlfn.IFNA(INDEX(database!$O$3:$O$7,MATCH(G19&H19,database!$M$3:$M$8,0)),0),_xlfn.IFNA(INDEX(database!$N$3:$N$7,MATCH(G19&H19,database!$M$3:$M$8,0)),0)) -> 0 | L19: =IF(I19=0,0,IF(I19=1,0,_xlfn.IFNA(INDEX(Attachment1!$B$63:$B$68,MATCH($C19,Attachment1!$A$63:$A$68,0)),0)*I19)) -> 0 | M19: =IF(I19=0,0,_xlfn.IFNA(INDEX(Attachment1!$C$63:$C$68,MATCH($C19,Attachment1!$A$63:$A$68,0)),0))*I19 -> 0 | P19: =SUM(K19:M19) -> 0
A20: 10 | J20: IDR | K20: =IF($C20=Attachment1!$A$63,_xlfn.IFNA(INDEX(database!$O$3:$O$7,MATCH(G20&H20,database!$M$3:$M$8,0)),0),_xlfn.IFNA(INDEX(database!$N$3:$N$7,MATCH(G20&H20,database!$M$3:$M$8,0)),0)) -> 0 | L20: =IF(I20=0,0,IF(I20=1,0,_xlfn.IFNA(INDEX(Attachment1!$B$63:$B$68,MATCH($C20,Attachment1!$A$63:$A$68,0)),0)*I20)) -> 0 | M20: =IF(I20=0,0,_xlfn.IFNA(INDEX(Attachment1!$C$63:$C$68,MATCH($C20,Attachment1!$A$63:$A$68,0)),0))*I20 -> 0 | P20: =SUM(K20:M20) -> 0
A21: 11 | J21: IDR | K21: =IF($C21=Attachment1!$A$63,_xlfn.IFNA(INDEX(database!$O$3:$O$7,MATCH(G21&H21,database!$M$3:$M$8,0)),0),_xlfn.IFNA(INDEX(database!$N$3:$N$7,MATCH(G21&H21,database!$M$3:$M$8,0)),0)) -> 0 | L21: =IF(I21=0,0,IF(I21=1,0,_xlfn.IFNA(INDEX(Attachment1!$B$63:$B$68,MATCH($C21,Attachment1!$A$63:$A$68,0)),0)*I21)) -> 0 | M21: =IF(I21=0,0,_xlfn.IFNA(INDEX(Attachment1!$C$63:$C$68,MATCH($C21,Attachment1!$A$63:$A$68,0)),0))*I21 -> 0 | P21: =SUM(K21:M21) -> 0 | S21: BUDGET 2025 YTD
A22: 12 | J22: IDR | K22: =IF($C22=Attachment1!$A$63,_xlfn.IFNA(INDEX(database!$O$3:$O$7,MATCH(G22&H22,database!$M$3:$M$8,0)),0),_xlfn.IFNA(INDEX(database!$N$3:$N$7,MATCH(G22&H22,database!$M$3:$M$8,0)),0)) -> 0 | L22: =IF(I22=0,0,IF(I22=1,0,_xlfn.IFNA(INDEX(Attachment1!$B$63:$B$68,MATCH($C22,Attachment1!$A$63:$A$68,0)),0)*I22)) -> 0 | M22: =IF(I22=0,0,_xlfn.IFNA(INDEX(Attachment1!$C$63:$C$68,MATCH($C22,Attachment1!$A$63:$A$68,0)),0))*I22 -> 0 | P22: =SUM(K22:M22) -> 0 | S22: Biaya Perjalanan Dinas Dalam Negeri
A23: 13 | J23: IDR | K23: =IF($C23=Attachment1!$A$63,_xlfn.IFNA(INDEX(database!$O$3:$O$7,MATCH(G23&H23,database!$M$3:$M$8,0)),0),_xlfn.IFNA(INDEX(database!$N$3:$N$7,MATCH(G23&H23,database!$M$3:$M$8,0)),0)) -> 0 | L23: =IF(I23=0,0,IF(I23=1,0,_xlfn.IFNA(INDEX(Attachment1!$B$63:$B$68,MATCH($C23,Attachment1!$A$63:$A$68,0)),0)*I23)) -> 0 | M23: =IF(I23=0,0,_xlfn.IFNA(INDEX(Attachment1!$C$63:$C$68,MATCH($C23,Attachment1!$A$63:$A$68,0)),0))*I23 -> 0 | P23: =SUM(K23:M23) -> 0 | S23: YTD JAN | T23: YTD FEB | U23: YTD MAR | V23: YTD APR | W23: YTD MAY | X23: YTD JUN | Y23: YTD JUL | Z23: YTD AUG | AA23: YTD SEP | AB23: YTD OCT | AC23: YTD NOV | AD23: YTD DEC | AE23: TOTAL
A24: 14 | J24: IDR | K24: =IF($C24=Attachment1!$A$63,_xlfn.IFNA(INDEX(database!$O$3:$O$7,MATCH(G24&H24,database!$M$3:$M$8,0)),0),_xlfn.IFNA(INDEX(database!$N$3:$N$7,MATCH(G24&H24,database!$M$3:$M$8,0)),0)) -> 0 | L24: =IF(I24=0,0,IF(I24=1,0,_xlfn.IFNA(INDEX(Attachment1!$B$63:$B$68,MATCH($C24,Attachment1!$A$63:$A$68,0)),0)*I24)) -> 0 | M24: =IF(I24=0,0,_xlfn.IFNA(INDEX(Attachment1!$C$63:$C$68,MATCH($C24,Attachment1!$A$63:$A$68,0)),0))*I24 -> 0 | P24: =SUM(K24:M24) -> 0 | S24: =SUM($S$17:S17) -> 0 | T24: =SUM($S$17:T17) -> 0 | U24: =SUM($S$17:U17) -> 0 | V24: =SUM($S$17:V17) -> 0 | W24: =SUM($S$17:W17) -> 0 | X24: =SUM($S$17:X17) -> 0 | Y24: =SUM($S$17:Y17) -> 0 | Z24: =SUM($S$17:Z17) -> 0 | ... AD24: =SUM($S$17:AD17) -> 0 | AE24: =SUM(S24:AD24) -> 0
A25: 15 | J25: IDR | K25: =IF($C25=Attachment1!$A$63,_xlfn.IFNA(INDEX(database!$O$3:$O$7,MATCH(G25&H25,database!$M$3:$M$8,0)),0),_xlfn.IFNA(INDEX(database!$N$3:$N$7,MATCH(G25&H25,database!$M$3:$M$8,0)),0)) -> 0 | L25: =IF(I25=0,0,IF(I25=1,0,_xlfn.IFNA(INDEX(Attachment1!$B$63:$B$68,MATCH($C25,Attachment1!$A$63:$A$68,0)),0)*I25)) -> 0 | M25: =IF(I25=0,0,_xlfn.IFNA(INDEX(Attachment1!$C$63:$C$68,MATCH($C25,Attachment1!$A$63:$A$68,0)),0))*I25 -> 0 | P25: =SUM(K25:M25) -> 0
A26: 16 | J26: IDR | K26: =IF($C26=Attachment1!$A$63,_xlfn.IFNA(INDEX(database!$O$3:$O$7,MATCH(G26&H26,database!$M$3:$M$8,0)),0),_xlfn.IFNA(INDEX(database!$N$3:$N$7,MATCH(G26&H26,database!$M$3:$M$8,0)),0)) -> 0 | L26: =IF(I26=0,0,IF(I26=1,0,_xlfn.IFNA(INDEX(Attachment1!$B$63:$B$68,MATCH($C26,Attachment1!$A$63:$A$68,0)),0)*I26)) -> 0 | M26: =IF(I26=0,0,_xlfn.IFNA(INDEX(Attachment1!$C$63:$C$68,MATCH($C26,Attachment1!$A$63:$A$68,0)),0))*I26 -> 0 | P26: =SUM(K26:M26) -> 0
A27: 17 | J27: IDR | K27: =IF($C27=Attachment1!$A$63,_xlfn.IFNA(INDEX(database!$O$3:$O$7,MATCH(G27&H27,database!$M$3:$M$8,0)),0),_xlfn.IFNA(INDEX(database!$N$3:$N$7,MATCH(G27&H27,database!$M$3:$M$8,0)),0)) -> 0 | L27: =IF(I27=0,0,IF(I27=1,0,_xlfn.IFNA(INDEX(Attachment1!$B$63:$B$68,MATCH($C27,Attachment1!$A$63:$A$68,0)),0)*I27)) -> 0 | M27: =IF(I27=0,0,_xlfn.IFNA(INDEX(Attachment1!$C$63:$C$68,MATCH($C27,Attachment1!$A$63:$A$68,0)),0))*I27 -> 0 | P27: =SUM(K27:M27) -> 0
A28: 18 | J28: IDR | K28: =IF($C28=Attachment1!$A$63,_xlfn.IFNA(INDEX(database!$O$3:$O$7,MATCH(G28&H28,database!$M$3:$M$8,0)),0),_xlfn.IFNA(INDEX(database!$N$3:$N$7,MATCH(G28&H28,database!$M$3:$M$8,0)),0)) -> 0 | L28: =IF(I28=0,0,IF(I28=1,0,_xlfn.IFNA(INDEX(Attachment1!$B$63:$B$68,MATCH($C28,Attachment1!$A$63:$A$68,0)),0)*I28)) -> 0 | M28: =IF(I28=0,0,_xlfn.IFNA(INDEX(Attachment1!$C$63:$C$68,MATCH($C28,Attachment1!$A$63:$A$68,0)),0))*I28 -> 0 | P28: =SUM(K28:M28) -> 0
A29: 19 | J29: IDR | K29: =IF($C29=Attachment1!$A$63,_xlfn.IFNA(INDEX(database!$O$3:$O$7,MATCH(G29&H29,database!$M$3:$M$8,0)),0),_xlfn.IFNA(INDEX(database!$N$3:$N$7,MATCH(G29&H29,database!$M$3:$M$8,0)),0)) -> 0 | L29: =IF(I29=0,0,IF(I29=1,0,_xlfn.IFNA(INDEX(Attachment1!$B$63:$B$68,MATCH($C29,Attachment1!$A$63:$A$68,0)),0)*I29)) -> 0 | M29: =IF(I29=0,0,_xlfn.IFNA(INDEX(Attachment1!$C$63:$C$68,MATCH($C29,Attachment1!$A$63:$A$68,0)),0))*I29 -> 0 | P29: =SUM(K29:M29) -> 0
A30: 20 | J30: IDR | K30: =IF($C30=Attachment1!$A$63,_xlfn.IFNA(INDEX(database!$O$3:$O$7,MATCH(G30&H30,database!$M$3:$M$8,0)),0),_xlfn.IFNA(INDEX(database!$N$3:$N$7,MATCH(G30&H30,database!$M$3:$M$8,0)),0)) -> 0 | L30: =IF(I30=0,0,IF(I30=1,0,_xlfn.IFNA(INDEX(Attachment1!$B$63:$B$68,MATCH($C30,Attachment1!$A$63:$A$68,0)),0)*I30)) -> 0 | M30: =IF(I30=0,0,_xlfn.IFNA(INDEX(Attachment1!$C$63:$C$68,MATCH($C30,Attachment1!$A$63:$A$68,0)),0))*I30 -> 0 | P30: =SUM(K30:M30) -> 0
A31: =A30+1 -> 21 | J31: IDR | K31: =IF($C31=Attachment1!$A$63,_xlfn.IFNA(INDEX(database!$O$3:$O$7,MATCH(G31&H31,database!$M$3:$M$8,0)),0),_xlfn.IFNA(INDEX(database!$N$3:$N$7,MATCH(G31&H31,database!$M$3:$M$8,0)),0)) -> 0 | L31: =IF(I31=0,0,IF(I31=1,0,_xlfn.IFNA(INDEX(Attachment1!$B$63:$B$68,MATCH($C31,Attachment1!$A$63:$A$68,0)),0)*I31)) -> 0 | M31: =IF(I31=0,0,_xlfn.IFNA(INDEX(Attachment1!$C$63:$C$68,MATCH($C31,Attachment1!$A$63:$A$68,0)),0))*I31 -> 0 | P31: =SUM(K31:M31) -> 0
A32: =A31+1 -> 22 | J32: IDR | K32: =IF($C32=Attachment1!$A$63,_xlfn.IFNA(INDEX(database!$O$3:$O$7,MATCH(G32&H32,database!$M$3:$M$8,0)),0),_xlfn.IFNA(INDEX(database!$N$3:$N$7,MATCH(G32&H32,database!$M$3:$M$8,0)),0)) -> 0 | L32: =IF(I32=0,0,IF(I32=1,0,_xlfn.IFNA(INDEX(Attachment1!$B$63:$B$68,MATCH($C32,Attachment1!$A$63:$A$68,0)),0)*I32)) -> 0 | M32: =IF(I32=0,0,_xlfn.IFNA(INDEX(Attachment1!$C$63:$C$68,MATCH($C32,Attachment1!$A$63:$A$68,0)),0))*I32 -> 0 | P32: =SUM(K32:M32) -> 0
A33: =A32+1 -> 23 | J33: IDR | K33: =IF($C33=Attachment1!$A$63,_xlfn.IFNA(INDEX(database!$O$3:$O$7,MATCH(G33&H33,database!$M$3:$M$8,0)),0),_xlfn.IFNA(INDEX(database!$N$3:$N$7,MATCH(G33&H33,database!$M$3:$M$8,0)),0)) -> 0 | L33: =IF(I33=0,0,IF(I33=1,0,_xlfn.IFNA(INDEX(Attachment1!$B$63:$B$68,MATCH($C33,Attachment1!$A$63:$A$68,0)),0)*I33)) -> 0 | M33: =IF(I33=0,0,_xlfn.IFNA(INDEX(Attachment1!$C$63:$C$68,MATCH($C33,Attachment1!$A$63:$A$68,0)),0))*I33 -> 0 | P33: =SUM(K33:M33) -> 0
A34: =A33+1 -> 24 | J34: IDR | K34: =IF($C34=Attachment1!$A$63,_xlfn.IFNA(INDEX(database!$O$3:$O$7,MATCH(G34&H34,database!$M$3:$M$8,0)),0),_xlfn.IFNA(INDEX(database!$N$3:$N$7,MATCH(G34&H34,database!$M$3:$M$8,0)),0)) -> 0 | L34: =IF(I34=0,0,IF(I34=1,0,_xlfn.IFNA(INDEX(Attachment1!$B$63:$B$68,MATCH($C34,Attachment1!$A$63:$A$68,0)),0)*I34)) -> 0 | M34: =IF(I34=0,0,_xlfn.IFNA(INDEX(Attachment1!$C$63:$C$68,MATCH($C34,Attachment1!$A$63:$A$68,0)),0))*I34 -> 0 | P34: =SUM(K34:M34) -> 0
A35: =A34+1 -> 25 | J35: IDR | K35: =IF($C35=Attachment1!$A$63,_xlfn.IFNA(INDEX(database!$O$3:$O$7,MATCH(G35&H35,database!$M$3:$M$8,0)),0),_xlfn.IFNA(INDEX(database!$N$3:$N$7,MATCH(G35&H35,database!$M$3:$M$8,0)),0)) -> 0 | L35: =IF(I35=0,0,IF(I35=1,0,_xlfn.IFNA(INDEX(Attachment1!$B$63:$B$68,MATCH($C35,Attachment1!$A$63:$A$68,0)),0)*I35)) -> 0 | M35: =IF(I35=0,0,_xlfn.IFNA(INDEX(Attachment1!$C$63:$C$68,MATCH($C35,Attachment1!$A$63:$A$68,0)),0))*I35 -> 0 | P35: =SUM(K35:M35) -> 0
A36: =A35+1 -> 26 | J36: IDR | K36: =IF($C36=Attachment1!$A$63,_xlfn.IFNA(INDEX(database!$O$3:$O$7,MATCH(G36&H36,database!$M$3:$M$8,0)),0),_xlfn.IFNA(INDEX(database!$N$3:$N$7,MATCH(G36&H36,database!$M$3:$M$8,0)),0)) -> 0 | L36: =IF(I36=0,0,IF(I36=1,0,_xlfn.IFNA(INDEX(Attachment1!$B$63:$B$68,MATCH($C36,Attachment1!$A$63:$A$68,0)),0)*I36)) -> 0 | M36: =IF(I36=0,0,_xlfn.IFNA(INDEX(Attachment1!$C$63:$C$68,MATCH($C36,Attachment1!$A$63:$A$68,0)),0))*I36 -> 0 | P36: =SUM(K36:M36) -> 0
A37: =A36+1 -> 27 | J37: IDR | K37: =IF($C37=Attachment1!$A$63,_xlfn.IFNA(INDEX(database!$O$3:$O$7,MATCH(G37&H37,database!$M$3:$M$8,0)),0),_xlfn.IFNA(INDEX(database!$N$3:$N$7,MATCH(G37&H37,database!$M$3:$M$8,0)),0)) -> 0 | L37: =IF(I37=0,0,IF(I37=1,0,_xlfn.IFNA(INDEX(Attachment1!$B$63:$B$68,MATCH($C37,Attachment1!$A$63:$A$68,0)),0)*I37)) -> 0 | M37: =IF(I37=0,0,_xlfn.IFNA(INDEX(Attachment1!$C$63:$C$68,MATCH($C37,Attachment1!$A$63:$A$68,0)),0))*I37 -> 0 | P37: =SUM(K37:M37) -> 0
A38: =A37+1 -> 28 | J38: IDR | K38: =IF($C38=Attachment1!$A$63,_xlfn.IFNA(INDEX(database!$O$3:$O$7,MATCH(G38&H38,database!$M$3:$M$8,0)),0),_xlfn.IFNA(INDEX(database!$N$3:$N$7,MATCH(G38&H38,database!$M$3:$M$8,0)),0)) -> 0 | L38: =IF(I38=0,0,IF(I38=1,0,_xlfn.IFNA(INDEX(Attachment1!$B$63:$B$68,MATCH($C38,Attachment1!$A$63:$A$68,0)),0)*I38)) -> 0 | M38: =IF(I38=0,0,_xlfn.IFNA(INDEX(Attachment1!$C$63:$C$68,MATCH($C38,Attachment1!$A$63:$A$68,0)),0))*I38 -> 0 | P38: =SUM(K38:M38) -> 0
A39: =A38+1 -> 29 | J39: IDR | K39: =IF($C39=Attachment1!$A$63,_xlfn.IFNA(INDEX(database!$O$3:$O$7,MATCH(G39&H39,database!$M$3:$M$8,0)),0),_xlfn.IFNA(INDEX(database!$N$3:$N$7,MATCH(G39&H39,database!$M$3:$M$8,0)),0)) -> 0 | L39: =IF(I39=0,0,IF(I39=1,0,_xlfn.IFNA(INDEX(Attachment1!$B$63:$B$68,MATCH($C39,Attachment1!$A$63:$A$68,0)),0)*I39)) -> 0 | M39: =IF(I39=0,0,_xlfn.IFNA(INDEX(Attachment1!$C$63:$C$68,MATCH($C39,Attachment1!$A$63:$A$68,0)),0))*I39 -> 0 | P39: =SUM(K39:M39) -> 0
A40: =A39+1 -> 30 | J40: IDR | K40: =IF($C40=Attachment1!$A$63,_xlfn.IFNA(INDEX(database!$O$3:$O$7,MATCH(G40&H40,database!$M$3:$M$8,0)),0),_xlfn.IFNA(INDEX(database!$N$3:$N$7,MATCH(G40&H40,database!$M$3:$M$8,0)),0)) -> 0 | L40: =IF(I40=0,0,IF(I40=1,0,_xlfn.IFNA(INDEX(Attachment1!$B$63:$B$68,MATCH($C40,Attachment1!$A$63:$A$68,0)),0)*I40)) -> 0 | M40: =IF(I40=0,0,_xlfn.IFNA(INDEX(Attachment1!$C$63:$C$68,MATCH($C40,Attachment1!$A$63:$A$68,0)),0))*I40 -> 0 | P40: =SUM(K40:M40) -> 0
C42: TOTAL | P42: =SUM(P11:P40) -> 9450000
B44: Create by, | D44: Competent Division, | H44: Review by, | M44: Approved by,
B47: Name : | D47: Name : _____________________ | H47: Name : ____________________ | M47: Name : __________________
B48: ="Division : "&" "&B5 -> Division : 2026 | D48: Comp Div Name : ____________ | H48: Head of FA | M48: Director
B49: =B3 -> PT Perintis Triniti Properti Tbk | D49: =B3 -> PT Perintis Triniti Properti Tbk | H49: =$B$3 -> PT Perintis Triniti Properti Tbk | M49: =$B$3 -> PT Perintis Triniti Properti Tbk
B54: Asumsi Perjalanan dan Akomodasi
B55: HFA, RA, | C55: Sebulan 1x | D55: 3 Hari 2 Malam | E55: September- Des 2021
B56: HFA, RA, | C56: Sebulan 4x | D56: 4 Hari 3 Malam | E56: Jan- Des 2022
B57: Marketing | C57: Sebulan 1x | D57: 26 Hari | E57: Jan- Des 2022

Sheet HC Program
A2: Budget HC Program
A3: Budget Year
A5: HUMAN CAPITAL PROGRAM
A7: No | B7: COMPANY | C7: Project | D7: PERIOD | E7: COST CATEGORY | F7: TOPIC/ACTIVITY | G7: INSTITUTION NAME | H7: UoM | I7: Qty | J7: Curr | K7: Price / Unit | L7: COST VALUE | O7: Budget HC Program
A8: 1 | J8: IDR | L8: =I8*K8 -> 0 | R8: 44197 | S8: 44228 | T8: 44256 | U8: 44287 | V8: 44317 | W8: 44348 | X8: 44378 | Y8: 44409 | Z8: 44440 | AA8: 44470 | AB8: 44501 | AC8: 44531 | AD8: TOTAL
A9: 2 | J9: IDR | L9: =I9*K9 -> 0 | O9: 62120001 | P9: Biaya Pelatihan & Seminar | Q9: Pelatihan & Seminar | R9: =SUMIF($E:$E,Q$9,$L:$L) -> 0 | S9: =SUMIF($E:$E,R$9,$L:$L) -> 0 | T9: =SUMIF($E:$E,S$9,$L:$L) -> 0 | U9: =SUMIF($E:$E,T$9,$L:$L) -> 0 | V9: =SUMIF($E:$E,U$9,$L:$L) -> 0 | W9: =SUMIF($E:$E,V$9,$L:$L) -> 0 | X9: =SUMIF($E:$E,W$9,$L:$L) -> 0 | Y9: =SUMIF($E:$E,X$9,$L:$L) -> 0 | ... AC9: =SUMIF($E:$E,AB$9,$L:$L) -> 0 | AD9: =SUM(R9:AC9) -> 0
A10: 3 | J10: IDR | L10: =I10*K10 -> 0 | O10: 62120003 | P10: Biaya Gathering / Outing / Employee Event | Q10: Gathering / HC Event | R10: =SUMIF($E:$E,Q$10,$L:$L) -> 0 | S10: =SUMIF($E:$E,R$10,$L:$L) -> 0 | T10: =SUMIF($E:$E,S$10,$L:$L) -> 0 | U10: =SUMIF($E:$E,T$10,$L:$L) -> 0 | V10: =SUMIF($E:$E,U$10,$L:$L) -> 0 | W10: =SUMIF($E:$E,V$10,$L:$L) -> 0 | X10: =SUMIF($E:$E,W$10,$L:$L) -> 0 | Y10: =SUMIF($E:$E,X$10,$L:$L) -> 0 | ... AC10: =SUMIF($E:$E,AB$10,$L:$L) -> 0 | AD10: =SUM(R10:AC10) -> 0
A11: 4 | J11: IDR | L11: =I11*K11 -> 0 | O11: 62120006 | P11: Biaya Lainnya | Q11: Others | R11: =SUMIF($E:$E,Q$11,$L:$L) -> 0 | S11: =SUMIF($E:$E,R$11,$L:$L) -> 0 | T11: =SUMIF($E:$E,S$11,$L:$L) -> 0 | U11: =SUMIF($E:$E,T$11,$L:$L) -> 0 | V11: =SUMIF($E:$E,U$11,$L:$L) -> 0 | W11: =SUMIF($E:$E,V$11,$L:$L) -> 0 | X11: =SUMIF($E:$E,W$11,$L:$L) -> 0 | Y11: =SUMIF($E:$E,X$11,$L:$L) -> 0 | ... AC11: =SUMIF($E:$E,AB$11,$L:$L) -> 0 | AD11: =SUM(R11:AC11) -> 0
A12: 5 | J12: IDR | L12: =I12*K12 -> 0
A13: 6 | J13: IDR | L13: =I13*K13 -> 0
A14: 7 | J14: IDR | L14: =I14*K14 -> 0
A15: 8 | J15: IDR | L15: =I15*K15 -> 0
A16: 9 | J16: IDR | L16: =I16*K16 -> 0
A17: 10 | J17: IDR | L17: =I17*K17 -> 0
A18: 11 | J18: IDR | L18: =I18*K18 -> 0
A19: 12 | J19: IDR | L19: =I19*K19 -> 0
A20: 13 | J20: IDR | L20: =I20*K20 -> 0
A21: 14 | J21: IDR | L21: =I21*K21 -> 0
A22: 15 | J22: IDR | L22: =I22*K22 -> 0
A23: 16 | J23: IDR | L23: =I23*K23 -> 0
... A82: 75 | J82: IDR | L82: =I82*K82 -> 0
H84: TOTAL | L84: =SUM(L8:L82) -> 0
B86: Create by, | F86: Review by, | I86: Approved by,
B90: Name : ____________________ | F90: Name : ____________________ | I90: Name : __________________
B91: HC Divison | F91: Head of FA | I91: Director

Sheet database
A1: CompanyName | B1: CompName | C1: ProyekName | D1: Currency | E1: Bulan | F1: Justification | G1: Destination | H1: Local | I1: Overseas | J1: AnP | K1: Aset | L1: HC | M1: Destination | N1: Ekonomi Class | O1: Ekonomi Class | P1: YTD | Q1: MTD
A2: Pilih Perusahaan | B2: Pilih Perusahaan | C2: Pilih Project | D2: IDR | E2: 45658 | F2: Must To Have | G2: Local | H2: Jakarta | I2: Jakarta | J2: Media Digital, Online, TV, Radio | K2: Bangunan | L2: Pelatihan & Seminar | N2: Citilink, Sriwijaya, Lion Air | O2: Garuda, Batik | P2: YTD JAN | Q2: JAN
A3: PT Perintis Triniti Properti Tbk | B3: =A3 -> PT Perintis Triniti Properti Tbk | C3: Head Office | D3: USD | E3: 45689 | F3: Nice To Have | G3: Overseas | H3: Labuan Bajo | I3: Singapore | J3: Media Cetak, Brosur, Spanduk, Katalog | K3: Kendaraan Operasional | L3: Gathering / HC Event | M3: =database!$H$2&database!H3 -> JakartaLabuan Bajo | N3: 4000000 | O3: 4500000 | P3: YTD FEB | Q3: FEB
A4: PT Sirius Terang Cemerlang | B4: =A4 -> PT Sirius Terang Cemerlang | C4: Brooklyn | D4: SGD | E4: 45717 | H4: Pontianak | I4: China | J4: Signage | K4: Peralatan Kantor | L4: Others | M4: =database!$H$2&database!H4 -> JakartaPontianak | N4: 2000000 | O4: 3000000 | P4: YTD MAR | Q4: MAR
A5: PT Triniti Menara Serpong | B5: =A5 -> PT Triniti Menara Serpong | C5: Yukata | D5: CNY | E5: 45748 | H5: Batam | I5: Hongkong | J5: Billboard | K5: Furnitur dan Perlengkapan Kantor | M5: =database!$H$2&database!H5 -> JakartaBatam | N5: 2500000 | O5: 3000000 | P5: YTD APR | Q5: APR
A6: PT Puri Triniti Batam | B6: =A6 -> PT Puri Triniti Batam | C6: Collins Boulevard | D6: EUR | E6: 45778 | H6: Palembang | I6: Australia | J6: Events & Exibition | K6: IT Hardware & Software | M6: =database!$H$2&database!H6 -> JakartaPalembang | P6: YTD MAY | Q6: MAY
A7: PT Triniti Pilar Gemilang | B7: =A9 -> PT Triniti Dinamik | C7: Marc's Boulevard | E7: 45809 | H7: Lampung | I7: Malaysia | J7: RoadSHow | K7: Peralatan Lainnya | M7: =database!$H$2&database!H7 -> JakartaLampung | N7: 1500000 | O7: 2000000 | P7: YTD JUN | Q7: JUN
A8: PT Triniti Menara Gading | B8: =A9 -> PT Triniti Dinamik | C8: The Smith | E8: 45839 | H8: Balikpapan | I8: Thailand | J8: Transportasi dan Akomodasi | M8: =database!$H$2&database!H8 -> JakartaBalikpapan | N8: =2400000 -> 2400000 | O8: 3000000 | P8: YTD JUL | Q8: JUL
A9: PT Triniti Dinamik | B9: =A10 -> PT Triniti Garam Properti | C9: Springwood | E9: 45870 | J9: Maket & Support | P9: YTD AUG | Q9: AUG
A10: PT Triniti Garam Properti | C10: Lampung-Holdwell Business Park | E10: 45901 | J10: Show Unit | P10: YTD SEP | Q10: SEP
A11: Sentul - JO | C11: Lampung-Noble Spring Residence | E11: 45931 | J11: Reward | P11: YTD OCT | Q11: OCT
C12: Sentul-19ha | E12: 45962 | J12: Beban Marketing Promosi Lainnya | P12: YTD NOV | Q12: NOV
C13: Sentul-72ha | E13: 45992 | P13: YTD DEC | Q13: DEC
C14: District East | E14: 46023 | Q14: TOTAL
E15: 46054
E16: 46082
E17: 46113
E18: 46143
E19: 46174
E20: 46204
E21: 46235
E22: 46266
E23: 46296
E24: 46327
E25: 46357

Sheet CASHFLOW (ongoing link)
A1: Proyeksi Cash Flow
A2: ENTITAS: | B2: Pilih Perusahaan
A3: PROJECT | B3: Pilih Project
A4: YEARS | B4: 2027 | C4: =SUM(B8,B8,B8) -> 0
A6: AKTIVITAS ARUS KAS | B6: ACTUAL JAN - AUG 26 | C6: BE SEP - DES 26 | D6: TOTAL FY 2027 | E6: 46388 | F6: 46419 | G6: 46447 | H6: 46478 | I6: 46508 | J6: 46539 | K6: 46569 | L6: 46600 | M6: 46631 | N6: 46661 | O6: 46692 | P6: 46722
A7: ARUS KAS DARI AKTIVITAS OPERASI
A8: PENERIMAAN KAS DARI AKTIVITAS OPERASI | B8: =SUM(B9:B18) -> 0 | C8: =SUM(C9:C18) -> 0 | D8: =SUM(D9:D18) -> 0 | E8: =SUM(E9:E18) -> 0 | F8: =SUM(F9:F18) -> 0 | G8: =SUM(G9:G18) -> 0 | H8: =SUM(H9:H18) -> 0 | I8: =SUM(I9:I18) -> 0 | ... P8: =SUM(P9:P18) -> 0
A9: PENERIMAAN DARI KONSUMEN
A10: UANG MUKA PELANGGAN - APARTMENT | D10: =SUM(E10:P10) -> 0
A11: UANG MUKA PELANGGAN - CONDOVILLA | D11: =SUM(E11:P11) -> 0
A12: UANG MUKA PELANGGAN - SHOPHOUSE/COMMERCIAL | D12: =SUM(E12:P12) -> 0
A13: UANG MUKA PELANGGAN - LANDED HOUSE | D13: =SUM(E13:P13) -> 0
A14: PENJUALAN UNIT READY TO BUILD LAND / KAVLING | D14: =SUM(E14:P14) -> 0
A15: UANG MUKA PELANGGAN - BUSINESS PARK | D15: =SUM(E15:P15) -> 0
A16: PIUTANG USAHA | D16: =SUM(E16:P16) -> 0
A17: PENERIMAAN LAINNYA
A18: LAIN-LAIN | D18: =SUM(E18:P18) -> 0
A19: PENGELUARAN KAS DARI AKTIVITAS OPERASI
A20: PENGELUARAN OPERASIONAL | B20: =SUM(B21:B178) -> 0 | C20: =SUM(C21:C178) -> 0 | D20: =SUM(D21:D178) -> 0 | E20: =SUM(E21:E178) -> 0 | F20: =SUM(F21:F178) -> 0 | G20: =SUM(G21:G178) -> 0 | H20: =SUM(H21:H178) -> 0 | I20: =SUM(I21:I178) -> 0 | ... P20: =SUM(P21:P178) -> 0
A21: BEBAN KOMISI PENJUALAN
A22: KOMISI PENJUALAN SALES INHOUSE | D22: =SUM(E22:P22) -> 0
A23: KOMISI PENJUALAN SALES AGENT | D23: =SUM(E23:P23) -> 0
A24: BEBAN PROGRAM PENJUALAN
A25: SUBSIDI BOOKING FEE | D25: =SUM(E25:P25) -> 0
A26: SUBSIDI DOWN PAYMENT | D26: =SUM(E26:P26) -> 0
A27: SUBSIDI ANGSURAN | D27: =SUM(E27:P27) -> 0
A28: SUBSIDI AKAD | D28: =SUM(E28:P28) -> 0
A29: RENTBACK | D29: =SUM(E29:P29) -> 0
A30: CASHBACK PATUNGAN RUMAH | D30: =SUM(E30:P30) -> 0
A31: BEBAN MARKETING & PROMOSI
A32: MEDIA DIGITAL / ONLINE (WEBSITE, TV, RADIO, M-ADS)
A33: MEDIA CETAK (MAJALAH, KORAN)
A34: PERCETAKAN BROSUR, SPANDUK, KATALOG, UMBUL2
A35: SIGNAGE | D35: =SUM(E35:P35) -> 0
A36: BILLBOARD | D36: =SUM(E36:P36) -> 0
A37: EVENTS & EXIBITION | D37: =SUM(E37:P37) -> 0
A38: SEWA PAMERAN | D38: =SUM(E38:P38) -> 0
A39: ROADSHOW | D39: =SUM(E39:P39) -> 0
A40: TRANSPORTASI DAN AKOMODASI | D40: =SUM(E40:P40) -> 0
A41: TRANSPORTASI DAN AKOMODASI MKT | D41: =SUM(E41:P41) -> 0
A42: MAKET & SUPPORT | D42: =SUM(E42:P42) -> 0
A43: SHOW UNIT | D43: =SUM(E43:P43) -> 0
A44: REWARD | D44: =SUM(E44:P44) -> 0
A45: REWARD - KONSUMEN | D45: =SUM(E45:P45) -> 0
A46: BEBAN MARKETING PROMOSI LAINNYA | D46: =SUM(E46:P46) -> 0
A47: BEBAN KARYAWAN
A48: BEBAN GAJI, THR & BONUS
A49: BEBAN TRANSPORTASI
A50: BEBAN TUNJANGAN TRANSPORTASI
A51: BEBAN PESANGON
A52: BEBAN UANG MAKAN
A53: BEBAN LEMBUR
A54: BEBAN ASURANSI
A55: BEBAN KARYAWAN
A56: BIAYA LEMBUR - PROJECT
A57: BEBAN ASURANSI KESEHATAN KARYAWAN
A58: BEBAN BPJS KESEHATAN
... A60: BEBAN BPJS KETENAGAKERJAAN
A61: BEBAN BILLING RATE | D61: =SUM(E61:P61) -> 0
A62: BEBAN IMBALAN PASCA KERJA | D62: =SUM(E62:P62) -> 0
A63: BIAYA PPH 21 - BACK OFFICE | D63: =SUM(E63:P63) -> 0
A64: BIAYA TUNJANGAN LAINNYA - BACK OFFICE | D64: =SUM(E64:P64) -> 0
A65: BIAYA TUNJANGAN LAINNYA - MARKETING | D65: =SUM(E65:P65) -> 0
A66: BEBAN TUNJANGAN KARYAWAN | D66: =SUM(E66:P66) -> 0
A67: BEBAN TUNJANGAN KARYAWAN | D67: =SUM(E67:P67) -> 0
A68: BEBAN PELATIHAN & SEMINAR | D68: =SUM(E68:P68) -> 0
A69: BEBAN PEREKRUTAN KARYAWAN | D69: =SUM(E69:P69) -> 0
A70: BEBAN GATHERING, OUTING, TEAM BUILDING | D70: =SUM(E70:P70) -> 0
A71: BEBAN SUMBANGAN UNTUK KARYAWAN | D71: =SUM(E71:P71) -> 0
A72: BEBAN PPH PS 21 | D72: =SUM(E72:P72) -> 0
... A74: BEBAN LAINNYA | D74: =SUM(E74:P74) -> 0
A75: BEBAN UMUM DAN ADMINISTRASI
A76: BEBAN PEMELIHARAAN & RENOVASI BANGUNAN KANTOR
A77: BEBAN PEMELIHARAAN INVENTARIS KANTOR
A78: BEBAN PEMELIHARAAN KENDARAAN KANTOR
A79: BEBAN SEWA BANGUNAN UNTUK OPERASIONAL KANTOR
A80: BEBAN SEWA RUMAH MESS UNTUK OPERASIONAL
A81: BEBAN SEWA GEDUNG UNTUK ACARA KANTOR
A82: BEBAN SEWA KENDARAAN
A83: BEBAN SEWA LAINNYA
A84: BEBAN SEWA PERALATAN
A85: BEBAN SEWA RUMAH DINAS / MESS KARYAWAN
A86: BEBAN SEWA PERALATAN KANTOR
... A97: BEBAN JASA PENYELENGGARA ACARA (EO)
A98: BEBAN JASA KONSULTAN SISTEM | D98: =SUM(E98:P98) -> 0
A99: BEBAN JASA PENERJEMAH (TRANSLATOR) | D99: =SUM(E99:P99) -> 0
A100: BEBAN JASA PENYELENGGARA ACARA (EO) | D100: =SUM(E100:P100) -> 0
A101: BEBAN JASA KONSULTAN PAJAK | D101: =SUM(E101:P101) -> 0
A102: BEBAN KONSULTAN MANAGEMENT/BISNIS | D102: =SUM(E102:P102) -> 0
A103: BEBAN JASA KEAMANAN | D103: =SUM(E103:P103) -> 0
A104: BEBAN JASA ANNUAL REPORT | D104: =SUM(E104:P104) -> 0
A105: BEBAN PERJALANAN DINAS LUAR KOTA | D105: =SUM(E105:P105) -> 0
A106: BEBAN PERJALANAN DINAS LUAR NEGERI | D106: =SUM(E106:P106) -> 0
A107: BEBAN TRANSPORTASI, BENSIN, TOLL, PARKIR, TAKSI | D107: =SUM(E107:P107) -> 0
A108: BEBAN LISTRIK DAN AIR | D108: =SUM(E108:P108) -> 0
A109: BEBAN LANGGANAN INTERNET, WEBSITE, TELEPON, PULSA HP | D109: =SUM(E109:P109) -> 0
... A131: BEBAN KANTOR HAND OVER | D131: =SUM(E131:P131) -> 0
A132: PENERIMAAN (BEBAN) LAIN-LAIN
A133: PENDAPATAN BUNGA
A134: PENDAPATAN BUNGA DEPOSITO
...

Sheet CF OLD
B2: CASH FLOW
B4: in IDR Mio
B6: MARKETING REVENUE ( In IDR Bio) | G6: 46023 | I6: 46054 | J6: 46082 | K6: 46113 | L6: 46143 | M6: 46174 | N6: 46204 | O6: 46235 | P6: 46266 | Q6: 46296 | R6: 46296 | S6: 46296 | T6: 46327 | U6: 46357 | V6: 46357 | W6: 46357 | X6: TOTAL
B7: Paul & Prive (Condovilla) | G7: 0 | I7: 0 | J7: 0 | K7: 0 | L7: 0 | M7: 720620000 | N7: 0 | O7: 0 | P7: 0 | Q7: 0 | R7: 0 | S7: 0 | T7: 0 | U7: 0 | V7: 0 | W7: 0 | X7: =SUM(G7:W7) -> 720620000
B8: Paul Lane (Shophouse) | G8: 0 | I8: 0 | J8: 0 | K8: 0 | L8: 0 | M8: 0 | N8: 0 | O8: 0 | P8: 0 | Q8: 0 | R8: 0 | S8: 0 | T8: 0 | U8: 0 | V8: 0 | W8: 0 | X8: =SUM(G8:W8) -> 0
B9: Glenn The Hive (Residential) Phase-1 | G9: 0 | I9: 0 | J9: 0 | K9: 0 | L9: 0 | M9: 0 | N9: 0 | O9: 0 | P9: 0 | Q9: 0 | R9: 0 | S9: 0 | T9: 0 | U9: 0 | V9: 0 | W9: 0 | X9: =SUM(G9:W9) -> 0
B10: Glenn The Hive (Residential) Phase-2
B11: TOTAL MARKETING REVENUE | G11: =SUM(G7:G10) -> 0 | I11: =SUM(I7:I10) -> 0 | J11: =SUM(J7:J10) -> 0 | K11: =SUM(K7:K10) -> 0 | L11: =SUM(L7:L10) -> 0 | M11: =SUM(M7:M10) -> 720620000 | N11: =SUM(N7:N10) -> 0 | O11: =SUM(O7:O10) -> 0 | P11: =SUM(P7:P10) -> 0 | ... X11: =SUM(X7:X10) -> 720620000
B13: Statement of Cash Flow (In IDR Mio) | F13: TOTAL ALL | G13: ACTUAL 2025 | H13: BEST ESTIMATE | K13: BEST ESTIMATE | L13: PROJECTION | X13: TOTAL BE
G14: YTD SEP 25 | H14: 45931 | I14: 45962 | J14: 45992 | K14: 2025 | L14: 46023 | M14: 46054 | N14: 46082 | O14: 46113 | P14: 46143 | Q14: 46174 | R14: 46204 | S14: 46235 | T14: 46266 | U14: 46296 | V14: 46327 | W14: 46357 | X14: 2026
B16: Operating Activities
C17: Collection from customer | F17: =SUM(F18:F22) -> 0 | G17: =SUM(G18:G22) -> 0 | I17: =SUM(I18:I22) -> 0 | J17: =SUM(J18:J22) -> 0 | K17: =SUM(K18:K22) -> 0 | L17: =SUM(L18:L22) -> 0 | M17: =SUM(M18:M22) -> 0 | N17: =SUM(N18:N22) -> 0 | O17: =SUM(O18:O22) -> 0 | P17: =SUM(P18:P22) -> 0 | ... X17: =SUM(X18:X22) -> 0
E18: ( diisi dengan penerimaan konsumen dari masing2 tipe cluster/ project ) | K18: =SUM(G18:J18) -> 0 | X18: =SUM(L18:W18) -> 0
K19: =SUM(G19:J19) -> 0 | X19: =SUM(L19:W19) -> 0
K20: =SUM(G20:J20) -> 0 | X20: =SUM(L20:W20) -> 0
K21: =SUM(G21:J21) -> 0 | X21: =SUM(L21:W21) -> 0
E22: Others income | K22: =SUM(G22:J22) -> 0 | X22: =SUM(L22:W22) -> 0
C23: Cash out for Operating Activities | F23: =F24+F35 -> 0 | G23: =G24+G35+G32 -> 0 | I23: =I24+I35+I32 -> 0 | J23: =J24+J35+J32 -> 0 | K23: =K24+K35+K32 -> 0 | L23: =L24+L35+L32 -> 0 | M23: =M24+M35+M32 -> 0 | N23: =N24+N35+N32 -> 0 | O23: =O24+O35+O32 -> 0 | P23: =P24+P35+P32 -> 0 | ... X23: =X24+X35+X32 -> 0
D24: Operational Cost (Non Cons) | F24: =SUM(F25:F30) -> 0 | G24: =SUM(G25:G31) -> 0 | I24: =SUM(I25:I31) -> 0 | J24: =SUM(J25:J31) -> 0 | K24: =SUM(K25:K31) -> 0 | L24: =SUM(L25:L31) -> 0 | M24: =SUM(M25:M31) -> 0 | N24: =SUM(N25:N31) -> 0 | O24: =SUM(O25:O31) -> 0 | P24: =SUM(P25:P31) -> 0 | ... X24: =SUM(X25:X31) -> 0
E25: Sales Commission | K25: =SUM(G25:J25) -> 0 | X25: =SUM(L25:W25) -> 0
E26: Marketing Cost | K26: =SUM(G26:J26) -> 0 | X26: =SUM(L26:W26) -> 0
E27: Employee Expense | K27: =SUM(G27:J27) -> 0 | X27: =SUM(L27:W27) -> 0
E28: Operational Expenses | K28: =SUM(G28:J28) -> 0 | X28: =SUM(L28:W28) -> 0
E29: Others Income (Expenses) | K29: =SUM(G29:J29) -> 0 | X29: =SUM(L29:W29) -> 0
E30: Taxes | K30: =SUM(G30:J30) -> 0 | X30: =SUM(L30:W30) -> 0
E31: Management Fee | G31: 0 | I31: 0 | J31: 0 | K31: =SUM(G31:J31) -> 0 | L31: 0 | M31: 0 | N31: 0 | O31: 0 | P31: 0 | X31: =SUM(L31:W31) -> 0
D32: Land cost | G32: =SUM(G33:G34) -> 0 | I32: =SUM(I33:I34) -> 0 | J32: =SUM(J33:J34) -> 0 | K32: =SUM(K33:K34) -> 0 | L32: =SUM(L33:L34) -> 0 | M32: =SUM(M33:M34) -> 0 | N32: =SUM(N33:N34) -> 0 | O32: =SUM(O33:O34) -> 0 | P32: =SUM(P33:P34) -> 0 | ... X32: =SUM(X33:X34) -> 0
E33: Land Preparation Cost
E34: Land Acquisition Cost
D35: Development Cost | F35: =SUM(F36:F40) -> 0 | G35: =SUM(G36:G40) -> 0 | I35: =SUM(I36:I40) -> 0 | J35: =SUM(J36:J40) -> 0 | K35: =SUM(K36:K40) -> 0 | L35: =SUM(L36:L40) -> 0 | M35: =SUM(M36:M40) -> 0 | N35: =SUM(N36:N40) -> 0 | O35: =SUM(O36:O40) -> 0 | P35: =SUM(P36:P40) -> 0 | ... X35: =SUM(X36:X40) -> 0
E36: Construction Cost | K36: =SUM(G36:J36) -> 0 | X36: =SUM(L36:W36) -> 0
E37: Infrastructure Cost | K37: =SUM(G37:J37) -> 0 | X37: =SUM(L37:W37) -> 0
E38: Facilities Cost | K38: =SUM(G38:J38) -> 0 | X38: =SUM(L38:W38) -> 0
E39: Design & Professional Fees | K39: =SUM(G39:J39) -> 0 | X39: =SUM(L39:W39) -> 0
E40: Legal, License & Permits | K40: =SUM(G40:J40) -> 0 | X40: =SUM(L40:W40) -> 0
B42: Net from Operating Activities | F42: =F17+F23 -> 0 | G42: =G17+G23 -> 0 | I42: =I17+I23 -> 0 | J42: =J17+J23 -> 0 | K42: =K17+K23 -> 0 | L42: =L17+L23 -> 0 | M42: =M17+M23 -> 0 | N42: =N17+N23 -> 0 | O42: =O17+O23 -> 0 | P42: =P17+P23 -> 0 | ... X42: =X17+X23 -> 0
C43: Accumulative Operating Activities | F43: =F42 -> 0 | G43: =G42 -> 0 | I43: =G43+I42 -> 0 | J43: =I43+J42 -> 0 | K43: =J43+K42 -> 0 | L43: =K43+L42 -> 0 | M43: =L43+M42 -> 0 | N43: =M43+N42 -> 0 | O43: =N43+O42 -> 0 | P43: =O43+P42 -> 0 | Q43: =O43+Q42 -> 0 | R43: =O43+R42 -> 0 | S43: =P43+S42 -> 0 | T43: =S43+T42 -> 0 | U43: =R43+U42 -> 0 | V43: =S43+V42 -> 0 | W43: =T43+W42 -> 0
B44: Investing Activities
C45: Purchase of fixed asset | K45: =SUM(G45:J45) -> 0 | X45: =SUM(L45:W45) -> 0
C46: Research & Development | K46: =SUM(G46:J46) -> 0 | X46: =SUM(L46:W46) -> 0
B48: Net from Investing Activities | F48: =SUM(F45:F46) -> 0 | G48: =SUM(G45:G46) -> 0 | I48: =SUM(I45:I46) -> 0 | J48: =SUM(J45:J46) -> 0 | K48: =SUM(K45:K46) -> 0 | L48: =SUM(L45:L46) -> 0 | M48: =SUM(M45:M46) -> 0 | N48: =SUM(N45:N46) -> 0 | O48: =SUM(O45:O46) -> 0 | P48: =SUM(P45:P46) -> 0 | ... X48: =SUM(X45:X46) -> 0
C49: Accumulative Investing Activities | F49: =F48 -> 0 | G49: =G48 -> 0 | I49: =G49+I48 -> 0 | J49: =I49+J48 -> 0 | K49: =J49+K48 -> 0 | L49: =K49+L48 -> 0 | M49: =L49+M48 -> 0 | N49: =M49+N48 -> 0 | O49: =N49+O48 -> 0 | P49: =O49+P48 -> 0 | Q49: =O49+Q48 -> 0 | R49: =O49+R48 -> 0 | S49: =P49+S48 -> 0 | T49: =S49+T48 -> 0 | U49: =R49+U48 -> 0 | V49: =S49+V48 -> 0 | W49: =T49+W48 -> 0 | X49: =X48 -> 0
B50: Financing Activities
D51: Equity | K51: =SUM(G51:J51) -> 0 | X51: =SUM(L51:W51) -> 0
D52: Loan Disbursement | K52: =SUM(G52:J52) -> 0 | X52: =SUM(G52:W52) -> 0
E53: Loan Principal Payment | K53: =SUM(G53:J53) -> 0 | X53: =SUM(G53:W53) -> 0
D54: Receipt/(Payment) for Loan - Non Bank | K54: =SUM(G54:J54) -> 0 | X54: =SUM(G54:W54) -> 0
D55: from Bank Loan | K55: =SUM(G55:J55) -> 0 | X55: =SUM(G55:W55) -> 0
D56: Intercompay AP | K56: =SUM(G56:J56) -> 0 | X56: =SUM(G56:W56) -> 0
D57: Others Receive from Financing | K57: =SUM(G57:J57) -> 0 | X57: =SUM(G57:W57) -> 0
D58: Payments of Loan Bank | K58: =SUM(G58:J58) -> 0 | X58: =SUM(G58:W58) -> 0
D59: Payments of Interest on Loans | K59: =SUM(G59:J59) -> 0 | X59: =SUM(G59:W59) -> 0
D60: Payment of Loan Interest tax | K60: =SUM(G60:J60) -> 0 | X60: =SUM(G60:W60) -> 0
D61: Payments of Loan Non Bank | K61: =SUM(G61:J61) -> 0 | X61: =SUM(G61:W61) -> 0
D62: Intercompay AR | K62: =SUM(G62:J62) -> 0 | X62: =SUM(G62:W62) -> 0
D63: Shareholder Loan | K63: =SUM(G63:J63) -> 0 | X63: =SUM(G63:W63) -> 0
D64: Restricted Deposito in Banks | K64: =SUM(G64:J64) -> 0 | X64: =SUM(G64:W64) -> 0
B67: Net from Financing Activities | F67: =SUM(F51:F64) -> 0 | G67: =SUM(G51:G64) -> 0 | I67: =SUM(I51:I64) -> 0 | J67: =SUM(J51:J64) -> 0 | K67: =SUM(K51:K64) -> 0 | L67: =SUM(L51:L64) -> 0 | M67: =SUM(M51:M64) -> 0 | N67: =SUM(N51:N64) -> 0 | O67: =SUM(O51:O64) -> 0 | P67: =SUM(P51:P64) -> 0 | ... X67: =SUM(X51:X64) -> 0
C68: Accumulative Financing Activities | F68: =F67 -> 0 | G68: =G67 -> 0 | I68: =G68+I67 -> 0 | J68: =I68+J67 -> 0 | K68: =J68+K67 -> 0 | L68: =K68+L67 -> 0 | M68: =L68+M67 -> 0 | N68: =M68+N67 -> 0 | O68: =N68+O67 -> 0 | P68: =O68+P67 -> 0 | Q68: =O68+Q67 -> 0 | R68: =O68+R67 -> 0 | S68: =P68+S67 -> 0 | T68: =S68+T67 -> 0 | U68: =R68+U67 -> 0 | V68: =S68+V67 -> 0 | W68: =T68+W67 -> 0 | X68: =X67 -> 0
B69: SURPLUS / (DEFISIT) | F69: =F42+F48+F67 -> 0 | G69: =G42+G48+G67 -> 0 | I69: =I42+I48+I67 -> 0 | J69: =J42+J48+J67 -> 0 | K69: =K42+K48+K67 -> 0 | L69: =L42+L48+L67 -> 0 | M69: =M42+M48+M67 -> 0 | N69: =N42+N48+N67 -> 0 | O69: =O42+O48+O67 -> 0 | P69: =P42+P48+P67 -> 0 | ... X69: =X42+X48+X67 -> 0
C70: Accumulative Surplus/(Defisit) | F70: =F69 -> 0 | G70: =G69 -> 0 | I70: =G70+I69 -> 0 | J70: =I70+J69 -> 0 | K70: =J70+K69 -> 0 | L70: =K70+L69 -> 0 | M70: =L70+M69 -> 0 | N70: =M70+N69 -> 0 | O70: =N70+O69 -> 0 | P70: =O70+P69 -> 0 | Q70: =O70+Q69 -> 0 | R70: =O70+R69 -> 0 | S70: =P70+S69 -> 0 | T70: =S70+T69 -> 0 | U70: =R70+U69 -> 0 | V70: =S70+V69 -> 0 | W70: =T70+W69 -> 0 | X70: =X69 -> 0
B71: BEGINNING BALANCE | F71: 0 | I71: =G72 -> 0 | J71: =I72 -> 0 | K71: =J72 -> 0 | L71: =K72 -> 0 | M71: =L72 -> 0 | N71: =M72 -> 0 | O71: =N72 -> 0 | P71: =O72 -> 0 | Q71: =O72 -> 0 | R71: =O72 -> 0 | S71: =P72 -> 0 | T71: =S72 -> 0 | U71: =R72 -> 0 | V71: =S72 -> 0 | W71: =T72 -> 0 | X71: =G71 -> 0
B72: ENDING BALANCE | F72: =F69+F71 -> 0 | G72: =G69+G71 -> 0 | I72: =I69+I71 -> 0 | J72: =J69+J71 -> 0 | K72: =K69+K71 -> 0 | L72: =L69+L71 -> 0 | M72: =M69+M71 -> 0 | N72: =N69+N71 -> 0 | O72: =O69+O71 -> 0 | P72: =P69+P71 -> 0 | ... X72: =X69+X71 -> 0
E73: Control
E74: Catatan Pengisian Data:
D75: 1 | E75: Untuk Kolom Actual YTD Okt 2026 Diisi dengan Link ke Workpaper Actual Breakdown CF dari Sistem, jangan dengan angka value / mati
D76: 2 | E76: Untuk Nilai pada Kolom Best Estimate 2026 dan 2026 harus diisi dengan Link ke Workpaper Breakdown Proyeksi, jangan dengan angka value/ mati
E79: Check
B80: Rekening Bank Escrow
B81: Mutasi Rekening Bank Escrow
G82: YTD JAN | I82: YTD FEB | J82: YTD MAR | K82: YTD APR | L82: YTD MAY | M82: YTD JUN | N82: YTD JUL | O82: YTD AUG | P82: YTD SEP | Q82: YTD OCT | R82: YTD NOV | S82: YTD DEC
D83: 2 | E83: Unit Sold | G83: =SUM($G$18:$G$21) -> 0 | I83: =SUM($G$17:I$17) -> 0 | J83: =SUM($G$17:J$17) -> 0 | K83: =SUM($G$17:K$17) -> 0 | L83: =SUM($G$17:L$17) -> 0 | M83: =SUM($G$17:M$17) -> 0 | N83: =SUM($G$17:N$17) -> 0 | O83: =SUM($G$17:O$17) -> 0 | P83: =SUM($G$17:P$17) -> 0 | ... S83: =SUM($G$17:S$17) -> 0
D84: 3 | E84: Other Incomes | G84: =SUM($G$22) -> 0 | I84: =SUM($G$22:I$22) -> 0 | J84: =SUM($G$22:J$22) -> 0 | K84: =SUM($G$22:K$22) -> 0 | L84: =SUM($G$22:L$22) -> 0 | M84: =SUM($G$22:M$22) -> 0 | N84: =SUM($G$22:N$22) -> 0 | O84: =SUM($G$22:O$22) -> 0 | P84: =SUM($G$22:P$22) -> 0 | ... S84: =SUM($G$22:S$22) -> 0
D85: 4 | E85: Sales & Marketing Expenses | G85: =SUM($G$25:$G$26) -> 0 | I85: =SUM($G$25:I$26) -> 0 | J85: =SUM($G$25:J$26) -> 0 | K85: =SUM($G$25:K$26) -> 0 | L85: =SUM($G$25:L$26) -> 0 | M85: =SUM($G$25:M$26) -> 0 | N85: =SUM($G$25:N$26) -> 0 | O85: =SUM($G$25:O$26) -> 0 | P85: =SUM($G$25:P$26) -> 0 | ... S85: =SUM($G$25:S$26) -> 0
D86: 5 | E86: Overhead & Operational Expenses | G86: =SUM($G$27:$G$29,$G$31) -> 0 | I86: =SUM($G$27:I$29,$G$31:I$31) -> 0 | J86: =SUM($G$27:J$29,$G$31:J$31) -> 0 | K86: =SUM($G$27:K$29,$G$31:K$31) -> 0 | L86: =SUM($G$27:L$29,$G$31:L$31) -> 0 | M86: =SUM($G$27:M$29,$G$31:M$31) -> 0 | N86: =SUM($G$27:N$29,$G$31:N$31) -> 0 | O86: =SUM($G$27:O$29,$G$31:O$31) -> 0 | P86: =SUM($G$27:P$29,$G$31:P$31) -> 0 | ... S86: =SUM($G$27:S$29,$G$31:S$31) -> 0
D87: 6 | E87: Taxes | G87: =SUM($G$30) -> 0 | I87: =SUM($G$30:I$30) -> 0 | J87: =SUM($G$30:J$30) -> 0 | K87: =SUM($G$30:K$30) -> 0 | L87: =SUM($G$30:L$30) -> 0 | M87: =SUM($G$30:M$30) -> 0 | N87: =SUM($G$30:N$30) -> 0 | O87: =SUM($G$30:O$30) -> 0 | P87: =SUM($G$30:P$30) -> 0 | ... S87: =SUM($G$30:S$30) -> 0
D88: 7 | E88: Land Cost | G88: =SUM($G$32) -> 0 | I88: =SUM($G$32:I$32) -> 0 | J88: =SUM($G$32:J$32) -> 0 | K88: =SUM($G$32:K$32) -> 0 | L88: =SUM($G$32:L$32) -> 0 | M88: =SUM($G$32:M$32) -> 0 | N88: =SUM($G$32:N$32) -> 0 | O88: =SUM($G$32:O$32) -> 0 | P88: =SUM($G$32:P$32) -> 0 | ... S88: =SUM($G$32:S$32) -> 0
D89: 8 | E89: Hard Cost | G89: =SUM($G$36) -> 0 | I89: =SUM($G$36:I$36) -> 0 | J89: =SUM($G$36:J$36) -> 0 | K89: =SUM($G$36:K$36) -> 0 | L89: =SUM($G$36:L$36) -> 0 | M89: =SUM($G$36:M$36) -> 0 | N89: =SUM($G$36:N$36) -> 0 | O89: =SUM($G$36:O$36) -> 0 | P89: =SUM($G$36:P$36) -> 0 | ... S89: =SUM($G$36:S$36) -> 0
D90: 9 | E90: Soft Cost | G90: =SUM($G$39:$G$40) -> 0 | I90: =SUM($G$39:I$40) -> 0 | J90: =SUM($G$39:J$40) -> 0 | K90: =SUM($G$39:K$40) -> 0 | L90: =SUM($G$39:L$40) -> 0 | M90: =SUM($G$39:M$40) -> 0 | N90: =SUM($G$39:N$40) -> 0 | O90: =SUM($G$39:O$40) -> 0 | P90: =SUM($G$39:P$40) -> 0 | ... S90: =SUM($G$39:S$40) -> 0
D91: 10 | E91: Purchase of Fixed Asset | G91: =SUM($G$45:$G$45) -> 0 | I91: =SUM($G$45:I$45) -> 0 | J91: =SUM($G$45:J$45) -> 0 | K91: =SUM($G$45:K$45) -> 0 | L91: =SUM($G$45:L$45) -> 0 | M91: =SUM($G$45:M$45) -> 0 | N91: =SUM($G$45:N$45) -> 0 | O91: =SUM($G$45:O$45) -> 0 | P91: =SUM($G$45:P$45) -> 0 | ... S91: =SUM($G$45:S$45) -> 0
D92: 11 | E92: Intercompany AR/AP - PTP | G92: =SUM($G$56) -> 0 | I92: =SUM($G$56:I$56) -> 0 | J92: =SUM($G$56:J$56) -> 0 | K92: =SUM($G$56:K$56) -> 0 | L92: =SUM($G$56:L$56) -> 0 | M92: =SUM($G$56:M$56) -> 0 | N92: =SUM($G$56:N$56) -> 0 | O92: =SUM($G$56:O$56) -> 0 | P92: =SUM($G$56:P$56) -> 0 | ... S92: =SUM($G$56:S$56) -> 0
D93: 12 | E93: Restricted Deposito in Banks | G93: =SUM($G$64) -> 0 | I93: =SUM($G$64:I$64) -> 0 | J93: =SUM($G$64:J$64) -> 0 | K93: =SUM($G$64:K$64) -> 0 | L93: =SUM($G$64:L$64) -> 0 | M93: =SUM($G$64:M$64) -> 0 | N93: =SUM($G$64:N$64) -> 0 | O93: =SUM($G$64:O$64) -> 0 | P93: =SUM($G$64:P$64) -> 0 | ... S93: =SUM($G$64:S$64) -> 0
D94: 13 | E94: Receipt/(Payment) Related Party Loan
D95: 14 | E95: Receipt/(Payment) for Loan - Bank (Panin & Clippan) | G95: =SUM($G$54) -> 0 | I95: =SUM($G$54:I$54) -> 0 | J95: =SUM($G$54:J$54) -> 0 | K95: =SUM($G$54:K$54) -> 0 | L95: =SUM($G$54:L$54) -> 0 | M95: =SUM($G$54:M$54) -> 0 | N95: =SUM($G$54:N$54) -> 0 | O95: =SUM($G$54:O$54) -> 0 | P95: =SUM($G$54:P$54) -> 0 | ... S95: =SUM($G$54:S$54) -> 0
D96: 15 | E96: Payments of Interest on Loans (Panin & Clippan)

Sheet BS
A1: PT PERINTIS TRINITI PROPERTI Tbk (TRIN)
A2: CONSOLIDATED OF FINANCIAL STATEMENT
A3: in IDR
A5: PROJECTED OF BALANCE SHEET | E5: ACTUAL 2025 | F5: BEST ESTIMATE | I5: BEST ESTIMATE | J5: PROJECTION | V5: TOTAL BE
A6: in IDR | E6: YTD SEP 25 | F6: 45931 | G6: 45962 | H6: 45992 | I6: 2025 | J6: 46023 | K6: 46054 | L6: 46082 | M6: 46113 | N6: 46143 | O6: 46174 | P6: 46204 | Q6: 46235 | R6: 46266 | S6: 46296 | T6: 46327 | U6: 46357 | V6: 2026
A7: ASSETS | V7: =SUM(J7:U7) -> 0
V8: =SUM(J8:U8) -> 0
B9: CURRENT ASSETS | I9: =SUM(E9:H9) -> 0 | V9: =SUM(J9:U9) -> 0
V10: =SUM(J10:U10) -> 0
C11: Cash and cash equivalent | I11: =SUM(E11:H11) -> 0 | V11: =SUM(J11:U11) -> 0
C12: Account receivable | I12: =SUM(E12:H12) -> 0 | V12: =SUM(J12:U12) -> 0
C13: Other Receivables | I13: =SUM(E13:H13) -> 0 | V13: =SUM(J13:U13) -> 0
C14: Related parties - net | I14: =SUM(E14:H14) -> 0 | V14: =SUM(J14:U14) -> 0
C15: Real Estate Assets Inventories | I15: =SUM(E15:H15) -> 0 | V15: =SUM(J15:U15) -> 0
C16: Prepaid taxes | I16: =SUM(E16:H16) -> 0 | V16: =SUM(J16:U16) -> 0
C17: Prepaid expenses | I17: =SUM(E17:H17) -> 0 | V17: =SUM(J17:U17) -> 0
C18: Advances | I18: =SUM(E18:H18) -> 0 | V18: =SUM(J18:U18) -> 0
C19: Security deposits | I19: =SUM(E19:H19) -> 0 | V19: =SUM(J19:U19) -> 0
B21: Total Current Assets | E21: =SUM(E11:E19) -> 0 | I21: =SUM(I11:I19) -> 0 | M21: =SUM(M11:M19) -> 0 | V21: =SUM(V11:V19) -> 0
B23: NON-CURRENT ASSETS | I23: =SUM(E23:H23) -> 0 | V23: =SUM(J23:U23) -> 0
V24: =SUM(J24:U24) -> 0
C25: Investment in associate | I25: =SUM(E25:H25) -> 0 | V25: =SUM(J25:U25) -> 0
C26: Investment in joint ventures | I26: =SUM(E26:H26) -> 0 | V26: =SUM(J26:U26) -> 0
C27: Investment properties | I27: =SUM(E27:H27) -> 0 | V27: =SUM(J27:U27) -> 0
C28: Fixed assets - net | I28: =SUM(E28:H28) -> 0 | V28: =SUM(J28:U28) -> 0
C29: Real Estate Assets | I29: =SUM(E29:H29) -> 0 | V29: =SUM(J29:U29) -> 0
C30: Deferred expenses | I30: =SUM(E30:H30) -> 0 | V30: =SUM(J30:U30) -> 0
C31: Others assets | I31: =SUM(E31:H31) -> 0 | V31: =SUM(J31:U31) -> 0
C32: Deferred tax assets | I32: =SUM(E32:H32) -> 0 | V32: =SUM(J32:U32) -> 0
C33: Goodwill | I33: =SUM(E33:H33) -> 0 | V33: =SUM(J33:U33) -> 0
B35: Total Non-current Assets | E35: =SUM(E23:E33) -> 0 | I35: =SUM(I23:I33) -> 0 | M35: =SUM(M23:M33) -> 0 | N35: =SUM(N23:N33) -> 0 | O35: =SUM(O23:O33) -> 0 | P35: =SUM(P23:P33) -> 0 | Q35: =SUM(Q23:Q33) -> 0 | R35: =SUM(R23:R33) -> 0 | S35: =SUM(S23:S33) -> 0 | T35: =SUM(T23:T33) -> 0 | ... V35: =SUM(V23:V33) -> 0
B37: TOTAL ASSETS | E37: =E21+E35 -> 0 | I37: =I21+I35 -> 0 | M37: =M21+M35 -> 0 | N37: =N21+N35 -> 0 | O37: =O21+O35 -> 0 | P37: =P21+P35 -> 0 | Q37: =Q21+Q35 -> 0 | R37: =R21+R35 -> 0 | S37: =S21+S35 -> 0 | T37: =T21+T35 -> 0 | ... V37: =V21+V35 -> 0
A41: PROJECTED OF BALANCE SHEET | E41: ACTUAL 2025 | G41: BEST ESTIMATE | I41: BEST ESTIMATE | J41: PROJECTION | V41: TOTAL BE
A42: in IDR | E42: YTD OKT 25 | G42: 45962 | H42: 45992 | I42: 2025 | J42: 46023 | K42: 46054 | L42: 46082 | M42: 46113 | N42: 46143 | O42: 46174 | P42: 46204 | Q42: 46235 | R42: 46266 | S42: 46296 | T42: 46327 | U42: 46357 | V42: 2026
A43: LIABILITIES AND EQUITY
B45: CURRENT LIABILITIES | I45: =SUM(E45:H45) -> 0 | V45: =SUM(J45:U45) -> 0
V46: =SUM(J46:U46) -> 0
B47: CURRENT LIABILITIES | I47: =SUM(E47:H47) -> 0 | V47: =SUM(J47:U47) -> 0
V48: =SUM(J48:U48) -> 0
C49: Accounts payables | I49: =SUM(E49:H49) -> 0 | V49: =SUM(J49:U49) -> 0
C50: Other payables Related parties | I50: =SUM(E50:H50) -> 0 | V50: =SUM(J50:U50) -> 0
C51: Other payables Third parties | I51: =SUM(E51:H51) -> 0 | V51: =SUM(J51:U51) -> 0
C52: Unearned revenues | I52: =SUM(E52:H52) -> 0 | V52: =SUM(J52:U52) -> 0
C53: Advances from customers | I53: =SUM(E53:H53) -> 0 | V53: =SUM(J53:U53) -> 0
C54: Taxes payable | I54: =SUM(E54:H54) -> 0 | V54: =SUM(J54:U54) -> 0
C55: Accrued expenses | I55: =SUM(E55:H55) -> 0 | V55: =SUM(J55:U55) -> 0
C56: Convertible bonds payable | I56: =SUM(E56:H56) -> 0 | V56: =SUM(J56:U56) -> 0
C57: Current maturity of long-term liabilities | I57: =SUM(E57:H57) -> 0 | V57: =SUM(J57:U57) -> 0
C58: Purchase of fixed assets payable CL | I58: =SUM(E58:H58) -> 0 | V58: =SUM(J58:U58) -> 0
B60: Total Current liabilities | E60: =SUM(E49:E58) -> 0 | I60: =SUM(E60:H60) -> 0 | M60: =SUM(M49:M58) -> 0 | V60: =SUM(V49:V58) -> 0
B62: NON-CURRENT LIABILITIES
C64: Long term liabilities Bank loan | I64: =SUM(E64:H64) -> 0
C65: Advances from customers Non Current | I65: =SUM(E65:H65) -> 0
C66: Joint ventures loan | I66: =SUM(E66:H66) -> 0
C67: Other payable - related parties | I67: =SUM(E67:H67) -> 0
I68: =SUM(E68:H68) -> 0
C69: Purchase of fixed assets payable NCL | I69: =SUM(E69:H69) -> 0
C70: Post-employment benefits liability | I70: =SUM(E70:H70) -> 0
B72: Total Non-current Liabilities | E72: =SUM(E64:E70) -> 0 | I72: =SUM(E72:H72) -> 0 | M72: =SUM(M64:M70) -> 0 | N72: =SUM(N64:N70) -> 0 | O72: =SUM(O64:O70) -> 0 | P72: =SUM(P64:P70) -> 0 | Q72: =SUM(Q64:Q70) -> 0 | R72: =SUM(R64:R70) -> 0 | S72: =SUM(S64:S70) -> 0 | T72: =SUM(T64:T70) -> 0 | ... V72: =SUM(V64:V70) -> 0
B74: TOTAL LIABILITES | E74: =E60+E72 -> 0 | I74: =SUM(E74:H74) -> 0 | M74: =M60+M72 -> 0 | N74: =N60+N72 -> 0 | O74: =O60+O72 -> 0 | P74: =P60+P72 -> 0 | Q74: =Q60+Q72 -> 0 | R74: =R60+R72 -> 0 | S74: =S60+S72 -> 0 | T74: =T60+T72 -> 0 | ... V74: =V60+V72 -> 0
A77: PROJECTED OF BALANCE SHEET | E77: ACTUAL 2025 | G77: BEST ESTIMATE | I77: BEST ESTIMATE | J77: PROJECTION | V77: TOTAL BE
A78: in IDR | E78: YTD OKT 25 | G78: 45962 | H78: 45992 | I78: 2025 | J78: 46023 | K78: 46054 | L78: 46082 | M78: 46113 | N78: 46143 | O78: 46174 | P78: 46204 | Q78: 46235 | R78: 46266 | S78: 46296 | T78: 46327 | U78: 46357 | V78: 2026
B81: EQUITY
D83: Authorized Capital | I83: =SUM(E83:H83) -> 0 | V83: =SUM(J83:U83) -> 0
D84: Additional paid-in capital | I84: =SUM(E84:H84) -> 0 | V84: =SUM(J84:U84) -> 0
D85: Additional paid-in capital - IPO Proceed | I85: =SUM(E85:H85) -> 0 | V85: =SUM(J85:U85) -> 0
D86: Additional paid-in capital - Right Issue Proceed | I86: =SUM(E86:H86) -> 0 | V86: =SUM(J86:U86) -> 0
D87: Treasury Stock | I87: =SUM(E87:H87) -> 0 | V87: =SUM(J87:U87) -> 0
D88: Other comprehensive income | I88: =SUM(E88:H88) -> 0 | V88: =SUM(J88:U88) -> 0
D89: Equity component in convertible bonds | I89: =SUM(E89:H89) -> 0 | V89: =SUM(J89:U89) -> 0
D90: Buy Back | I90: =SUM(E90:H90) -> 0 | V90: =SUM(J90:U90) -> 0
D91: Retained earnings | I91: =SUM(E91:H91) -> 0 | V91: =SUM(J91:U91) -> 0
C92: Total equity attributable
D93: to the owners of the parent company | E93: =SUM(E83:E91) -> 0 | G93: =SUM(G83:G91) -> 0 | H93: =SUM(H83:H91) -> 0 | I93: =SUM(I83:I91) -> 0 | J93: =SUM(J83:J91) -> 0 | K93: =SUM(K83:K91) -> 0 | L93: =SUM(L83:L91) -> 0 | M93: =SUM(M83:M91) -> 0 | N93: =SUM(N83:N91) -> 0 | ... V93: =SUM(V83:V91) -> 0
C95: Non-controlling interests
B97: Total Equity | E97: =E93+E95 -> 0 | I97: =I93+I95 -> 0 | M97: =M93+M95 -> 0 | N97: =N93+N95 -> 0 | O97: =O93+O95 -> 0 | P97: =P93+P95 -> 0 | Q97: =Q93+Q95 -> 0 | R97: =R93+R95 -> 0 | S97: =S93+S95 -> 0 | T97: =T93+T95 -> 0 | ... V97: =V93+V95 -> 0
A99: TOTAL LIABILITIES AND EQUITY | E99: =E74+E97 -> 0 | I99: =I74+I97 -> 0 | M99: =M74+M97 -> 0 | N99: =N74+N97 -> 0 | O99: =O74+O97 -> 0 | P99: =P74+P97 -> 0 | Q99: =Q74+Q97 -> 0 | R99: =R74+R97 -> 0 | S99: =S74+S97 -> 0 | T99: =T74+T97 -> 0 | ... V99: =V74+V97 -> 0
C101: Catatan Pengisian Data: | E101: =E37-E99 -> 0 | I101: =I37-I99 -> 0 | M101: =M37-M99 -> 0
B102: 1 | C102: Untuk Kolom Actual YTD Okt 2025 Diisi dengan Link ke Workpaper Actual Breakdown BS dari Sistem, jangan dengan angka value / mati
B103: 2 | C103: Untuk Nilai pada Kolom Best Estimate 2025 dan 2026 harus diisi dengan Link ke Workpaper Breakdown Proyeksi, jangan dengan angka value/ mati

Sheet PL OLD
B1: PT PERINTIS TRINITI PROPERTI Tbk.
B2: CONSOLIDATED STATEMENT OF PROFIT AND LOSS
B3: Actual and Projection
C4: YTD SEP 2025 | D4: BEST ESTIMATE 2025 | G4: BEST ESTIMATE | I4: PROJECTION 2026 | V4: BEST ESTIMATE 2022 | W4: PROJECTION 2026
D5: OCT | E5: NOV | F5: DES | G5: 2025 | I5: JAN | J5: FEB | K5: MAR | L5: APR | M5: MAY | N5: JUN | O5: JUL | P5: AUG | Q5: SEP | R5: OKT | S5: NOV | T5: DEC | V5: Q3 | W5: FULL YEAR
B6: Revenue | G6: =SUM(C6:F6) -> 0 | W6: =SUM(I6:T6) -> 0
B7: Cost of Sales & Direct Cost | G7: =SUM(C7:F7) -> 0 | W7: =SUM(I7:T7) -> 0
B8: Gross Profit | C8: =SUM(C6:C7) -> 0 | E8: =SUM(E6:E7) -> 0 | F8: =SUM(F6:F7) -> 0 | G8: =SUM(G6:G7) -> 0 | I8: =SUM(I6:I7) -> 0 | J8: =SUM(J6:J7) -> 0 | K8: =SUM(K6:K7) -> 0 | L8: =SUM(L6:L7) -> 0 | M8: =SUM(M6:M7) -> 0 | N8: =SUM(N6:N7) -> 0 | O8: =SUM(O6:O7) -> 0 | P8: =SUM(P6:P7) -> 0 | ... T8: =SUM(T6:T7) -> 0 | V8: 0 | W8: 0
B10: Selling Expenses | G10: =SUM(C10:F10) -> 0 | V10: #REF! | W10: =SUM(I10:T10) -> 0
B11: G&A Expenses | G11: =SUM(C11:F11) -> 0 | V11: #REF! | W11: =SUM(I11:T11) -> 0
B12: Other Expenses - Net | G12: =SUM(C12:F12) -> 0 | V12: #REF! | W12: =SUM(I12:T12) -> 0
B13: Share in net profit of Joint Venture | G13: =SUM(C13:F13) -> 0 | V13: #REF! | W13: =SUM(I13:T13) -> 0
B14: Share in net profit of Associate | G14: =SUM(C14:F14) -> 0 | V14: #REF! | W14: =SUM(I14:T14) -> 0
B15: Depreciation & Amortization | G15: =SUM(C15:F15) -> 0 | V15: #REF! | W15: =SUM(I15:T15) -> 0
B16: Financial Expenses | G16: =SUM(C16:F16) -> 0 | V16: #REF! | W16: =SUM(I16:T16) -> 0
B17: NET INCOME BEFORE TAX | C17: =SUM(C8:C16) -> 0 | E17: =SUM(E8:E16) -> 0 | F17: =SUM(F8:F16) -> 0 | G17: =SUM(G8:G16) -> 0 | I17: =SUM(I8:I16) -> 0 | J17: =SUM(J8:J16) -> 0 | K17: =SUM(K8:K16) -> 0 | L17: =SUM(L8:L16) -> 0 | M17: =SUM(M8:M16) -> 0 | N17: =SUM(N8:N16) -> 0 | O17: =SUM(O8:O16) -> 0 | P17: =SUM(P8:P16) -> 0 | ... T17: =SUM(T8:T16) -> 0 | V17: #REF! | W17: 0
B18: Income Tax | G18: 0 | W18: 0
B19: NET INCOME AFTER TAX | C19: =C17-C18 -> 0 | E19: =E17-E18 -> 0 | F19: =F17-F18 -> 0 | G19: =G17-G18 -> 0 | I19: =I17-I18 -> 0 | J19: =J17-J18 -> 0 | K19: =K17-K18 -> 0 | L19: =L17-L18 -> 0 | M19: =M17-M18 -> 0 | N19: =N17-N18 -> 0 | O19: =O17-O18 -> 0 | P19: =P17-P18 -> 0 | ... T19: =T17-T18 -> 0 | V19: #REF! | W19: 0
B21: EBITDA | C21: =C19-C15-C16-C18 -> 0 | E21: =E19-E15-E16-E18 -> 0 | F21: =F19-F15-F16-F18 -> 0 | G21: =G19-G15-G16-G18 -> 0 | I21: =I19-I15-I16-I18 -> 0 | J21: =J19-J15-J16-J18 -> 0 | K21: =K19-K15-K16-K18 -> 0 | L21: =L19-L15-L16-L18 -> 0 | M21: =M19-M15-M16-M18 -> 0 | N21: =N19-N15-N16-N18 -> 0 | O21: =O19-O15-O16-O18 -> 0 | P21: =P19-P15-P16-P18 -> 0 | ... T21: =T19-T15-T16-T18 -> 0 | V21: #REF! | W21: 0
B24: Catatan Pengisian Data: | G24: 0
A25: 1 | B25: Untuk Kolom Actual YTD Okt 2025 Diisi dengan Link ke Workpaper Actual Breakdown PL dari Sistem, jangan dengan angka value / mati
A26: 2 | B26: Untuk Nilai pada Kolom Best Estimate 2025 dan 2026 harus diisi dengan Link ke Workpaper Breakdown Proyeksi, jangan dengan angka value/ mati

Sheet Budget Payroll
A1: BUDGET payroll
A2: ENTITAS: | B2: Pilih Perusahaan | R2: PAYROLL
A3: PROJECT | B3: Pilih Project
A4: Division
A5: BUDGET YEARS | B5: 2027
A7: No Akun | B7: Keterangan Biaya | C7: Budget Tahun 2027 | D7: Rincian Budget | E7: 46388 | F7: 46419 | G7: 46447 | H7: 46478 | I7: 46508 | J7: 46539 | K7: 46569 | L7: 46600 | M7: 46631 | N7: 46661 | O7: 46692 | P7: 46722 | R7: Budget Tahun 2027 | S7: Rincian Budget | T7: 46388 | U7: 46419 | V7: 46447 | W7: 46478 | X7: 46508 | Y7: 46539 | Z7: 46569 | AA7: 46600 | AB7: 46631 | AC7: 46661 | AD7: 46692 | AE7: 46722
A8: 62110001 | B8: BEBAN GAJI, THR & BONUS | R8: 11368173145 | T8: 874679782 | U8: 874679782 | V8: 1260929576 | W8: 874679782 | X8: 874679782 | Y8: 880679782 | Z8: 880679782 | AA8: 880679782 | AB8: 880679782 | AC8: 880679782 | AD8: 880679782 | AE8: 1324445749
A9: 62110002 | B9: BEBAN TRANSPORTASI | R9: 80900000 | T9: 6450000 | U9: 6450000 | V9: 6450000 | W9: 6450000 | X9: 6450000 | Y9: 6950000 | Z9: 6950000 | AA9: 6950000 | AB9: 6950000 | AC9: 6950000 | AD9: 6950000 | AE9: 6950000
A10: 62110003 | B10: BEBAN TUNJANGAN TRANSPORTASI | R10: 0
A11: 62110004 | B11: BEBAN PESANGON
A12: 62110005 | B12: BEBAN UANG MAKAN
A13: 62110006 | B13: BEBAN LEMBUR
A14: 62110007 | B14: BEBAN ASURANSI
A15: 62110008 | B15: BEBAN KARYAWAN
A16: 62110009 | B16: BIAYA LEMBUR - PROJECT
A17: 62110010 | B17: BEBAN ASURANSI KESEHATAN KARYAWAN
A18: 62110011 | B18: BEBAN BPJS KESEHATAN
A19: 62110012 | B19: BIAYA TUNJANGAN LAINNYA - PROJECT
A20: 62110013 | B20: BEBAN BPJS KETENAGAKERJAAN
A21: 62110014 | B21: BEBAN BILLING RATE
A22: 62110015 | B22: BEBAN IMBALAN PASCA KERJA
... A33: 62120008 | B33: BEBAN LAINNYA
A34: TOTAL | E34: =SUM(E8:E33) -> 0 | F34: =SUM(F8:F33) -> 0 | G34: =SUM(G8:G33) -> 0 | H34: =SUM(H8:H33) -> 0 | I34: =SUM(I8:I33) -> 0 | J34: =SUM(J8:J33) -> 0 | K34: =SUM(K8:K33) -> 0 | L34: =SUM(L8:L33) -> 0 | ... P34: =SUM(P8:P33) -> 0 | R34: 13205766321 | T34: 1013510419 | U34: 1013510419 | V34: 1476065820 | W34: 1013510419 | X34: 1013510419 | Y34: 1020984694 | Z34: 1020984694 | AA34: 1020984694 | AB34: 1020984694 | AC34: 1020984694 | AD34: 1020984694 | AE34: 1549750661
E36: YTD JAN | F36: YTD FEB | G36: YTD MAR | H36: YTD APR | I36: YTD MAY | J36: YTD JUN | K36: YTD JUL | L36: YTD AUG | M36: YTD SEP | N36: YTD OCT | O36: YTD NOV | P36: YTD DEC | T36: YTD JAN | U36: YTD FEB | V36: YTD MAR | W36: YTD APR | X36: YTD MAY | Y36: YTD JUN | Z36: YTD JUL | AA36: YTD AUG | AB36: YTD SEP | AC36: YTD OCT | AD36: YTD NOV | AE36: YTD DEC
D37: TOTAL | E37: =E34 -> 0 | F37: =SUM($E$34:F$34) -> 0 | G37: =SUM($E$34:G$34) -> 0 | H37: =SUM($E$34:H$34) -> 0 | I37: =SUM($E$34:I$34) -> 0 | J37: =SUM($E$34:J$34) -> 0 | K37: =SUM($E$34:K$34) -> 0 | L37: =SUM($E$34:L$34) -> 0 | M37: =SUM($E$34:M$34) -> 0 | ... P37: =SUM($E$34:P$34) -> 0 | S37: TOTAL | T37: 1013510419 | U37: 2027020838 | V37: 3503086658 | W37: 4516597077 | X37: 5530107496 | Y37: 6551092190 | Z37: 7572076884 | AA37: 8593061578 | AB37: 9614046272 | AC37: 10635030966 | AD37: 11656015660 | AE37: 13205766321

Sheet COA one system
A1: AccountID | B1: ket
A2: 10000000 | B2: ASET
A3: 11000000 | B3: ASET LANCAR
A4: 11100000 | B4: KAS DAN BANK
A5: 11110000 | B5: KAS
A6: 11110001 | B6: KAS BESAR
A7: 11110002 | B7: KAS KECIL
A8: 11110003 | B8: KAS PROYEK
A9: 11110004 | B9: POS SILANG
A10: 11110005 | B10: CASH ADVANCE RM
A11: 11110006 | B11: KAS DAN SETARA KAS
A12: 11110007 | B12: KAS MARKETING
A13: 11110008 | B13: CASH ADVANCE MARKETING
... A1297: 91310002 | B1297: LABA KOMPREHENSIF TAHUN BERJALAN YANG DIATRIBUSIKAN

Sheet PL (ongoing link)
A1: Proyeksi Laba Rugi
A2: ENTITAS: | B2: Pilih Perusahaan
A3: PROJECT | B3: Pilih Project
A4: YEARS | B4: 2027
A7: Kode | B7: Account | C7: ACTUAL JAN - AUG 26 | D7: BE SEP - DES 26 | E7: BE FY 2026 | F7: FY 2027 | G7: 46388 | H7: 46419 | I7: 46447 | J7: 46478 | K7: 46508 | L7: 46539 | M7: 46569 | N7: 46600 | O7: 46631 | P7: 46661 | Q7: 46692 | R7: 46722
A8: 41110000 - PENJUALAN UNIT RESIDENTIAL
A9: 41110001 | B9: PENJUALAN UNIT APARTEMENT | E9: =SUM(C9:D9) -> 0 | F9: =SUM(G9:R9) -> 0
A10: 41110002 | B10: PENJUALAN UNIT CONDOVILLA | E10: =SUM(C10:D10) -> 0 | F10: =SUM(G10:R10) -> 0
A11: 41110003 | B11: PENJUALAN UNIT TOWNHOUSE | E11: =SUM(C11:D11) -> 0 | F11: =SUM(G11:R11) -> 0
A12: 41110004 | B12: PENJUALAN UNIT STUDENT VILLAGE | E12: =SUM(C12:D12) -> 0 | F12: =SUM(G12:R12) -> 0
A13: 41110005 | B13: PENJUALAN UNIT LANDED HOUSE | E13: =SUM(C13:D13) -> 0 | F13: =SUM(G13:R13) -> 0
A14: 41110006 | B14: PENJUALAN UNIT READY TO BUILD LAND / KAVLING | E14: =SUM(C14:D14) -> 0 | F14: =SUM(G14:R14) -> 0
A15: 41110007 | B15: PENJUALAN UNIT XXXX | E15: =SUM(C15:D15) -> 0 | F15: =SUM(G15:R15) -> 0
C16: =SUM(C8:C15) -> 0 | D16: =SUM(D8:D15) -> 0 | E16: =SUM(E8:E15) -> 0 | F16: =SUM(F8:F15) -> 0 | G16: =SUM(G8:G15) -> 0 | H16: =SUM(H8:H15) -> 0 | I16: =SUM(I8:I15) -> 0 | J16: =SUM(J8:J15) -> 0 | ... R16: =SUM(R8:R15) -> 0
A17: 41120000 - PENJUALAN UNIT RETAIL & COMMERCIAL
A18: 41120001 | B18: PENJUALAN UNIT OFFICE | E18: =SUM(C18:D18) -> 0 | F18: =SUM(G18:R18) -> 0
A19: 41120002 | B19: PENJUALAN UNIT SOHO | E19: =SUM(C19:D19) -> 0 | F19: =SUM(G19:R19) -> 0
A20: 41120003 | B20: PENJUALAN UNIT SHOPHOUSE/COMMERCIAL | E20: =SUM(C20:D20) -> 0 | F20: =SUM(G20:R20) -> 0
A21: 41120004 | B21: PENJUALAN UNIT BUSINESS PARK | E21: =SUM(C21:D21) -> 0 | F21: =SUM(G21:R21) -> 0
C22: =SUM(C18:C21) -> 0 | D22: =SUM(D18:D21) -> 0 | E22: =SUM(E18:E21) -> 0 | F22: =SUM(F18:F21) -> 0 | G22: =SUM(G18:G21) -> 0 | H22: =SUM(H18:H21) -> 0 | I22: =SUM(I18:I21) -> 0 | J22: =SUM(J18:J21) -> 0 | ... R22: =SUM(R18:R21) -> 0
A23: 41130000 - PENJUALAN UNIT LAINNYA
A24: 41130001 | B24: PENJUALAN UNIT LAINNYA | E24: =SUM(C24:D24) -> 0 | F24: =SUM(G24:R24) -> 0
A25: 41130002 | B25: PENJUALAN UNIT XXXX | E25: =SUM(C25:D25) -> 0 | F25: =SUM(G25:R25) -> 0
C26: =SUM(C24:C25) -> 0 | D26: =SUM(D24:D25) -> 0 | E26: =SUM(E24:E25) -> 0 | F26: =SUM(F24:F25) -> 0 | G26: =SUM(G24:G25) -> 0 | H26: =SUM(H24:H25) -> 0 | I26: =SUM(I24:I25) -> 0 | J26: =SUM(J24:J25) -> 0 | ... R26: =SUM(R24:R25) -> 0
A27: 42110000 - PENDAPATAAN SEWA UNIT RESIDENTIAL
A28: 42110001 | B28: PENDAPATAN SEWA APARTMENET | E28: =SUM(C28:D28) -> 0 | F28: =SUM(G28:R28) -> 0
A29: 42110002 | B29: PENDAPATAN SEWA CONDOVILLA | E29: =SUM(C29:D29) -> 0 | F29: =SUM(G29:R29) -> 0
A30: 42110003 | B30: PENDAPATAN SEWA TOWNHOUSE | E30: =SUM(C30:D30) -> 0 | F30: =SUM(G30:R30) -> 0
A31: 42110004 | B31: PENDAPATAN SEWA STUDENT VILLAGE | E31: =SUM(C31:D31) -> 0 | F31: =SUM(G31:R31) -> 0
A32: 42110005 | B32: PENDAPATAN SEWA LANDED HOUSE | E32: =SUM(C32:D32) -> 0 | F32: =SUM(G32:R32) -> 0
C33: =SUM(C28:C32) -> 0 | D33: =SUM(D28:D32) -> 0 | E33: =SUM(E28:E32) -> 0 | F33: =SUM(F28:F32) -> 0 | G33: =SUM(G28:G32) -> 0 | H33: =SUM(H28:H32) -> 0 | I33: =SUM(I28:I32) -> 0 | J33: =SUM(J28:J32) -> 0 | ... R33: =SUM(R28:R32) -> 0
A34: 42120000 - PENDAPATAAN SEWA UNIT RETAIL & COMMERCIAL
A35: 42110006 | B35: PENDAPATAN SEWA OFFICE | E35: =SUM(C35:D35) -> 0 | F35: =SUM(G35:R35) -> 0
A36: 42110007 | B36: PENDAPATAN SEWA SOHO | E36: =SUM(C36:D36) -> 0 | F36: =SUM(G36:R36) -> 0
A37: 42110008 | B37: PENDAPATAN SEWA SHOPHOUSE | E37: =SUM(C37:D37) -> 0 | F37: =SUM(G37:R37) -> 0
A38: 42110009 | B38: PENDAPATAN HOTEL | E38: =SUM(C38:D38) -> 0 | F38: =SUM(G38:R38) -> 0
C39: =SUM(C35:C38) -> 0 | D39: =SUM(D35:D38) -> 0 | E39: =SUM(E35:E38) -> 0 | F39: =SUM(F35:F38) -> 0 | G39: =SUM(G35:G38) -> 0 | H39: =SUM(H35:H38) -> 0 | I39: =SUM(I35:I38) -> 0 | J39: =SUM(J35:J38) -> 0 | ... R39: =SUM(R35:R38) -> 0
A40: 42210000 - KOMISI PENJUALAN
A41: 42210001 | B41: KOMISI PENJUALAN | E41: =SUM(C41:D41) -> 0 | F41: =SUM(G41:R41) -> 0
C42: =SUM(C41) -> 0 | D42: =SUM(D41) -> 0 | E42: =SUM(E41) -> 0 | F42: =SUM(F41) -> 0 | G42: =SUM(G41) -> 0 | H42: =SUM(H41) -> 0 | I42: =SUM(I41) -> 0 | J42: =SUM(J41) -> 0 | ... R42: =SUM(R41) -> 0
A43: 42310000 - PENDAPATAN JASA MANAGEMEN
A44: 42310001 | B44: JASA MANAGEMEN PENGEMBANGAN KONSTRUKSI | E44: =SUM(C44:D44) -> 0 | F44: =SUM(G44:R44) -> 0
C45: =SUM(C44) -> 0 | D45: =SUM(D44) -> 0 | E45: =SUM(E44) -> 0 | F45: =SUM(F44) -> 0 | G45: =SUM(G44) -> 0 | H45: =SUM(H44) -> 0 | I45: =SUM(I44) -> 0 | J45: =SUM(J44) -> 0 | ... R45: =SUM(R44) -> 0
A46: 51110000 - BEBAN POKOK PENJUALAN RESIDENTIAL
A47: 51110001 | B47: BEBAN POKOK PENJUALAN UNIT APARTMENT | E47: =SUM(C47:D47) -> 0 | F47: =SUM(G47:R47) -> 0
A48: 51110002 | B48: BEBAN POKOK PENJUALAN UNIT CONDOVILLA | E48: =SUM(C48:D48) -> 0 | F48: =SUM(G48:R48) -> 0
A49: 51110003 | B49: BEBAN POKOK PENJUALAN UNIT TOWNHOUSE | E49: =SUM(C49:D49) -> 0 | F49: =SUM(G49:R49) -> 0
A50: 51110004 | B50: BEBAN POKOK PENJUALAN UNIT STUDENT VILLAGE | E50: =SUM(C50:D50) -> 0 | F50: =SUM(G50:R50) -> 0
A51: 51110005 | B51: BEBAN POKOK PENJUALAN UNIT LANDED HOUSE | E51: =SUM(C51:D51) -> 0 | F51: =SUM(G51:R51) -> 0
A52: 51110006 | B52: BEBAN POKOK PENJUALAN UNIT READY TO BUILD LAND / KAVLING | E52: =SUM(C52:D52) -> 0 | F52: =SUM(G52:R52) -> 0
C53: =SUM(C47:C52) -> 0 | D53: =SUM(D47:D52) -> 0 | E53: =SUM(E47:E52) -> 0 | F53: =SUM(F47:F52) -> 0 | G53: =SUM(G47:G52) -> 0 | H53: =SUM(H47:H52) -> 0 | I53: =SUM(I47:I52) -> 0 | J53: =SUM(J47:J52) -> 0 | ... R53: =SUM(R47:R52) -> 0
A54: 51120000 - BEBAN POKOK PENJUALAN RETAIL & COMMERCIAL
A55: 51120001 | B55: BEBAN POKOK PENJUALAN UNIT OFFICE | E55: =SUM(C55:D55) -> 0 | F55: =SUM(G55:R55) -> 0
A56: 51120002 | B56: BEBAN POKOK PENJUALAN UNIT SOHO | E56: =SUM(C56:D56) -> 0 | F56: =SUM(G56:R56) -> 0
A57: 51120003 | B57: BEBAN POKOK PENJUALAN UNIT SHOPHOUSE | E57: =SUM(C57:D57) -> 0 | F57: =SUM(G57:R57) -> 0
A58: 51120004 | B58: BEBAN POKOK PENJUALAN UNIT XXXX | E58: =SUM(C58:D58) -> 0 | F58: =SUM(G58:R58) -> 0
C59: =SUM(C55:C58) -> 0 | D59: =SUM(D55:D58) -> 0 | E59: =SUM(E55:E58) -> 0 | F59: =SUM(F55:F58) -> 0 | G59: =SUM(G55:G58) -> 0 | H59: =SUM(H55:H58) -> 0 | I59: =SUM(I55:I58) -> 0 | J59: =SUM(J55:J58) -> 0 | ... R59: =SUM(R55:R58) -> 0
A60: 51130000 - BEBAN POKOK PENJUALAN LAINNYA
A61: 51130001 | B61: BEBAN POKOK PENJUALAN UNIT LAINNYA | E61: =SUM(C61:D61) -> 0 | F61: =SUM(G61:R61) -> 0
C62: =SUM(C61) -> 0 | D62: =SUM(D61) -> 0 | E62: =SUM(E61) -> 0 | F62: =SUM(F61) -> 0 | G62: =SUM(G61) -> 0 | H62: =SUM(H61) -> 0 | I62: =SUM(I61) -> 0 | J62: =SUM(J61) -> 0 | ... R62: =SUM(R61) -> 0
A63: 51210000 - BEBAN LANGSUNG KOMISI MARKETING
A64: 51210001 | B64: MARKETING IN-HOUSE | E64: =SUM(C64:D64) -> 0 | F64: =SUM(G64:R64) -> 0
A65: 51210002 | B65: MARKETING AGENT | E65: =SUM(C65:D65) -> 0 | F65: =SUM(G65:R65) -> 0
C66: =SUM(C64:C65) -> 0 | D66: =SUM(D64:D65) -> 0 | E66: =SUM(E64:E65) -> 0 | F66: =SUM(F64:F65) -> 0 | G66: =SUM(G64:G65) -> 0 | H66: =SUM(H64:H65) -> 0 | I66: =SUM(I64:I65) -> 0 | J66: =SUM(J64:J65) -> 0 | ... R66: =SUM(R64:R65) -> 0
A67: LABA KOTOR | C67: =SUM(C16,C22,C26,C33,C39,C42,C45)-SUM(C53,C59,C62,C66) -> 0 | D67: =SUM(D16,D22,D26,D33,D39,D42,D45)-SUM(D53,D59,D62,D66) -> 0 | E67: =SUM(E16,E22,E26,E33,E39,E42,E45)-SUM(E53,E59,E62,E66) -> 0 | F67: =SUM(F16,F22,F26,F33,F39,F42,F45)-SUM(F53,F59,F62,F66) -> 0 | G67: =SUM(G16,G22,G26,G33,G39,G42,G45)-SUM(G53,G59,G62,G66) -> 0 | H67: =SUM(H16,H22,H26,H33,H39,H42,H45)-SUM(H53,H59,H62,H66) -> 0 | I67: =SUM(I16,I22,I26,I33,I39,I42,I45)-SUM(I53,I59,I62,I66) -> 0 | J67: =SUM(J16,J22,J26,J33,J39,J42,J45)-SUM(J53,J59,J62,J66) -> 0 | ... R67: =SUM(R16,R22,R26,R33,R39,R42,R45)-SUM(R53,R59,R62,R66) -> 0
A69: 61110000 - BEBAN KOMISI PENJUALAN
A70: 61110001 | B70: BEBAN KOMISI IN-HOUSE | E70: =SUM(C70:D70) -> 0 | F70: =SUM(G70:R70) -> 0
A71: 61110002 | B71: BEBAN KOMISI AGENT | E71: =SUM(C71:D71) -> 0 | F71: =SUM(G71:R71) -> 0
A72: 61110003 | B72: BONUS PENJUALAN MARKETING | E72: =SUM(C72:D72) -> 0 | F72: =SUM(G72:R72) -> 0
A73: 61110004 | B73: BEBAN KOMISI BUYER GET BUYER | E73: =SUM(C73:D73) -> 0 | F73: =SUM(G73:R73) -> 0
C74: =SUM(C70:C73) -> 0 | D74: =SUM(D70:D73) -> 0 | E74: =SUM(E70:E73) -> 0 | F74: =SUM(F70:F73) -> 0 | G74: =SUM(G70:G73) -> 0 | H74: =SUM(H70:H73) -> 0 | I74: =SUM(I70:I73) -> 0 | J74: =SUM(J70:J73) -> 0 | ... R74: =SUM(R70:R73) -> 0
A75: 61210000 - BEBAN MARKETING DAN PROMOSI
A76: 61210001 | B76: MEDIA DIGITAL / ONLINE (WEBSITE, TV, RADIO, M-ADS) | E76: =SUM(C76:D76) -> 0 | F76: =SUM(G76:R76) -> 0
A77: 61210002 | B77: MEDIA CETAK (MAJALAH, KORAN) | E77: =SUM(C77:D77) -> 0 | F77: =SUM(G77:R77) -> 0
A78: 61210003 | B78: PERCETAKAN BROSUR, SPANDUK, KATALOG | E78: =SUM(C78:D78) -> 0 | F78: =SUM(G78:R78) -> 0
A79: 61210004 | B79: SIGNAGE | E79: =SUM(C79:D79) -> 0 | F79: =SUM(G79:R79) -> 0
A80: 61210005 | B80: BILLBOARD | E80: =SUM(C80:D80) -> 0 | F80: =SUM(G80:R80) -> 0
A81: 61210006 | B81: EVENTS & EXIBITION | E81: =SUM(C81:D81) -> 0 | F81: =SUM(G81:R81) -> 0
A82: 61210007 | B82: ROADSHOW | E82: =SUM(C82:D82) -> 0 | F82: =SUM(G82:R82) -> 0
A83: 61210008 | B83: TRANSPORTASI DAN AKOMODASI | E83: =SUM(C83:D83) -> 0 | F83: =SUM(G83:R83) -> 0
A84: 61210009 | B84: MAKET & SUPPORT | E84: =SUM(C84:D84) -> 0 | F84: =SUM(G84:R84) -> 0
A85: 61210010 | B85: SHOW UNIT | E85: =SUM(C85:D85) -> 0 | F85: =SUM(G85:R85) -> 0
A86: 61210011 | B86: REWARD | E86: =SUM(C86:D86) -> 0 | F86: =SUM(G86:R86) -> 0
A87: 61210012 | B87: BEBAN MARKETING PROMOSI LAINNYA | E87: =SUM(C87:D87) -> 0 | F87: =SUM(G87:R87) -> 0
A88: 61210013 | B88: BEBAN CASH BACK PEMBAYARAN | E88: =SUM(C88:D88) -> 0 | F88: =SUM(G88:R88) -> 0
C89: =SUM(C76:C88) -> 0 | D89: =SUM(D76:D88) -> 0 | E89: =SUM(E76:E88) -> 0 | F89: =SUM(F76:F88) -> 0 | G89: =SUM(G76:G88) -> 0 | H89: =SUM(H76:H88) -> 0 | I89: =SUM(I76:I88) -> 0 | J89: =SUM(J76:J88) -> 0 | ... R89: =SUM(R76:R88) -> 0
A90: 62110000 - BEBAN GAJI
A91: 62110001 | B91: BEBAN GAJI, THR & BONUS | E91: =SUM(C91:D91) -> 0 | F91: =SUM(G91:R91) -> 0
A92: 62110002 | B92: BEBAN TRANSPORTASI | E92: =SUM(C92:D92) -> 0 | F92: =SUM(G92:R92) -> 0
A93: 62110003 | B93: BEBAN UANG MAKAN | E93: =SUM(C93:D93) -> 0 | F93: =SUM(G93:R93) -> 0
A94: 62110004 | B94: BEBAN LEMBUR | E94: =SUM(C94:D94) -> 0 | F94: =SUM(G94:R94) -> 0
A95: 62110005 | B95: BEBAN ASURANSI | E95: =SUM(C95:D95) -> 0 | F95: =SUM(G95:R95) -> 0
A96: 62110006 | B96: BEBAN BPJS KESEHATAN | E96: =SUM(C96:D96) -> 0 | F96: =SUM(G96:R96) -> 0
A97: 62110007 | B97: BEBAN BPJS KETENAGAKERJAAN | E97: =SUM(C97:D97) -> 0 | F97: =SUM(G97:R97) -> 0
A98: 62110008 | B98: BEBAN IMBALAN PASCA KERJA | E98: =SUM(C98:D98) -> 0 | F98: =SUM(G98:R98) -> 0
C99: =SUM(C91:C98) -> 0 | D99: =SUM(D91:D98) -> 0 | E99: =SUM(E91:E98) -> 0 | F99: =SUM(F91:F98) -> 0 | G99: =SUM(G91:G98) -> 0 | H99: =SUM(H91:H98) -> 0 | I99: =SUM(I91:I98) -> 0 | J99: =SUM(J91:J98) -> 0 | ... R99: =SUM(R91:R98) -> 0
A100: 62120000 - BEBAN TUNJANGAN KARYAWAN
A101: 62120001 | B101: BEBAN PELATIHAN & SEMINAR | E101: =SUM(C101:D101) -> 0 | F101: =SUM(G101:R101) -> 0
A102: 62120002 | B102: BEBAN PEREKRUTAN KARYAWAN | E102: =SUM(C102:D102) -> 0 | F102: =SUM(G102:R102) -> 0
A103: 62120003 | B103: BEBAN GATHERING, OUTING, TEAM BUILDING | E103: =SUM(C103:D103) -> 0 | F103: =SUM(G103:R103) -> 0
...
